Workbook
Name coeff_d_02913344_4cc8_4f3c_b5cd_7d7e9a7f0abe: #REF!
Name coeff_d_345d0e54_e172_4e98_9782_d533d7cc86fc: #REF!
Name OTRO1: #REF!
Name OTRO3: #REF!

Sheet PDM
A1: EJE | B1: PONDERADOR EJE | C1: NOMBRE DE SECTOR | D1: SECTOR MGA | E1: PROGRAMA MGA | F1: COD,.INT. PROGRAMA | G1: PROGRAMA PDT | H1: COD SUBPROGRAMA | I1: COD. INT, SUBPROGRAMA | J1: SUBPROGRAMA | K1: COD. INT. MR | L1: META DE RESULTADO | M1: INDICADOR DE RESULTADO | N1: L.B | O1: PRODUCTO MGA | P1: BPIN | Q1: NOMBRE DEL PROYECTO | R1: COD META PRODUCTO | S1: META DE PRODUCTO | T1: L.B | U1: UNIDAD DE MEDIDA | V1: TENDENCIA INDICADOR | W1: INDICADOR | X1: RESPONSABLE | Y1: PACTO POR LA NIŃEZ | Z1: VALOR ESPERADO CUATRIENIO | AA1: % TOTAL EJEJCUTADO 2024 VS CUATRIENIO | AB1: % TOTAL EJECUTADO 2025 VS CUATRIENIO | AC1: % TOTAL EJECUTADO 2026 VS CUATRIENIO | AD1: % TOTAL EJECUTADO 2027 VS CUATRIENIO | AE1: PORCENTAJE TOTAL PDM AVANCE CUATRIENIO | AF1: VALOR ESPERADO 2024 | AG1: VALOR ESPERADO 2025 | AH1: VALOR ESPERADO 2026 | AI1: VALOR ESPERADO 2027 | AJ1: T1. PLANEADO 2024 | AK1: T1. EJECUTADO 2024 | AL1: T2. PLANEADO 2024 | AM1: T2. EJECUTADO 2024 | AN1: T3. PLANEADO 2024 | AO1: T3. EJECUTADO 2024 | AP1: T4. PLANEADO 2024 | AQ1: T.4 EJECUTADO 2024 | AR1: TOTAL PLANEADO 2024 | AS1: TOTAL EJECUTADO 2024 | AT1: AVANCE 2024 | AU1: % TOTAL PLANEADO 2024 | AV1: % TOTAL AVANCE 2024 | AW1: ESTADO PROGRAMADO-NO PROGRAMADO | AX1: SOPORTES DE CUMPLIMIENTO 2024 | AY1: T1. PLANEADO 2025 | AZ1: T1. EJECUTADO 2025 | BA1: T2. PLANEADO 2025 | BB1: T2. EJECUTADO 2025 | BC1: T3. PLANEADO 2025 | BD1: T3. EJECUTADO 2025 | BE1: T4. PLANEADO 2025 | BF1: T.4 EJECUTADO 2025 | BG1: TOTAL PLANEADO 2025 | BH1: TOTAL EJECUTADO 2025 | BI1: AVANCE 2025 | BJ1: % TOTAL PLANEADO 2025 | BK1: % TOTAL AVANCE 2025 | BL1: ESTADO PROGRAMADO-NO PROGRAMADO | BM1: SOPORTES DE CUMPLIMIENTO 2025 | BN1: APROPIACION DEFINITIVA 2025 | BO1: COMPROMISOS 2025 | BP1: APROPIACION 2024 | BQ1: COMPROMISOS 2024 | BR1: TOTAL ASIGNADO | BS1: TOTAL COMPROMISOS | BT1: % EJECUCIÓN FINANCIERA | BU1: APROPIACION INICIAL 2025 | BV1: APROPIACION DEFINITIVA 2025 | BW1: COMPROMISOS 2025 | BX1: PAGOS 2025 | BY1: % EJECUCION 2025 | BZ1: 2024 PLAN FINANCIERO PDM | CA1: 2025 PLAN FINANCIERO PDM | CB1: 2026 PLAN FINANCIERO PDM | CC1: 2027 PLAN FINANCIERO PDM | CD1: TOTALES PLAN FINANCIERO PDM
A2: Eje 1. Ambiente, Conectividad y Ordenamiento y servicios públicos | B2: 0.235 | D2: 32 | E2: 3204 | F2: 1 | G2: Programa Integral de Sostenibilidad y Educación Ambiental (PISEA) (Gestión Intergal del recurso hídrico) | H2: 0900 | I2: 1.1 | J2: CUSOR- Conservación y Uso Sostenible de los Recursos Hídricos | K2: 1.1.1 | L2: Implementar al 100% las acciones integrales para la protección de áreas de interés hídrico, caracterización y conservación del recurso hídrico y la ejecución de políticas efectivas para la gestión del cambio climático | M2: Porcentaje de acciones integrales para la protección de áreas de interés hídrico, caracterización y conservación del recurso hídrico implementadas | N2: 0 | O2: 3204001 | P2: 2024257990001 | Q2: Implementación de la educacion, sensibilizacion ambiental y Uso Sostenible de los Recursos Hídricos en el Municipio de Tenjo Cundinamarca | R2: 1 | S2: Dar cumplimiento a las estrategias enmarcadas en el art. 111 de la Ley 99 de 1993 "Adquisición o mantenimiento de áreas de interés para acueductos municipales, distritales y regionales" | T2: 2 Estrategias (Reforestación y manteniniento) 880 has DMI 308 Has de propiedad del municipio | U2: Número | V2: I | W2: Actividades desarrolladas | X2: Secretaría de Desarrollo Económico y Medio Ambiente o quien haga sus veces | Z2: =SUM(AF2:AI2) -> 4 | AA2: =AS2/Z2 -> 0.25 | AB2: =BI2/Z2 -> 0.2125 | AE2: =SUMPRODUCT(AA2:AD2, {0.15,0.35,0.35,0.15}) -> 0.111875 | AF2: 1 | AG2: 1 | AH2: 1 | AI2: 1 | AN2: 0.7 | AO2: 0.7 | AP2: 0.3 | AQ2: 0.3 | AR2: =(AJ2+AL2+AN2+AP2) -> 1 | AS2: =(AK2+AM2+AO2+AQ2) -> 1 | AT2: =AS2/AR2 -> 1 | AU2: =MIN((AR2 /AR2) * 100, 100) & "%" -> 100% | AV2: =IF(AR2=0, 0, AS2/AR2) -> 1 | AW2: P | AX2: META 1 | AY2: 0.15 | AZ2: 0.15 | BA2: 0.35 | BB2: 0.35 | BC2: 0.35 | BD2: 0.35 | BE2: 0.15 | BG2: =(AY2+BA2+BC2+BE2) -> 1 | BH2: =(AZ2+BB2+BD2+BF2) -> 0.85 | BI2: =BH2/BG2 -> 0.85 | BJ2: =MIN((BG2 /BG2) * 100, 100) & "%" -> 100% | BK2: =IF(BG2=0, 0, BH2/BG2) -> 0.85 | BL2: P | BM2: Meta 1.docx | BN2: 3404125267 | BO2: 205200000 | BP2: 52700000 | BQ2: 52700000 | BR2: =+BN2+BP2 -> 3456825267 | BS2: =+BO2+BQ2 -> 257900000 | BT2: =IFERROR(BS2/BR2, "") -> 0.074606027 | BU2: 924152848 | BV2: 3404125267 | BW2: 1405200000 | BX2: 148860000 | BY2: =IFERROR(BW2/BV2, "") -> 0.41279327 | BZ2: 913789867 | CA2: 950341565 | CB2: 993344662 | CC2: 1035710435 | CD2: 3893186529
A3: Eje 1. Ambiente, Conectividad y Ordenamiento y servicios públicos | B3: 0.235 | D3: 32 | E3: 3204 | F3: 1 | G3: Programa Integral de Sostenibilidad y Educación Ambiental (PISEA) (Gestión Intergal del recurso hídrico) | H3: 0900 | I3: 1.1 | J3: CUSOR- Conservación y Uso Sostenible de los Recursos Hídricos | K3: 1.1.1 | L3: Implementar al 100% las acciones integrales para la protección de áreas de interés hídrico, caracterización y conservación del recurso hídrico y la ejecución de políticas efectivas para la gestión del cambio climático | M3: Porcentaje de acciones integrales para la protección de áreas de interés hídrico, caracterización y conservación del recurso hídrico implementadas | N3: 0 | O3: 3204002 | P3: 2024257990001 | Q3: Implementación de la educacion, sensibilizacion ambiental y Uso Sostenible de los Recursos Hídricos en el Municipio de Tenjo Cundinamarca | R3: 2 | S3: Implementar 1 estrategia para la caracterización y conservación del recurso hídrico del municipio en el marco del POMCA del Río Bogotá y de la Sentencia del Río Bogotá | T3: 0 | U3: Número | V3: I | W3: Número de actividades realizadas | X3: Secretaría de Desarrollo Económico y Medio Ambiente o quien haga sus veces | Z3: =SUM(AF3:AI3) -> 4 | AA3: =AS3/Z3 -> 0.2475 | AB3: =BI3/Z3 -> 0.2125 | AE3: =SUMPRODUCT(AA3:AD3, {0.15,0.35,0.35,0.15}) -> 0.1115 | AF3: 1 | AG3: 1 | AH3: 1 | AI3: 1 | AN3: 0.65 | AO3: 0.65 | AP3: 0.35 | AQ3: 0.34 | AR3: =(AJ3+AL3+AN3+AP3) -> 1 | AS3: =(AK3+AM3+AO3+AQ3) -> 0.99 | AT3: =AS3/AR3 -> 0.99 | AU3: =MIN((AR3 /AR3) * 100, 100) & "%" -> 100% | AV3: =IF(AR3=0, 0, AS3/AR3) -> 0.99 | AW3: P | AX3: META 2 | AY3: 0.15 | AZ3: 0.15 | BA3: 0.35 | BB3: 0.35 | BC3: 0.35 | BD3: 0.35 | BE3: 0.15 | BG3: =(AY3+BA3+BC3+BE3) -> 1 | BH3: =(AZ3+BB3+BD3+BF3) -> 0.85 | BI3: =BH3/BG3 -> 0.85 | BJ3: =MIN((BG3 /BG3) * 100, 100) & "%" -> 100% | BK3: =IF(BG3=0, 0, BH3/BG3) -> 0.85 | BL3: P | BM3: Meta 2.docx | BN3: 419330408 | BO3: 151546432 | BP3: 91418093 | BQ3: 91418093 | BR3: =+BN3+BP3 -> 510748501 | BS3: =+BO3+BQ3 -> 242964525 | BT3: =IFERROR(BS3/BR3, "") -> 0.47570286 | BU3: 315064557 | BV3: 419330408 | BW3: 198752519 | BX3: 147625458 | BY3: =IFERROR(BW3/BV3, "") -> 0.47397593 | BZ3: 210000000 | CA3: 214200000 | CB3: 218484000 | CC3: 225038520 | CD3: 867722520
A4: Eje 1. Ambiente, Conectividad y Ordenamiento y servicios públicos | B4: 0.235 | D4: 32 | E4: 3204 | F4: 1 | G4: Programa Integral de Sostenibilidad y Educación Ambiental (PISEA) (Gestión Intergal del recurso hídrico) | H4: 0900 | I4: 1.1 | J4: CUSOR- Conservación y Uso Sostenible de los Recursos Hídricos | K4: 1.1.1 | L4: Implementar al 100% las acciones integrales para la protección de áreas de interés hídrico, caracterización y conservación del recurso hídrico y la ejecución de políticas efectivas para la gestión del cambio climático | M4: Porcentaje de acciones integrales para la protección de áreas de interés hídrico, caracterización y conservación del recurso hídrico implementadas | N4: 0 | O4: 3204006 | P4: 2024257990001 | Q4: Implementación de la educacion, sensibilizacion ambiental y Uso Sostenible de los Recursos Hídricos en el Municipio de Tenjo Cundinamarca | R4: 3 | S4: Implementar 4 líneas estratégicas de la política pública de gestión integral del cambio climático departamental (ORDENANZA No. 0112/2023) | T4: 0 | U4: Número | V4: I | W4: 4 líneas estratégicas implementadas | X4: Secretaría de Desarrollo Económico y Medio Ambiente o quien haga sus veces | Z4: =SUM(AF4:AI4) -> 4 | AA4: =AS4/Z4 -> 0.25 | AB4: =BI4/Z4 -> 0.11842105 | AE4: =SUMPRODUCT(AA4:AD4, {0.15,0.35,0.35,0.15}) -> 0.078947368 | AF4: 1 | AG4: 1 | AH4: 1 | AI4: 1 | AN4: 0.2 | AO4: 0.2 | AP4: 0.8 | AQ4: 0.8 | AR4: =(AJ4+AL4+AN4+AP4) -> 1 | AS4: =(AK4+AM4+AO4+AQ4) -> 1 | AT4: =AS4/AR4 -> 1 | AU4: =MIN((AR4 /AR4) * 100, 100) & "%" -> 100% | AV4: =IF(AR4=0, 0, AS4/AR4) -> 1 | AW4: P | AX4: META 3 | AY4: 0.15 | AZ4: 0 | BA4: 0.1 | BB4: 0.1 | BC4: 0.35 | BD4: 0.35 | BE4: 0.35 | BG4: =(AY4+BA4+BC4+BE4) -> 0.95 | BH4: =(AZ4+BB4+BD4+BF4) -> 0.45 | BI4: =BH4/BG4 -> 0.47368421 | BJ4: =MIN((BG4 /BG4) * 100, 100) & "%" -> 100% | BK4: =IF(BG4=0, 0, BH4/BG4) -> 0.47368421 | BL4: P | BM4: Meta 3.docx | BN4: 234094874 | BO4: 0 | BP4: 183385555 | BQ4: 183385555 | BR4: =+BN4+BP4 -> 417480429 | BS4: =+BO4+BQ4 -> 183385555 | BT4: =IFERROR(BS4/BR4, "") -> 0.43926743 | BU4: 130000000 | BV4: 234094874 | BW4: 0 | BX4: 0 | BY4: =IFERROR(BW4/BV4, "") -> 0 | BZ4: 159000000 | CA4: 162180000 | CB4: 165423600 | CC4: 170386308 | CD4: 656989908
A5: Eje 1. Ambiente, Conectividad y Ordenamiento y servicios públicos | B5: 0.235 | D5: 32 | E5: 3204 | F5: 1 | G5: Programa Integral de Sostenibilidad y Educación Ambiental (PISEA) (Gestión Intergal del recurso hídrico) | H5: 0900 | I5: 1.2 | J5: Es el Tiempo de la Educación y Sensibilización Ambiental | K5: 1.1.2 | L5: Implementar en 25% la Política Pública de Educación Ambiental, actualizando y ejecutando completamente el Plan Institucional de Gestión Ambiental (PIGA), y fomentando la participación de la comunidad en la preservación y valoración de los recursos naturales a través de programas educativos | M5: Porcentaje de política de Educación Ambiental implementado | N5: 0 | O5: 3204001 | P5: 2024257990001 | Q5: Implementación de la educacion, sensibilizacion ambiental y Uso Sostenible de los Recursos Hídricos en el Municipio de Tenjo Cundinamarca | R5: 4 | S5: Formular e implementar al 25% la Política Pública de Educación Ambiental | T5: 0 | U5: Porcentaje | V5: I | W5: 1 política Pública formulada e implementada al 25% | X5: Secretaría de Desarrollo Económico y Medio Ambiente o quien haga sus veces | Z5: =SUM(AF5:AI5) -> 0.25 | AA5: =AS5/Z5 -> 0.2 | AB5: =BI5/Z5 -> 3.2 | AE5: =SUMPRODUCT(AA5:AD5, {0.15,0.35,0.35,0.15}) -> 1.15 | AF5: 0.04 | AG5: 0.08 | AH5: 0.1 | AI5: 0.03 | AN5: 0.04 | AO5: 0.04 | AP5: 0.04 | AQ5: 0.01 | AR5: =(AJ5+AL5+AN5+AP5) -> 0.08 | AS5: =(AK5+AM5+AO5+AQ5) -> 0.05 | AT5: =AS5/AR5 -> 0.625 | AU5: =MIN((AR5 /AR5) * 100, 100) & "%" -> 100% | AV5: =IF(AR5=0, 0, AS5/AR5) -> 0.625 | AW5: P | AX5: META 4 | AY5: 0.05 | AZ5: 0.05 | BA5: 0.1 | BB5: 0.1 | BC5: 0.05 | BD5: 0.05 | BE5: 0.05 | BG5: =(AY5+BA5+BC5+BE5) -> 0.25 | BH5: =(AZ5+BB5+BD5+BF5) -> 0.2 | BI5: =BH5/BG5 -> 0.8 | BJ5: =MIN((BG5 /BG5) * 100, 100) & "%" -> 100% | BK5: =IF(BG5=0, 0, BH5/BG5) -> 0.8 | BL5: P | BM5: Meta 4.docx | BN5: 100000000 | BO5: 0 | BP5: 0 | BQ5: 0 | BR5: =+BN5+BP5 -> 100000000 | BS5: =+BO5+BQ5 -> 0 | BT5: =IFERROR(BS5/BR5, "") -> 0 | BU5: 60000000 | BV5: 100000000 | BW5: 60000000 | BX5: 26333332 | BY5: =IFERROR(BW5/BV5, "") -> 0.6 | BZ5: 45000000 | CA5: 45900000 | CB5: 46818000 | CC5: 48222540 | CD5: 185940540
A6: Eje 1. Ambiente, Conectividad y Ordenamiento y servicios públicos | B6: 0.235 | D6: 32 | E6: 3204 | F6: 1 | G6: Programa Integral de Sostenibilidad y Educación Ambiental (PISEA) (Gestión Intergal del recurso hídrico) | H6: 0900 | I6: 1.2 | J6: Es el Tiempo de la Educación y Sensibilización Ambiental | K6: 1.1.2 | L6: Implementar en 25% la Política Pública de Educación Ambiental, actualizando y ejecutando completamente el Plan Institucional de Gestión Ambiental (PIGA), y fomentando la participación de la comunidad en la preservación y valoración de los recursos naturales a través de programas educativos | M6: Porcentaje de política de Educación Ambiental implementado | N6: 0 | O6: 3204001 | P6: 2024257990001 | Q6: Implementación de la educacion, sensibilizacion ambiental y Uso Sostenible de los Recursos Hídricos en el Municipio de Tenjo Cundinamarca | R6: 5 | S6: Actualizar e implementar el Plan Institucional de Gestión Ambiental PIGA | T6: 1 | U6: Número | V6: M | W6: 1 plan actualizado e implementado | X6: Secretaría de Desarrollo Económico y Medio Ambiente o quien haga sus veces | Z6: =SUM(AF6:AI6) -> 1 | AA6: =AS6/Z6 -> 1 | AB6: =BI6/Z6 -> 1 | AE6: =SUMPRODUCT(AA6:AD6, {0.15,0.35,0.35,0.15}) -> 0.5 | AF6: 0.1 | AG6: 0.4 | AH6: 0.4 | AI6: 0.1 | AN6: 0.7 | AO6: 0.7 | AP6: 0.3 | AQ6: 0.3 | AR6: =(AJ6+AL6+AN6+AP6) -> 1 | AS6: =(AK6+AM6+AO6+AQ6) -> 1 | AT6: =AS6/AR6 -> 1 | AU6: =MIN((AR6 /AR6) * 100, 100) & "%" -> 100% | AV6: =IF(AR6=0, 0, AS6/AR6) -> 1 | AW6: P | AX6: META 5 | AY6: 0.1 | AZ6: 0.1 | BA6: 0.1 | BB6: 0.1 | BC6: 0.2 | BD6: 0.2 | BE6: 0 | BG6: =(AY6+BA6+BC6+BE6) -> 0.4 | BH6: =(AZ6+BB6+BD6+BF6) -> 0.4 | BI6: =BH6/BG6 -> 1 | BJ6: =MIN((BG6 /BG6) * 100, 100) & "%" -> 100% | BK6: =IF(BG6=0, 0, BH6/BG6) -> 1 | BL6: P | BM6: Meta 5.docx | BN6: 39048521 | BO6: 34240000 | BP6: 11778450 | BQ6: 11778450 | BR6: =+BN6+BP6 -> 50826971 | BS6: =+BO6+BQ6 -> 46018450 | BT6: =IFERROR(BS6/BR6, "") -> 0.9053943 | BU6: 35826971 | BV6: 39048521 | BW6: 34240000 | BX6: 24853333 | BY6: =IFERROR(BW6/BV6, "") -> 0.87685779 | BZ6: 60000000 | CA6: 61200000 | CB6: 62424000 | CC6: 64296720 | CD6: 247920720
A7: Eje 1. Ambiente, Conectividad y Ordenamiento y servicios públicos | B7: 0.235 | D7: 32 | E7: 3204 | F7: 1 | G7: Programa Integral de Sostenibilidad y Educación Ambiental (PISEA) (Gestión Intergal del recurso hídrico) | H7: 0900 | I7: 1.2 | J7: Es el Tiempo de la Educación y Sensibilización Ambiental | K7: 1.1.2 | L7: Implementar en 25% la Política Pública de Educación Ambiental, actualizando y ejecutando completamente el Plan Institucional de Gestión Ambiental (PIGA), y fomentando la participación de la comunidad en la preservación y valoración de los recursos naturales a través de programas educativos | M7: Porcentaje de política de Educación Ambiental implementado | N7: 0 | O7: 3204049 | P7: 2024257990001 | Q7: Implementación de la educacion, sensibilizacion ambiental y Uso Sostenible de los Recursos Hídricos en el Municipio de Tenjo Cundinamarca | R7: 6 | S7: Ejecutar un modelo de sensibilización de potencialidades ambientales involucrando la comunidad educativa, grupos ambientalistas, JAC y comunidad en general | T7: 0 | U7: Número | V7: I | W7: Modelo ejecutado | X7: Secretaría de Desarrollo Económico y Medio Ambiente o quien haga sus veces | Z7: =SUM(AF7:AI7) -> 1 | AA7: =AS7/Z7 -> 1 | AB7: =BI7/Z7 -> 0.425 | AE7: =SUMPRODUCT(AA7:AD7, {0.15,0.35,0.35,0.15}) -> 0.29875 | AF7: 0.1 | AG7: 0.4 | AH7: 0.4 | AI7: 0.1 | AN7: 0.5 | AO7: 0.5 | AP7: 0.5 | AQ7: 0.5 | AR7: =(AJ7+AL7+AN7+AP7) -> 1 | AS7: =(AK7+AM7+AO7+AQ7) -> 1 | AT7: =AS7/AR7 -> 1 | AU7: =MIN((AR7 /AR7) * 100, 100) & "%" -> 100% | AV7: =IF(AR7=0, 0, AS7/AR7) -> 1 | AW7: P | AX7: META 6 | AY7: 0.1 | AZ7: 0.1 | BA7: 0.1 | BB7: 0.05 | BC7: 0.1 | BD7: 0.02 | BE7: 0.1 | BG7: =(AY7+BA7+BC7+BE7) -> 0.4 | BH7: =(AZ7+BB7+BD7+BF7) -> 0.17 | BI7: =BH7/BG7 -> 0.425 | BJ7: =MIN((BG7 /BG7) * 100, 100) & "%" -> 100% | BK7: =IF(BG7=0, 0, BH7/BG7) -> 0.425 | BL7: P | BM7: Meta 6.docx | BN7: 55308000 | BO7: 38633333 | BP7: 209500000 | BQ7: 209500000 | BR7: =+BN7+BP7 -> 264808000 | BS7: =+BO7+BQ7 -> 248133333 | BT7: =IFERROR(BS7/BR7, "") -> 0.93703111 | BU7: 55308000 | BV7: 49633333 | BW7: 38633333 | BX7: 8233333 | BY7: =IFERROR(BW7/BV7, "") -> 0.77837475 | BZ7: 67000000 | CA7: 68340000 | CB7: 69706800 | CC7: 71798004 | CD7: 276844804
A8: Eje 1. Ambiente, Conectividad y Ordenamiento y servicios públicos | B8: 0.235 | D8: 32 | E8: 3204 | F8: 1 | G8: Programa Integral de Sostenibilidad y Educación Ambiental (PISEA) (Gestión Intergal del recurso hídrico) | H8: 0900 | I8: 1.2 | J8: Es el Tiempo de la Educación y Sensibilización Ambiental | K8: 1.1.2 | L8: Implementar en 25% la Política Pública de Educación Ambiental, actualizando y ejecutando completamente el Plan Institucional de Gestión Ambiental (PIGA), y fomentando la participación de la comunidad en la preservación y valoración de los recursos naturales a través de programas educativos | M8: Porcentaje de política de Educación Ambiental implementado | N8: 0 | O8: 3204056 | P8: 2024257990001 | Q8: Implementación de la educacion, sensibilizacion ambiental y Uso Sostenible de los Recursos Hídricos en el Municipio de Tenjo Cundinamarca | R8: 7 | S8: Ejecutar al 100% los PROCEDAS | T8: 1 | U8: Porcentaje | V8: M | W8: Porcentaje PROCEDAS ejecutado | X8: Secretaría de Desarrollo Económico y Medio Ambiente o quien haga sus veces | Y8: SI | Z8: =SUM(AF8:AI8)/4 -> 1 | AA8: =AS8/Z8 -> 0.4375 | AB8: =BI8/Z8 -> 0.75 | AE8: =SUMPRODUCT(AA8:AD8, {0.15,0.35,0.35,0.15}) -> 0.328125 | AF8: 1 | AG8: 1 | AH8: 1 | AI8: 1 | AN8: 0.75 | AO8: 0.75 | AP8: 0.25 | AQ8: 0.125 | AR8: =(AJ8+AL8+AN8+AP8)/2 -> 0.5 | AS8: =(AK8+AM8+AO8+AQ8)/2 -> 0.4375 | AT8: =AS8/AR8 -> 0.875 | AU8: =MIN((AR8 /AR8) * 100, 100) & "%" -> 100% | AV8: =IF(AR8=0, 0, AS8/AR8) -> 0.875 | AW8: P | AX8: META 7 | AY8: 0.15 | AZ8: 0.15 | BA8: 0.3 | BB8: 0.3 | BC8: 0.3 | BD8: 0.3 | BE8: 0.25 | BG8: =(AY8+BA8+BC8+BE8) -> 1 | BH8: =(AZ8+BB8+BD8+BF8) -> 0.75 | BI8: =BH8/BG8 -> 0.75 | BJ8: =MIN((BG8 /BG8) * 100, 100) & "%" -> 100% | BK8: =IF(BG8=0, 0, BH8/BG8) -> 0.75 | BL8: P | BM8: Meta 7.docx | BN8: 81500000 | BO8: 30000000 | BP8: 10000000 | BQ8: 10000000 | BR8: =+BN8+BP8 -> 91500000 | BS8: =+BO8+BQ8 -> 40000000 | BT8: =IFERROR(BS8/BR8, "") -> 0.43715847 | BU8: 60000000 | BV8: 81500000 | BW8: 30000000 | BX8: 21200000 | BY8: =IFERROR(BW8/BV8, "") -> 0.36809816 | BZ8: 30000000 | CA8: 30600000 | CB8: 31212000 | CC8: 32148360 | CD8: 123960360
A9: Eje 1. Ambiente, Conectividad y Ordenamiento y servicios públicos | B9: 0.235 | D9: 40 | E9: 4002 | F9: 2 | G9: Programa Integral de Transformación Urbana (PINTU) (Ordenamiento territorial y desarrollo urbano) | H9: 1400 | I9: 2.1 | J9: Es el tiempo de la legalización y saneamiento urbanístico | K9: 2.1.1 | L9: Asegurar al 100% la eficacia en la gestión y regulación de propiedades para el uso público en el municipio, logrando la legalización y saneamiento para infraestructura y equipamiento público | M9: Porcentaje de eficacia en la gestión y regulación de propiedades para el uso público en el municipio asegurado | N9: 0 | O9: 4002016 | P9: 2024257990002 | Q9: Fortalecimiento integral del programa de transformacion Urbana en el Municipio de Tenjo Cundinamarca | R9: 8 | S9: Realizar en mínimo 10 predios de interés el proceso de formalización y saneamiento | T9: 0 | U9: Número | V9: I | W9: Número de predios de interés con proceso de formalización y saneamiento | X9: Sec. de Planeación y Desarrollo Territorial | Z9: =SUM(AF9:AI9) -> 10 | AA9: =AS9/Z9 -> 0.2 | AB9: =BI9/Z9 -> 0.1 | AE9: =SUMPRODUCT(AA9:AD9, {0.15,0.35,0.35,0.15}) -> 0.065 | AF9: 2 | AG9: 6 | AH9: 2 | AI9: 0 | AN9: 1 | AO9: 1 | AP9: 1 | AQ9: 1 | AR9: =(AJ9+AL9+AN9+AP9) -> 2 | AS9: =(AK9+AM9+AO9+AQ9) -> 2 | AT9: =AS9/AR9 -> 1 | AU9: =MIN((AR9 /AR9) * 100, 100) & "%" -> 100% | AV9: =IF(AR9=0, 0, AS9/AR9) -> 1 | AW9: P | AX9: Meta 8.docx | AY9: 2 | AZ9: 2 | BA9: 4 | BB9: 4 | BC9: 0 | BD9: 0 | BE9: 0 | BF9: 0 | BG9: =(AY9+BA9+BC9+BE9) -> 6 | BH9: =(AZ9+BB9+BD9+BF9) -> 6 | BI9: =BH9/BG9 -> 1 | BJ9: =MIN((BG9 /BG9) * 100, 100) & "%" -> 100% | BK9: =IF(BG9=0, 0, BH9/BG9) -> 1 | BL9: P | BM9: Meta 8.docx | BN9: 95000000 | BO9: 60000000 | BP9: 21000000 | BQ9: 21000000 | BR9: =+BN9+BP9 -> 116000000 | BS9: =+BO9+BQ9 -> 81000000 | BT9: =IFERROR(BS9/BR9, "") -> 0.69827586 | BU9: 60000000 | BV9: 70000000 | BW9: 70000000 | BX9: 55800000 | BY9: =IFERROR(BW9/BV9, "") -> 1 | BZ9: 70000000 | CA9: 71400000 | CB9: 72828000 | CC9: 75012840 | CD9: 289240840
A10: Eje 1. Ambiente, Conectividad y Ordenamiento y servicios públicos | B10: 0.235 | D10: 40 | E10: 4002 | F10: 2 | G10: Programa Integral de Transformación Urbana (PINTU) (Ordenamiento territorial y desarrollo urbano) | H10: 1400 | I10: 2.1 | J10: Es el tiempo de la legalización y saneamiento urbanístico | K10: 2.1.1 | L10: Asegurar al 100% la eficacia en la gestión y regulación de propiedades para el uso público en el municipio, logrando la legalización y saneamiento para infraestructura y equipamiento público | M10: Porcentaje de eficacia en la gestión y regulación de propiedades para el uso público en el municipio asegurado | N10: 0 | O10: 4002040 | P10: 2024257990002 | Q10: Fortalecimiento integral del programa de transformacion Urbana en el Municipio de Tenjo Cundinamarca | R10: 9 | S10: Realizar la titulación del 80% de bienes destinados al uso público en actuaciones urbanísticas a favor del municipio | T10: 0.1 | U10: Porcentaje | V10: I | W10: Porcentaje de funcionamiento del Banco Inmobiliario | X10: Sec. de Urbanismo | Z10: =SUM(AF10:AI10) -> 0.8 | AA10: =AS10/Z10 -> 0.4375 | AB10: =BI10/Z10 -> 0.9375 | AE10: =SUMPRODUCT(AA10:AD10, {0.15,0.35,0.35,0.15}) -> 0.39375 | AF10: 0.1 | AG10: 0.2 | AH10: 0.3 | AI10: 0.2 | AN10: 0.07 | AO10: 0.07 | AP10: 0.28 | AQ10: 0.28 | AR10: =(AJ10+AL10+AN10+AP10) -> 0.35 | AS10: =(AK10+AM10+AO10+AQ10) -> 0.35 | AT10: =AS10/AR10 -> 1 | AU10: =MIN((AR10 /AR10) * 100, 100) & "%" -> 100% | AV10: =IF(AR10=0, 0, AS10/AR10) -> 1 | AW10: P | AX10: META 09.docx | AY10: 0.05 | AZ10: 0.05 | BA10: 0.05 | BB10: 0.05 | BC10: 0.05 | BD10: 0.05 | BE10: 0.05 | BG10: =(AY10+BA10+BC10+BE10) -> 0.2 | BH10: =(AZ10+BB10+BD10+BF10) -> 0.15 | BI10: =BH10/BG10 -> 0.75 | BJ10: =MIN((BG10 /BG10) * 100, 100) & "%" -> 100% | BK10: =IF(BG10=0, 0, BH10/BG10) -> 0.75 | BL10: P | BM10: Meta 9.docx | BN10: 60000000 | BO10: 58773333 | BP10: 29500000 | BQ10: 29500000 | BR10: =+BN10+BP10 -> 89500000 | BS10: =+BO10+BQ10 -> 88273333 | BT10: =IFERROR(BS10/BR10, "") -> 0.98629422 | BU10: 60000000 | BV10: 60000000 | BW10: 58773333 | BX10: 42140372 | BY10: =IFERROR(BW10/BV10, "") -> 0.97955555 | BZ10: 90000000 | CA10: 91800000 | CB10: 93636000 | CC10: 96445080 | CD10: 371881080
A11: Eje 1. Ambiente, Conectividad y Ordenamiento y servicios públicos | B11: 0.235 | D11: 40 | E11: 4002 | F11: 2 | G11: Programa Integral de Transformación Urbana (PINTU) (Ordenamiento territorial y desarrollo urbano) | H11: 1400 | I11: 2.1 | J11: Es el tiempo de la legalización y saneamiento urbanístico | K11: 2.1.1 | L11: Asegurar al 100% la eficacia en la gestión y regulación de propiedades para el uso público en el municipio, logrando la legalización y saneamiento para infraestructura y equipamiento público | M11: Porcentaje de eficacia en la gestión y regulación de propiedades para el uso público en el municipio asegurado | N11: 0 | O11: 4002042 | P11: 2024257990002 | Q11: Fortalecimiento integral del programa de transformacion Urbana en el Municipio de Tenjo Cundinamarca | R11: 10 | S11: Ejecutar al 100 % un proceso con la empresa inmobiliaria de Cundinamarca para la compra y adquisición de predios para uso institucional, dotacional, espacio público, cultural y otros. | T11: 1 | U11: Porcentaje | V11: M | W11: Porcentaje del proceso de compra de predios ejecutados | X11: Sec. de Urbanismo | Z11: =SUM(AF11:AI11)/2 -> 1 | AA11: =AS11/Z11 -> 1 | AB11: =BI11/Z11 -> 0.75 | AE11: =SUMPRODUCT(AA11:AD11, {0.15,0.35,0.35,0.15}) -> 0.4125 | AF11: 1 | AG11: 0 | AH11: 1 | AI11: 0 | AN11: 1 | AO11: 1 | AP11: 0 | AQ11: 0 | AR11: =(AJ11+AL11+AN11+AP11) -> 1 | AS11: =(AK11+AM11+AO11+AQ11) -> 1 | AT11: =AS11/AR11 -> 1 | AU11: =MIN((AR11 /AR11) * 100, 100) & "%" -> 100% | AV11: =IF(AR11=0, 0, AS11/AR11) -> 1 | AW11: P | AX11: META 10.docx | AY11: 1 | AZ11: 1 | BA11: 1 | BB11: 1 | BC11: 1 | BD11: 1 | BE11: 1 | BF11: 0 | BG11: =(AY11+BA11+BC11+BE11)/4 -> 1 | BH11: =(AZ11+BB11+BD11+BF11)/4 -> 0.75 | BI11: =BH11/BG11 -> 0.75 | BJ11: =MIN((BG11 /BG11) * 100, 100) & "%" -> 100% | BK11: =IF(BG11=0, 0, BH11/BG11) -> 0.75 | BL11: P | BM11: Meta 10.docx | BN11: 40000000 | BO11: 0 | BP11: 0 | BQ11: 0 | BR11: =+BN11+BP11 -> 40000000 | BS11: =+BO11+BQ11 -> 0 | BT11: =IFERROR(BS11/BR11, "") -> 0 | BU11: 0 | BV11: 40000000 | BW11: 40000000 | BX11: 0 | BY11: =IFERROR(BW11/BV11, "") -> 1 | BZ11: 40000000 | CA11: 40800000 | CB11: 41616000 | CC11: 42864480 | CD11: 165280480
A12: Eje 1. Ambiente, Conectividad y Ordenamiento y servicios públicos | B12: 0.235 | D12: 40 | E12: 4002 | F12: 2 | G12: Programa Integral de Transformación Urbana (PINTU) (Ordenamiento territorial y desarrollo urbano) | H12: 1400 | I12: 2,2 | J12: Acciones urbanísticas innovadoras | K12: 2.2.1 | L12: Optimizar al 100% la gestión y regulación del uso del suelo en el municipio | M12: Porcentaje de gestión y regulación del uso del suelo optimizada | N12: 0 | O12: 4002036 | P12: 2024257990002 | Q12: Fortalecimiento integral del programa de transformacion Urbana en el Municipio de Tenjo Cundinamarca | R12: 11 | S12: Implementar anualmente un programa de gestión urbanística y financiación del suelo | T12: 1 | U12: Número | V12: M | W12: Programa de revisión de instrumentos de gestión y financiación del suelo implementado | X12: Sec. de Urbanismo | Z12: =SUM(AF12:AI12) -> 4 | AA12: =AS12/Z12 -> 0.2375 | AB12: =BI12/Z12 -> 0.2125 | AE12: =SUMPRODUCT(AA12:AD12, {0.15,0.35,0.35,0.15}) -> 0.11 | AF12: 1 | AG12: 1 | AH12: 1 | AI12: 1 | AN12: 0.7 | AO12: 0.7 | AP12: 0.3 | AQ12: 0.25 | AR12: =(AJ12+AL12+AN12+AP12) -> 1 | AS12: =(AK12+AM12+AO12+AQ12) -> 0.95 | AT12: =AS12/AR12 -> 0.95 | AU12: =MIN((AR12 /AR12) * 100, 100) & "%" -> 100% | AV12: =IF(AR12=0, 0, AS12/AR12) -> 0.95 | AW12: P | AX12: META 11.docx | AY12: 0.25 | AZ12: 0.25 | BA12: 0.3 | BB12: 0.3 | BC12: 0.3 | BD12: 0.3 | BE12: 0.15 | BG12: =(AY12+BA12+BC12+BE12) -> 1 | BH12: =(AZ12+BB12+BD12+BF12) -> 0.85 | BI12: =BH12/BG12 -> 0.85 | BJ12: =MIN((BG12 /BG12) * 100, 100) & "%" -> 100% | BK12: =IF(BG12=0, 0, BH12/BG12) -> 0.85 | BL12: P | BM12: Meta 11.docx | BN12: 420000000 | BO12: 280610000 | BP12: 144661334 | BQ12: 144661334 | BR12: =+BN12+BP12 -> 564661334 | BS12: =+BO12+BQ12 -> 425271334 | BT12: =IFERROR(BS12/BR12, "") -> 0.75314407 | BU12: 420000000 | BV12: 327110000 | BW12: 327110000 | BX12: 209617959 | BY12: =IFERROR(BW12/BV12, "") -> 1 | BZ12: 200000000 | CA12: 204000000 | CB12: 208080000 | CC12: 214322400 | CD12: 826402400
A13: Eje 1. Ambiente, Conectividad y Ordenamiento y servicios públicos | B13: 0.235 | D13: 45 | E13: 4599 | F13: 3 | G13: Programa Avanzado de Gestión Territorial Inteligente (PRAGETI) (Fortalecimiento a la gestión y dirección de la gestió pública territorial) | H13: 1000 | I13: 3.1 | J13: Sistemas de Información y datos para la toma de decisiones | K13: 3.1.1 | L13: Implementar al 100% el sistema de Información y datos de gestión del desarrollo territorial y toma de decisiones, mediante la implementación efectiva de tecnologías avanzadas en análisis de datos y la optimización del funcionamiento de los consejos y comités de planificación y estratificación | M13: Porcentaje de sistema de Información y datos implementado | N13: 0.71 | O13: 4599005 | P13: 2024257990003 | Q13: Fortalecimiento a la direccion y gestión publica en el Municipio de Tenjo Cundinamarca | R13: 12 | S13: Actualizar mantener y fortalecer en un 100% la infraestructura de datos espaciales en el cuatrienio | T13: 0.4 | U13: Porcentaje | V13: I | W13: Funcionamiento garantizado | X13: Sec. de Planeación y Desarrollo Territorial | Z13: =SUM(AF13:AI13)/4 -> 1 | AA13: =AS13/Z13 -> 0.45 | AB13: =BI13/Z13 -> 0.9 | AE13: =SUMPRODUCT(AA13:AD13, {0.15,0.35,0.35,0.15}) -> 0.3825 | AF13: 1 | AG13: 1 | AH13: 1 | AI13: 1 | AN13: 0.5 | AO13: 0.5 | AP13: 0.5 | AQ13: 0.4 | AR13: =(AJ13+AL13+AN13+AP13)/2 -> 0.5 | AS13: =(AK13+AM13+AO13+AQ13)/2 -> 0.45 | AT13: =AS13/AR13 -> 0.9 | AU13: =MIN((AR13 /AR13) * 100, 100) & "%" -> 100% | AV13: =IF(AR13=0, 0, AS13/AR13) -> 0.9 | AW13: P | AX13: Meta 12.docx | AY13: 0.15 | AZ13: 0.15 | BA13: 0.3 | BB13: 0.3 | BC13: 0.45 | BD13: 0.45 | BE13: 0.1 | BG13: =(AY13+BA13+BC13+BE13) -> 1 | BH13: =(AZ13+BB13+BD13+BF13) -> 0.9 | BI13: =BH13/BG13 -> 0.9 | BJ13: =MIN((BG13 /BG13) * 100, 100) & "%" -> 100% | BK13: =IF(BG13=0, 0, BH13/BG13) -> 0.9 | BL13: P | BM13: Meta 12.docx | BN13: 442681049 | BO13: 44000000 | BP13: 11400000 | BQ13: 11400000 | BR13: =+BN13+BP13 -> 454081049 | BS13: =+BO13+BQ13 -> 55400000 | BT13: =IFERROR(BS13/BR13, "") -> 0.12200465 | BU13: 92681049 | BV13: 72681049 | BW13: 58000000 | BX13: 39266666 | BY13: =IFERROR(BW13/BV13, "") -> 0.79800719 | BZ13: 375000000 | CA13: 382500000 | CB13: 390150000 | CC13: 401854500 | CD13: 1549504500
A14: Eje 1. Ambiente, Conectividad y Ordenamiento y servicios públicos | B14: 0.235 | D14: 45 | E14: 4599 | F14: 3 | G14: Programa Avanzado de Gestión Territorial Inteligente (PRAGETI) (Fortalecimiento a la gestión y dirección de la gestió pública territorial) | H14: 1000 | I14: 3.1 | J14: Sistemas de Información y datos para la toma de decisiones | K14: 3.1.1 | L14: Implementar al 100% el sistema de Información y datos de gestión del desarrollo territorial y toma de decisiones, mediante la implementación efectiva de tecnologías avanzadas en análisis de datos y la optimización del funcionamiento de los consejos y comités de planificación y estratificación | M14: Porcentaje de sistema de Información y datos implementado | N14: 0.71 | O14: 4599025 | P14: 2024257990003 | Q14: Fortalecimiento a la direccion y gestión publica en el Municipio de Tenjo Cundinamarca | R14: 13 | S14: Garantizar el funcionamiento del servicio público de catastro multipropósito, logrando la hablilitación como Gestor Catastral al 100% | T14: 1 | U14: Porcentaje | V14: M | W14: Funcionamiento garantizado | X14: Sec. de Planeación y Desarrollo Territorial | Z14: =SUM(AF14:AI14) -> 1 | AA14: =AS14/Z14 -> 0.3 | AB14: =BI14/Z14 -> 0.6 | AE14: =SUMPRODUCT(AA14:AD14, {0.15,0.35,0.35,0.15}) -> 0.255 | AF14: 0.3 | AG14: 0.1 | AH14: 0.4 | AI14: 0.2 | AN14: 0.1 | AO14: 0.1 | AP14: 0.2 | AQ14: 0.2 | AR14: =(AJ14+AL14+AN14+AP14) -> 0.3 | AS14: =(AK14+AM14+AO14+AQ14) -> 0.3 | AT14: =AS14/AR14 -> 1 | AU14: =MIN((AR14 /AR14) * 100, 100) & "%" -> 100% | AV14: =IF(AR14=0, 0, AS14/AR14) -> 1 | AW14: P | AX14: Meta 13.docx | AY14: 0.03 | AZ14: 0.03 | BA14: 0.03 | BB14: 0 | BC14: 0.03 | BD14: 0.03 | BE14: 0.01 | BG14: =(AY14+BA14+BC14+BE14) -> 0.1 | BH14: =(AZ14+BB14+BD14+BF14) -> 0.06 | BI14: =BH14/BG14 -> 0.6 | BJ14: =MIN((BG14 /BG14) * 100, 100) & "%" -> 100% | BK14: =IF(BG14=0, 0, BH14/BG14) -> 0.6 | BL14: P | BM14: Meta 13.docx | BN14: 510000000 | BO14: 45000000 | BP14: 336500000 | BQ14: 336500000 | BR14: =+BN14+BP14 -> 846500000 | BS14: =+BO14+BQ14 -> 381500000 | BT14: =IFERROR(BS14/BR14, "") -> 0.45067927 | BU14: 510000000 | BV14: 120000000 | BW14: 31250000 | BX14: 11850000 | BY14: =IFERROR(BW14/BV14, "") -> 0.26041667 | BZ14: 500000000 | CA14: 510000000 | CB14: 520200000 | CC14: 535806000 | CD14: 2066006000
A15: Eje 1. Ambiente, Conectividad y Ordenamiento y servicios públicos | B15: 0.235 | D15: 45 | E15: 4599 | F15: 3 | G15: Programa Avanzado de Gestión Territorial Inteligente (PRAGETI) (Fortalecimiento a la gestión y dirección de la gestió pública territorial) | H15: 1000 | I15: 3.1 | J15: Sistemas de Información y datos para la toma de decisiones | K15: 3.1.1 | L15: Implementar al 100% el sistema de Información y datos de gestión del desarrollo territorial y toma de decisiones, mediante la implementación efectiva de tecnologías avanzadas en análisis de datos y la optimización del funcionamiento de los consejos y comités de planificación y estratificación | M15: Porcentaje de sistema de Información y datos implementado | N15: 0.71 | O15: 4599031 | P15: 2024257990003 | Q15: Fortalecimiento a la direccion y gestión publica en el Municipio de Tenjo Cundinamarca | R15: 14 | S15: Formular al 100% los proyectos de inversión para el cumplimiento de metas del plan de desarrollo municipal | T15: SD | U15: Porcentaje | V15: I | W15: Porcentaje de proyectos de inversión formulados y actualizados | X15: Sec. de Planeación y Desarrollo Territorial | Z15: =SUM(AF15:AI15)/4 -> 1 | AA15: =AS15/Z15 -> 0.475 | AB15: =BI15/Z15 -> 0.85 | AE15: =SUMPRODUCT(AA15:AD15, {0.15,0.35,0.35,0.15}) -> 0.36875 | AF15: 1 | AG15: 1 | AH15: 1 | AI15: 1 | AN15: 0.75 | AO15: 0.75 | AP15: 0.25 | AQ15: 0.2 | AR15: =(AJ15+AL15+AN15+AP15)/2 -> 0.5 | AS15: =(AK15+AM15+AO15+AQ15)/2 -> 0.475 | AT15: =AS15/AR15 -> 0.95 | AU15: =MIN((AR15 /AR15) * 100, 100) & "%" -> 100% | AV15: =IF(AR15=0, 0, AS15/AR15) -> 0.95 | AW15: P | AX15: Meta 14.docx | AY15: 0.25 | AZ15: 0.25 | BA15: 0.25 | BB15: 0.25 | BC15: 0.35 | BD15: 0.35 | BE15: 0.15 | BG15: =(AY15+BA15+BC15+BE15) -> 1 | BH15: =(AZ15+BB15+BD15+BF15) -> 0.85 | BI15: =BH15/BG15 -> 0.85 | BJ15: =MIN((BG15 /BG15) * 100, 100) & "%" -> 100% | BK15: =IF(BG15=0, 0, BH15/BG15) -> 0.85 | BL15: P | BM15: Meta 14.docx | BN15: 194000000 | BO15: 99753334 | BP15: 45533333 | BQ15: 45533333 | BR15: =+BN15+BP15 -> 239533333 | BS15: =+BO15+BQ15 -> 145286667 | BT15: =IFERROR(BS15/BR15, "") -> 0.6065405 | BU15: 170000000 | BV15: 103753334 | BW15: 99753334 | BX15: 76023333 | BY15: =IFERROR(BW15/BV15, "") -> 0.96144702 | BZ15: 160000000 | CA15: 163200000 | CB15: 166464000 | CC15: 171457920 | CD15: 661121920
A16: Eje 1. Ambiente, Conectividad y Ordenamiento y servicios públicos | B16: 0.235 | D16: 45 | E16: 4599 | F16: 3 | G16: Programa Avanzado de Gestión Territorial Inteligente (PRAGETI) (Fortalecimiento a la gestión y dirección de la gestió pública territorial) | H16: 1000 | I16: 3.1 | J16: Sistemas de Información y datos para la toma de decisiones | K16: 3.1.1 | L16: Implementar al 100% el sistema de Información y datos de gestión del desarrollo territorial y toma de decisiones, mediante la implementación efectiva de tecnologías avanzadas en análisis de datos y la optimización del funcionamiento de los consejos y comités de planificación y estratificación | M16: Porcentaje de sistema de Información y datos implementado | N16: 0.71 | O16: 4599032 | P16: 2024257990003 | Q16: Fortalecimiento a la direccion y gestión publica en el Municipio de Tenjo Cundinamarca | R16: 15 | S16: Desarrollar 4 seguimientos anuales a la ejecución del Plan de Desarrollo Territorial gerenado un esquema de ajuste a y mejoras en la toma de decisiones | T16: 4 | U16: Número | V16: M | W16: Seguimientos anuales al plan de Desarrollo realizados | X16: Sec. de Planeación y Desarrollo Territorial | Z16: =SUM(AF16:AI16) -> 16 | AA16: =AS16/Z16 -> 0.25 | AB16: =BI16/Z16 -> 0.0546875 | AE16: =SUMPRODUCT(AA16:AD16, {0.15,0.35,0.35,0.15}) -> 0.056640625 | AF16: 4 | AG16: 4 | AH16: 4 | AI16: 4 | AN16: 2 | AO16: 2 | AP16: 2 | AQ16: 2 | AR16: =(AJ16+AL16+AN16+AP16) -> 4 | AS16: =(AK16+AM16+AO16+AQ16) -> 4 | AT16: =AS16/AR16 -> 1 | AU16: =MIN((AR16 /AR16) * 100, 100) & "%" -> 100% | AV16: =IF(AR16=0, 0, AS16/AR16) -> 1 | AW16: P | AX16: Meta 15.docx | AY16: 1 | AZ16: 1 | BA16: 1 | BB16: 1 | BC16: 1.5 | BD16: 1.5 | BE16: 0.5 | BG16: =(AY16+BA16+BC16+BE16) -> 4 | BH16: =(AZ16+BB16+BD16+BF16) -> 3.5 | BI16: =BH16/BG16 -> 0.875 | BJ16: =MIN((BG16 /BG16) * 100, 100) & "%" -> 100% | BK16: =IF(BG16=0, 0, BH16/BG16) -> 0.875 | BL16: P | BM16: Meta 15.docx | BN16: 125000000 | BO16: 15000000 | BP16: 2000000 | BQ16: 2000000 | BR16: =+BN16+BP16 -> 127000000 | BS16: =+BO16+BQ16 -> 17000000 | BT16: =IFERROR(BS16/BR16, "") -> 0.13385827 | BU16: 125000000 | BV16: 63400000 | BW16: 63400000 | BX16: 21240000 | BY16: =IFERROR(BW16/BV16, "") -> 1 | BZ16: 110000000 | CA16: 112200000 | CB16: 114444000 | CC16: 117877320 | CD16: 454521320
A17: Eje 1. Ambiente, Conectividad y Ordenamiento y servicios públicos | B17: 0.235 | D17: 45 | E17: 4599 | F17: 3 | G17: Programa Avanzado de Gestión Territorial Inteligente (PRAGETI) (Fortalecimiento a la gestión y dirección de la gestió pública territorial) | H17: 1000 | I17: 3.1 | J17: Sistemas de Información y datos para la toma de decisiones | K17: 3.1.1 | L17: Implementar al 100% el sistema de Información y datos de gestión del desarrollo territorial y toma de decisiones, mediante la implementación efectiva de tecnologías avanzadas en análisis de datos y la optimización del funcionamiento de los consejos y comités de planificación y estratificación | M17: Porcentaje de sistema de Información y datos implementado | N17: 0.71 | O17: 4599023 | P17: 2024257990003 | Q17: Fortalecimiento a la direccion y gestión publica en el Municipio de Tenjo Cundinamarca | R17: 16 | S17: Implementar un modelo de gobierno de datos con el manejo de herramientas de analítica de datos para la toma de decisiones. | T17: 0 | U17: Número | V17: I | W17: Modelo de gobierno de datos implementado | X17: Sec. de Planeación y Desarrollo Territorial | Y17: SI | Z17: =SUM(AF17:AI17) -> 1 | AA17: =AS17/Z17 -> 1 | AB17: =BI17/Z17 -> 0.83333333 | AE17: =SUMPRODUCT(AA17:AD17, {0.15,0.35,0.35,0.15}) -> 0.44166667 | AF17: 0.2 | AG17: 0.3 | AH17: 0.3 | AI17: 0.2 | AN17: 0.4 | AO17: 0.4 | AP17: 0.6 | AQ17: 0.6 | AR17: =(AJ17+AL17+AN17+AP17) -> 1 | AS17: =(AK17+AM17+AO17+AQ17) -> 1 | AT17: =AS17/AR17 -> 1 | AU17: =MIN((AR17 /AR17) * 100, 100) & "%" -> 100% | AV17: =IF(AR17=0, 0, AS17/AR17) -> 1 | AW17: P | AX17: Meta 16.docx | AY17: 0.5 | AZ17: 0.5 | BA17: 0.5 | BB17: 0.5 | BC17: 1.5 | BD17: 1.5 | BE17: 0.5 | BG17: =(AY17+BA17+BC17+BE17) -> 3 | BH17: =(AZ17+BB17+BD17+BF17) -> 2.5 | BI17: =BH17/BG17 -> 0.83333333 | BJ17: =MIN((BG17 /BG17) * 100, 100) & "%" -> 100% | BK17: =IF(BG17=0, 0, BH17/BG17) -> 0.83333333 | BL17: P | BM17: Meta 16.docx | BN17: 71400000 | BO17: 71400000 | BP17: 88000000 | BQ17: 88000000 | BR17: =+BN17+BP17 -> 159400000 | BS17: =+BO17+BQ17 -> 159400000 | BT17: =IFERROR(BS17/BR17, "") -> 1 | BU17: 71400000 | BV17: 71400000 | BW17: 71400000 | BX17: 54442500 | BY17: =IFERROR(BW17/BV17, "") -> 1 | BZ17: 70000000 | CA17: 71400000 | CB17: 72828000 | CC17: 75012840 | CD17: 289240840
A18: Eje 1. Ambiente, Conectividad y Ordenamiento y servicios públicos | B18: 0.235 | D18: 45 | E18: 4599 | F18: 3 | G18: Programa Avanzado de Gestión Territorial Inteligente (PRAGETI) (Fortalecimiento a la gestión y dirección de la gestió pública territorial) | H18: 1000 | I18: 3.1 | J18: Sistemas de Información y datos para la toma de decisiones | K18: 3.1.1 | L18: Implementar al 100% el sistema de Información y datos de gestión del desarrollo territorial y toma de decisiones, mediante la implementación efectiva de tecnologías avanzadas en análisis de datos y la optimización del funcionamiento de los consejos y comités de planificación y estratificación | M18: Porcentaje de sistema de Información y datos implementado | N18: 0.71 | O18: 4599033 | P18: 2024257990003 | Q18: Fortalecimiento a la direccion y gestión publica en el Municipio de Tenjo Cundinamarca | R18: 17 | S18: Garantizar el sistema de información y el proceso de encuestas del sisben al 100% | T18: 1 | U18: Número | V18: M | W18: Funcionamiento garantizado | X18: Sec. de Planeación y Desarrollo Territorial | Z18: =SUM(AF18:AI18)/4 -> 1 | AA18: =AS18/Z18 -> 0.5 | AB18: =BI18/Z18 -> 0.85 | AE18: =SUMPRODUCT(AA18:AD18, {0.15,0.35,0.35,0.15}) -> 0.3725 | AF18: 1 | AG18: 1 | AH18: 1 | AI18: 1 | AN18: 0.75 | AO18: 0.75 | AP18: 0.25 | AQ18: 0.25 | AR18: =(AJ18+AL18+AN18+AP18)/2 -> 0.5 | AS18: =(AK18+AM18+AO18+AQ18)/2 -> 0.5 | AT18: =AS18/AR18 -> 1 | AU18: =MIN((AR18 /AR18) * 100, 100) & "%" -> 100% | AV18: =IF(AR18=0, 0, AS18/AR18) -> 1 | AW18: P | AX18: Meta 17.docx | AY18: 0.2 | AZ18: 0.2 | BA18: 0.25 | BB18: 0.25 | BC18: 0.4 | BD18: 0.4 | BE18: 0.15 | BG18: =(AY18+BA18+BC18+BE18) -> 1 | BH18: =(AZ18+BB18+BD18+BF18) -> 0.85 | BI18: =BH18/BG18 -> 0.85 | BJ18: =MIN((BG18 /BG18) * 100, 100) & "%" -> 100% | BK18: =IF(BG18=0, 0, BH18/BG18) -> 0.85 | BL18: P | BM18: Meta 17.docx | BN18: 110000000 | BO18: 93500000 | BP18: 24855200 | BQ18: 24855200 | BR18: =+BN18+BP18 -> 134855200 | BS18: =+BO18+BQ18 -> 118355200 | BT18: =IFERROR(BS18/BR18, "") -> 0.87764654 | BU18: 110000000 | BV18: 110000000 | BW18: 93500000 | BX18: 68113332 | BY18: =IFERROR(BW18/BV18, "") -> 0.85 | BZ18: 80000000 | CA18: 81600000 | CB18: 83232000 | CC18: 85728960 | CD18: 330560960
A19: Eje 1. Ambiente, Conectividad y Ordenamiento y servicios públicos | B19: 0.235 | D19: 45 | E19: 4599 | F19: 3 | G19: Programa Avanzado de Gestión Territorial Inteligente (PRAGETI) (Fortalecimiento a la gestión y dirección de la gestió pública territorial) | H19: 1000 | I19: 3.1 | J19: Sistemas de Información y datos para la toma de decisiones | K19: 3.1.1 | L19: Implementar al 100% el sistema de Información y datos de gestión del desarrollo territorial y toma de decisiones, mediante la implementación efectiva de tecnologías avanzadas en análisis de datos y la optimización del funcionamiento de los consejos y comités de planificación y estratificación | M19: Porcentaje de sistema de Información y datos implementado | N19: 0.71 | O19: 4599033 | P19: 2024257990003 | Q19: Fortalecimiento a la direccion y gestión publica en el Municipio de Tenjo Cundinamarca | R19: 18 | S19: Garantizar el funcionamiento del Consejo Territorial de Planeación | T19: 1 | U19: Número | V19: M | W19: Funcionamiento garantizado | X19: Sec. de Planeación y Desarrollo Territorial | Z19: =SUM(AF19:AI19)/4 -> 1 | AA19: =AS19/Z19 -> 1 | AB19: =BI19/Z19 -> 0.7 | AE19: =SUMPRODUCT(AA19:AD19, {0.15,0.35,0.35,0.15}) -> 0.395 | AF19: 1 | AG19: 1 | AH19: 1 | AI19: 1 | AN19: 0.5 | AO19: 0.5 | AP19: 0.5 | AQ19: 0.5 | AR19: =(AJ19+AL19+AN19+AP19) -> 1 | AS19: =(AK19+AM19+AO19+AQ19) -> 1 | AT19: =AS19/AR19 -> 1 | AU19: =MIN((AR19 /AR19) * 100, 100) & "%" -> 100% | AV19: =IF(AR19=0, 0, AS19/AR19) -> 1 | AW19: P | AX19: Meta 18.docx | AY19: 0.1 | AZ19: 0.1 | BA19: 0.1 | BB19: 0.1 | BC19: 0.5 | BD19: 0.5 | BE19: 0.3 | BG19: =(AY19+BA19+BC19+BE19) -> 1 | BH19: =(AZ19+BB19+BD19+BF19) -> 0.7 | BI19: =BH19/BG19 -> 0.7 | BJ19: =MIN((BG19 /BG19) * 100, 100) & "%" -> 100% | BK19: =IF(BG19=0, 0, BH19/BG19) -> 0.7 | BL19: P | BM19: Meta 18.docx | BN19: 15000000 | BO19: 0 | BP19: 0 | BQ19: 0 | BR19: =+BN19+BP19 -> 15000000 | BS19: =+BO19+BQ19 -> 0 | BT19: =IFERROR(BS19/BR19, "") -> 0 | BU19: 15000000 | BV19: 15000000 | BW19: 14930914 | BX19: 0 | BY19: =IFERROR(BW19/BV19, "") -> 0.99539427 | BZ19: 20000000 | CA19: 20400000 | CB19: 20808000 | CC19: 21432240 | CD19: 82640240
A20: Eje 1. Ambiente, Conectividad y Ordenamiento y servicios públicos | B20: 0.235 | D20: 45 | E20: 4599 | F20: 3 | G20: Programa Avanzado de Gestión Territorial Inteligente (PRAGETI) (Fortalecimiento a la gestión y dirección de la gestió pública territorial) | H20: 1000 | I20: 3.1 | J20: Sistemas de Información y datos para la toma de decisiones | K20: 3.1.1 | L20: Implementar al 100% el sistema de Información y datos de gestión del desarrollo territorial y toma de decisiones, mediante la implementación efectiva de tecnologías avanzadas en análisis de datos y la optimización del funcionamiento de los consejos y comités de planificación y estratificación | M20: Porcentaje de sistema de Información y datos implementado | N20: 0.71 | O20: 4599005 | P20: 2024257990003 | Q20: Fortalecimiento a la direccion y gestión publica en el Municipio de Tenjo Cundinamarca | R20: 19 | S20: Garantizar el funcionamiento de comité de estratificación | T20: 0.5 | U20: Porcentaje | V20: I | W20: Actalización aplicada | X20: Sec. de Planeación y Desarrollo Territorial | Z20: =SUM(AF20:AI20)/4 -> 1 | AA20: =AS20/Z20 -> 0.98 | AB20: =BI20/Z20 -> 0.5 | AE20: =SUMPRODUCT(AA20:AD20, {0.15,0.35,0.35,0.15}) -> 0.322 | AF20: 1 | AG20: 1 | AH20: 1 | AI20: 1 | AN20: 0.4 | AO20: 0.4 | AP20: 0.6 | AQ20: 0.58 | AR20: =(AJ20+AL20+AN20+AP20) -> 1 | AS20: =(AK20+AM20+AO20+AQ20) -> 0.98 | AT20: =AS20/AR20 -> 0.98 | AU20: =MIN((AR20 /AR20) * 100, 100) & "%" -> 100% | AV20: =IF(AR20=0, 0, AS20/AR20) -> 0.98 | AW20: P | AX20: Meta 19.docx | AY20: 0 | AZ20: 0 | BA20: 0 | BB20: 0 | BC20: 0.5 | BD20: 0.5 | BE20: 0.5 | BG20: =(AY20+BA20+BC20+BE20) -> 1 | BH20: =(AZ20+BB20+BD20+BF20) -> 0.5 | BI20: =BH20/BG20 -> 0.5 | BJ20: =MIN((BG20 /BG20) * 100, 100) & "%" -> 100% | BK20: =IF(BG20=0, 0, BH20/BG20) -> 0.5 | BL20: P | BM20: Meta 19.docx | BN20: 5100000 | BO20: 0 | BP20: 195173 | BQ20: 195173 | BR20: =+BN20+BP20 -> 5295173 | BS20: =+BO20+BQ20 -> 195173 | BT20: =IFERROR(BS20/BR20, "") -> 0.036858664 | BU20: 5100000 | BV20: 5100000 | BW20: 208835 | BX20: 208835 | BY20: =IFERROR(BW20/BV20, "") -> 0.040948039 | BZ20: 5000000 | CA20: 5100000 | CB20: 5202000 | CC20: 5358060 | CD20: 20660060
A21: Eje 1. Ambiente, Conectividad y Ordenamiento y servicios públicos | B21: 0.235 | D21: 40 | E21: 4002 | F21: 4 | G21: Ordenamiento Territorial y Desarrollo Urbano Inteligente y Sostenible-OTEDUS (Ordenamiento territorial y desarrollo urbano) | H21: 1400 | I21: 4.1 | J21: Ordenamiento Territorial Inteligente | K21: 4.1.1 | L21: Garantizar al 100% las acciones de revisión, ajustes y actualización de PBOT | M21: Porcentaje de acciones de garantizadas | N21: 0.2 | O21: 4002018 | P21: 2024257990004 | Q21: Implementación del Desarrollo Urbano y Ordenamiento Territorial Inteligente en el Municipio de Tenjo Cundinamarca | R21: 20 | S21: Desarrollar un programa de actualización cartográfica | T21: 0 | U21: Número | V21: I | W21: Programa desarrollado | X21: Sec. de Planeación y Desarrollo Territorial | Z21: =SUM(AF21:AI21) -> 1 | AA21: =AS21/Z21 -> 0.88 | AB21: =BI21/Z21 -> 0 | AE21: =SUMPRODUCT(AA21:AD21, {0.15,0.35,0.35,0.15}) -> 0.132 | AF21: 1 | AG21: 0 | AH21: 0 | AI21: 0 | AN21: 0.7 | AO21: 0.7 | AP21: 0.3 | AQ21: 0.18 | AR21: =(AJ21+AL21+AN21+AP21) -> 1 | AS21: =(AK21+AM21+AO21+AQ21) -> 0.88 | AT21: =AS21/AR21 -> 0.88 | AU21: =MIN((AR21 /AR21) * 100, 100) & "%" -> 100% | AV21: =IF(AR21=0, 0, AS21/AR21) -> 0.88 | AW21: P | AX21: Meta 20.docx | AY21: 0 | BA21: 0 | BB21: 0 | BC21: 0 | BE21: 0 | BG21: =(AY21+BA21+BC21+BE21) -> 0 | BH21: =(AZ21+BB21+BD21+BF21) -> 0 | BI21: =IF(BF21> 1, IF(BF21 = BG21, "100%", BF21 & "%"), IF(BF21 <= 0.01, "0%", BF21 * 100 & "%")) -> 0% | BJ21: =IF(BF21=0, 0, BG21/BF21) -> 0 | BK21: =IF(BG21=0, 0, BH21/BG21) -> 0 | BL21: NP | BM21: Meta 20.docx | BN21: 0 | BO21: 0 | BP21: 646022333 | BQ21: 646022333 | BR21: =+BN21+BP21 -> 646022333 | BS21: =+BO21+BQ21 -> 646022333 | BT21: =IFERROR(BS21/BR21, "") -> 1 | BU21: 0 | BV21: 0 | BW21: 0 | BX21: 0 | BY21: =IFERROR(BW21/BV21, "") | BZ21: 650000000 | CA21: 0 | CB21: 0 | CC21: 0 | CD21: 650000000
A22: Eje 1. Ambiente, Conectividad y Ordenamiento y servicios públicos | B22: 0.235 | D22: 40 | E22: 4002 | F22: 4 | G22: Ordenamiento Territorial y Desarrollo Urbano Inteligente y Sostenible-OTEDUS (Ordenamiento territorial y desarrollo urbano) | H22: 1400 | I22: 4.1 | J22: Ordenamiento Territorial Inteligente | K22: 4.1.1 | L22: Garantizar al 100% las acciones de revisión, ajustes y actualización de PBOT | M22: Porcentaje de acciones de garantizadas | N22: 0.2 | O22: 4002001 | P22: 2024257990004 | Q22: Implementación del Desarrollo Urbano y Ordenamiento Territorial Inteligente en el Municipio de Tenjo Cundinamarca | R22: 21 | S22: Realizar un proceso de revisión y ajustes al PBOT en el cuatrienio | T22: 0 | U22: Número | V22: I | W22: Proceso de revisión realizado | X22: Sec. de Planeación y Desarrollo Territorial | Z22: =SUM(AF22:AI22) -> 1 | AA22: =AS22/Z22 -> 0.2 | AB22: =BI22/Z22 -> 0.875 | AE22: =SUMPRODUCT(AA22:AD22, {0.15,0.35,0.35,0.15}) -> 0.33625 | AF22: 0.2 | AG22: 0.4 | AH22: 0.3 | AI22: 0.1 | AN22: 0.1 | AO22: 0.1 | AP22: 0.1 | AQ22: 0.1 | AR22: =(AJ22+AL22+AN22+AP22) -> 0.2 | AS22: =(AK22+AM22+AO22+AQ22) -> 0.2 | AT22: =AS22/AR22 -> 1 | AU22: =MIN((AR22 /AR22) * 100, 100) & "%" -> 100% | AV22: =IF(AR22=0, 0, AS22/AR22) -> 1 | AW22: P | AX22: Meta 21.docx | AY22: 0.1 | AZ22: 0.1 | BA22: 0.1 | BB22: 0.1 | BC22: 0.15 | BD22: 0.15 | BE22: 0.05 | BG22: =(AY22+BA22+BC22+BE22) -> 0.4 | BH22: =(AZ22+BB22+BD22+BF22) -> 0.35 | BI22: =BH22/BG22 -> 0.875 | BJ22: =MIN((BG22 /BG22) * 100, 100) & "%" -> 100% | BK22: =IF(BG22=0, 0, BH22/BG22) -> 0.875 | BL22: P | BM22: Meta 21.docx | BN22: 300000000 | BO22: 184400000 | BP22: 54746667 | BQ22: 54746667 | BR22: =+BN22+BP22 -> 354746667 | BS22: =+BO22+BQ22 -> 239146667 | BT22: =IFERROR(BS22/BR22, "") -> 0.67413365 | BU22: 300000000 | BV22: 224400000 | BW22: 211950000 | BX22: 155066666 | BY22: =IFERROR(BW22/BV22, "") -> 0.94451872 | BZ22: 180000000 | CA22: 183600000 | CB22: 187272000 | CC22: 192890160 | CD22: 743762160
A23: Eje 1. Ambiente, Conectividad y Ordenamiento y servicios públicos | B23: 0.235 | D23: 40 | E23: 4002 | F23: 4 | G23: Ordenamiento Territorial y Desarrollo Urbano Inteligente y Sostenible-OTEDUS (Ordenamiento territorial y desarrollo urbano) | H23: 1400 | I23: 4.1 | J23: Ordenamiento Territorial Inteligente | K23: 4.1.1 | L23: Garantizar al 100% las acciones de revisión, ajustes y actualización de PBOT | M23: Porcentaje de acciones de garantizadas | N23: 0.2 | O23: 4002016 | P23: 2024257990004 | Q23: Implementación del Desarrollo Urbano y Ordenamiento Territorial Inteligente en el Municipio de Tenjo Cundinamarca | R23: 22 | S23: Mantener actualizado al 100% el expediente municipal del PBOT | T23: 0.6 | U23: Porcentaje | V23: M | W23: Expediente municipal fortalecido | X23: Sec. de Planeación y Desarrollo Territorial | Z23: =SUM(AF23:AI23)/4 -> 1 | AA23: =AS23/Z23 -> 0.5 | AB23: =BI23/Z23 -> 0.85 | AE23: =SUMPRODUCT(AA23:AD23, {0.15,0.35,0.35,0.15}) -> 0.3725 | AF23: 1 | AG23: 1 | AH23: 1 | AI23: 1 | AN23: 0.2 | AO23: 0.2 | AP23: 0.8 | AQ23: 0.8 | AR23: =(AJ23+AL23+AN23+AP23)/2 -> 0.5 | AS23: =(AK23+AM23+AO23+AQ23)/2 -> 0.5 | AT23: =AS23/AR23 -> 1 | AU23: =MIN((AR23 /AR23) * 100, 100) & "%" -> 100% | AV23: =IF(AR23=0, 0, AS23/AR23) -> 1 | AW23: P | AX23: Meta 22.docx | AY23: 0.15 | AZ23: 0.15 | BA23: 0.3 | BB23: 0.3 | BC23: 0.4 | BD23: 0.4 | BE23: 0.15 | BG23: =(AY23+BA23+BC23+BE23) -> 1 | BH23: =(AZ23+BB23+BD23+BF23) -> 0.85 | BI23: =BH23/BG23 -> 0.85 | BJ23: =MIN((BG23 /BG23) * 100, 100) & "%" -> 100% | BK23: =IF(BG23=0, 0, BH23/BG23) -> 0.85 | BL23: P | BM23: Meta 22.docx | BN23: 72000000 | BO23: 35530000 | BP23: 0 | BQ23: 0 | BR23: =+BN23+BP23 -> 72000000 | BS23: =+BO23+BQ23 -> 35530000 | BT23: =IFERROR(BS23/BR23, "") -> 0.49347222 | BU23: 72000000 | BV23: 35530000 | BW23: 35530000 | BX23: 25630000 | BY23: =IFERROR(BW23/BV23, "") -> 1 | BZ23: 131000000 | CA23: 133620000 | CB23: 136292400 | CC23: 140381172 | CD23: 541293572
A24: Eje 1. Ambiente, Conectividad y Ordenamiento y servicios públicos | B24: 0.235 | D24: 40 | E24: 4002 | F24: 4 | G24: Ordenamiento Territorial y Desarrollo Urbano Inteligente y Sostenible-OTEDUS (Ordenamiento territorial y desarrollo urbano) | H24: 1400 | I24: 4.1 | J24: Ordenamiento Territorial Inteligente | K24: 4.1.2 | L24: Garantizar al 100% las acciones de implementación del PEMP programadas para el cuatrienio | M24: Porcentaje de acciones de garantizadas | N24: 0 | O24: 4002015 | P24: 2024257990004 | Q24: Implementación del Desarrollo Urbano y Ordenamiento Territorial Inteligente en el Municipio de Tenjo Cundinamarca | R24: 23 | S24: Ejecutar el 30% del Plan Especial de Manejo y Protección PEMP con base en lineamientos de MinCultura | T24: SD | U24: Porcentaje | V24: I | W24: PEMP actualizado | X24: Sec. de Planeación y Desarrollo Territorial | Z24: =SUM(AF24:AI24) -> 0.3 | AA24: =AS24/Z24 -> 0.33333333 | AB24: =BI24/Z24 -> 2.8333333 | AE24: =SUMPRODUCT(AA24:AD24, {0.15,0.35,0.35,0.15}) -> 1.0416667 | AF24: 0.1 | AG24: 0.1 | AH24: 0.05 | AI24: 0.05 | AN24: 0.05 | AO24: 0.05 | AP24: 0.05 | AQ24: 0.05 | AR24: =(AJ24+AL24+AN24+AP24) -> 0.1 | AS24: =(AK24+AM24+AO24+AQ24) -> 0.1 | AT24: =AS24/AR24 -> 1 | AU24: =MIN((AR24 /AR24) * 100, 100) & "%" -> 100% | AV24: =IF(AR24=0, 0, AS24/AR24) -> 1 | AW24: P | AX24: Meta 23.docx | AY24: 0.025 | AZ24: 0.025 | BA24: 0.025 | BB24: 0.025 | BC24: 0.035 | BD24: 0.035 | BE24: 0.015 | BG24: =(AY24+BA24+BC24+BE24) -> 0.1 | BH24: =(AZ24+BB24+BD24+BF24) -> 0.085 | BI24: =BH24/BG24 -> 0.85 | BJ24: =MIN((BG24 /BG24) * 100, 100) & "%" -> 100% | BK24: =IF(BG24=0, 0, BH24/BG24) -> 0.85 | BL24: P | BM24: Meta 23.docx | BN24: 55000000 | BO24: 47700000 | BP24: 16500000 | BQ24: 16500000 | BR24: =+BN24+BP24 -> 71500000 | BS24: =+BO24+BQ24 -> 64200000 | BT24: =IFERROR(BS24/BR24, "") -> 0.8979021 | BU24: 55000000 | BV24: 55000000 | BW24: 47700000 | BX24: 34350000 | BY24: =IFERROR(BW24/BV24, "") -> 0.86727273 | BZ24: 40000000 | CA24: 40800000 | CB24: 41616000 | CC24: 42864480 | CD24: 165280480
A25: Eje 1. Ambiente, Conectividad y Ordenamiento y servicios públicos | B25: 0.235 | D25: 40 | E25: 4002 | F25: 4 | G25: Ordenamiento Territorial y Desarrollo Urbano Inteligente y Sostenible-OTEDUS (Ordenamiento territorial y desarrollo urbano) | H25: 1400 | I25: 4.1 | J25: Ordenamiento Territorial Inteligente | K25: 4.1.2 | L25: Garantizar al 100% las acciones de implementación del PEMP programadas para el cuatrienio | M25: Porcentaje de acciones de garantizadas | N25: 0 | O25: 4002023 | P25: 2024257990004 | Q25: Implementación del Desarrollo Urbano y Ordenamiento Territorial Inteligente en el Municipio de Tenjo Cundinamarca | R25: 24 | S25: Modernizar la infraestructura física del Parque Principal optimizando la actividad turística y el valor patrimonial del municipio de Tenjo en concordancia con el PEMP | T25: 0 | U25: Número | V25: I | W25: Número de parques modernizados | X25: Sec. Infraestructura y Obra Pública | Z25: =SUM(AF25:AI25) -> 1 | AA25: =AS25/Z25 -> 0 | AB25: =BI25/Z25 -> 0.85 | AE25: =SUMPRODUCT(AA25:AD25, {0.15,0.35,0.35,0.15}) -> 0.2975 | AF25: 0 | AG25: 0.2 | AH25: 0.7 | AI25: 0.1 | AN25: 0 | AO25: 0 | AP25: 0 | AQ25: 0 | AR25: 0 | AS25: 0 | AT25: 0 | AU25: =IF(AR25> 1, IF(AR25 = AS25, "100%", AR25 & "%"), IF(AR25 <= 0.01, "0%", AR25 * 100 & "%")) -> 0% | AV25: =IF(AR25=0, 0, AS25/AR25) -> 0 | AW25: NP | AY25: 0.02 | AZ25: 0.02 | BA25: 0.03 | BB25: 0.03 | BC25: 0.12 | BD25: 0.12 | BE25: 0.03 | BG25: =(AY25+BA25+BC25+BE25) -> 0.2 | BH25: =(AZ25+BB25+BD25+BF25) -> 0.17 | BI25: =BH25/BG25 -> 0.85 | BJ25: =MIN((BG25 /BG25) * 100, 100) & "%" -> 100% | BK25: =IF(BG25=0, 0, BH25/BG25) -> 0.85 | BL25: P | BM25: Meta 24.docx | BN25: 50000000 | BO25: 0 | BP25: 0 | BQ25: 0 | BR25: =+BN25+BP25 -> 50000000 | BS25: =+BO25+BQ25 -> 0 | BT25: =IFERROR(BS25/BR25, "") -> 0 | BU25: 50000000 | BV25: 50000000 | BW25: 50000000 | BX25: 0 | BY25: =IFERROR(BW25/BV25, "") -> 1 | BZ25: 0 | CA25: 0 | CB25: 0 | CC25: 200000000 | CD25: 200000000
A26: Eje 1. Ambiente, Conectividad y Ordenamiento y servicios públicos | B26: 0.235 | D26: 40 | E26: 4003 | F26: 5 | G26: Programa Integral de Innovación de Servicios Públicos de Acuedcto, Alcantarillado y Aseo (PISAAA) (Acceso de la población a los servicios de agua potable y saneamiento básico) | H26: 1400 | I26: 5.1 | J26: Es el tiempo de Agua Potable con Calidad | K26: 5.1.1 | L26: Incrementar al 99% la calidad y continuidad del servicio de acueducto | M26: Porcentaje de calidad y continuidad del servicios de acueducto incrementado | N26: % en el municipio 97,93 % en la cabecera municipal 99,58 % Centros poblados y rural disperso 96,73 Fuente: Dane.mapa.argis.com | O26: 4003017 | P26: 2024257990005 | Q26: Optimización del programa integral para el acceso de la población a los serivicios de agua potable y saneamiento básico en el municipio de Tenjo Cundinamarca | R26: 25 | S26: Optimizar 27 km de redes de acueducto | T26: 2 km | U26: Km | V26: M | W26: Km de redes de acueducto optimizadas | X26: Sec. Infraestructura y Obra Pública | Y26: SI | Z26: =SUM(AF26:AI26) -> 27 | AA26: =AS26/Z26 -> 0.22222222 | AB26: =BI26/Z26 -> 0.03 | AE26: =SUMPRODUCT(AA26:AD26, {0.15,0.35,0.35,0.15}) -> 0.043833333 | AF26: 6 | AG26: 10 | AH26: 6 | AI26: 5 | AN26: 0.001 | AO26: 0 | AP26: 6 | AQ26: 6 | AR26: =(AJ26+AL26+AN26+AP26) -> 6.001 | AS26: =(AK26+AM26+AO26+AQ26) -> 6 | AT26: =AS26/AR26 -> 0.99983336 | AU26: =MIN((AR26 /AR26) * 100, 100) & "%" -> 100% | AV26: =IF(AR26=0, 0, AS26/AR26) -> 0.99983336 | AW26: P | AX26: META 25.docx | AY26: 0.2 | AZ26: 0.2 | BA26: 0.1 | BB26: 0.2 | BC26: 7.7 | BD26: 7.7 | BE26: 2 | BG26: =(AY26+BA26+BC26+BE26) -> 10 | BH26: =(AZ26+BB26+BD26+BF26) -> 8.1 | BI26: =BH26/BG26 -> 0.81 | BJ26: =MIN((BG26 /BG26) * 100, 100) & "%" -> 100% | BK26: =IF(BG26=0, 0, BH26/BG26) -> 0.81 | BL26: P | BM26: Meta 25.docx | BN26: 400000000 | BO26: 86925000 | BP26: 1323000000 | BQ26: 1323000000 | BR26: =+BN26+BP26 -> 1723000000 | BS26: =+BO26+BQ26 -> 1409925000 | BT26: =IFERROR(BS26/BR26, "") -> 0.81829658 | BU26: 100000000 | BV26: 400000000 | BW26: 86925000 | BX26: 65487500 | BY26: =IFERROR(BW26/BV26, "") -> 0.2173125 | BZ26: 800000000 | CA26: 900000000 | CB26: 0 | CC26: 1166398880 | CD26: 2866398880
A27: Eje 1. Ambiente, Conectividad y Ordenamiento y servicios públicos | B27: 0.235 | D27: 40 | E27: 4003 | F27: 5 | G27: Programa Integral de Innovación de Servicios Públicos de Acuedcto, Alcantarillado y Aseo (PISAAA) (Acceso de la población a los servicios de agua potable y saneamiento básico) | H27: 1400 | I27: 5.1 | J27: Es el tiempo de Agua Potable con Calidad | K27: 5.1.1 | L27: Incrementar al 99% la calidad y continuidad del servicio de acueducto | M27: Porcentaje de calidad y continuidad del servicios de acueducto incrementado | N27: % en el municipio 97,93 % en la cabecera municipal 99,58 % Centros poblados y rural disperso 96,73 Fuente: Dane.mapa.argis.com | O27: 4003009 | P27: 2024257990005 | Q27: Optimización del programa integral para el acceso de la población a los serivicios de agua potable y saneamiento básico en el municipio de Tenjo Cundinamarca | R27: 26 | S27: Optimizar la macromedición y sectorización al 80% en el municipio de Tenjo en las redes de acueducto. | T27: 7,75% | U27: Porcentaje | V27: I | W27: Porcentaje de macro medición y sectorización optimizadas | X27: Sec. Infraestructura y Obra Pública | Y27: SI | Z27: =SUM(AF27:AI27) -> 0.8 | AA27: =AS27/Z27 -> 0.375 | AB27: =BI27/Z27 -> 0.625 | AE27: =SUMPRODUCT(AA27:AD27, {0.15,0.35,0.35,0.15}) -> 0.275 | AF27: 0.3 | AG27: 0.4 | AH27: 0.1 | AI27: 0 | AN27: 1e-05 | AO27: 0 | AP27: 0.3 | AQ27: 0.3 | AR27: =(AJ27+AL27+AN27+AP27) -> 0.30001 | AS27: =(AK27+AM27+AO27+AQ27) -> 0.3 | AT27: =AS27/AR27 -> 0.99996667 | AU27: =MIN((AR27 /AR27) * 100, 100) & "%" -> 100% | AV27: =IF(AR27=0, 0, AS27/AR27) -> 0.99996667 | AW27: P | AX27: META 26.docx | AY27: 0 | AZ27: 0 | BA27: 0 | BB27: 0 | BC27: 0.2 | BD27: 0.2 | BE27: 0.2 | BG27: =(AY27+BA27+BC27+BE27) -> 0.4 | BH27: =(AZ27+BB27+BD27+BF27) -> 0.2 | BI27: =BH27/BG27 -> 0.5 | BJ27: =MIN((BG27 /BG27) * 100, 100) & "%" -> 100% | BK27: =IF(BG27=0, 0, BH27/BG27) -> 0.5 | BL27: P | BM27: Meta 26.docx | BN27: 100000000 | BO27: 0 | BP27: 800000000 | BQ27: 800000000 | BR27: =+BN27+BP27 -> 900000000 | BS27: =+BO27+BQ27 -> 800000000 | BT27: =IFERROR(BS27/BR27, "") -> 0.88888889 | BU27: 100000000 | BV27: 100000000 | BW27: 0 | BX27: 0 | BY27: =IFERROR(BW27/BV27, "") -> 0 | BZ27: 125000000 | CA27: 100000000 | CB27: 120000000 | CC27: 125000000 | CD27: 470000000
A28: Eje 1. Ambiente, Conectividad y Ordenamiento y servicios públicos | B28: 0.235 | D28: 40 | E28: 4003 | F28: 5 | G28: Programa Integral de Innovación de Servicios Públicos de Acuedcto, Alcantarillado y Aseo (PISAAA) (Acceso de la población a los servicios de agua potable y saneamiento básico) | H28: 1400 | I28: 5.1 | J28: Es el tiempo de Agua Potable con Calidad | K28: 5.1.1 | L28: Incrementar al 99% la calidad y continuidad del servicio de acueducto | M28: Porcentaje de calidad y continuidad del servicios de acueducto incrementado | N28: % en el municipio 97,93 % en la cabecera municipal 99,58 % Centros poblados y rural disperso 96,73 Fuente: Dane.mapa.argis.com | O28: 4003009 | P28: 2024257990005 | Q28: Optimización del programa integral para el acceso de la población a los serivicios de agua potable y saneamiento básico en el municipio de Tenjo Cundinamarca | R28: 27 | S28: Optimizar la micro medición telemétrica para 3500 usuarios de la Empresa de Servicios Públicos de Tenjo – EMSERTENJO | T28: 0 | U28: Número | V28: I | W28: Número de usuarios con optimización telemétrica | X28: Sec. Infraestructura y Obra Pública | Y28: SI | Z28: =SUM(AF28:AI28) -> 3500 | AA28: =AS28/Z28 -> 0 | AB28: =BI28/Z28 -> 0 | AE28: =SUMPRODUCT(AA28:AD28, {0.15,0.35,0.35,0.15}) -> 0 | AF28: 0 | AG28: 1000 | AH28: 2000 | AI28: 500 | AN28: 0 | AO28: 0 | AP28: 0 | AQ28: 0 | AR28: 0 | AS28: =(AK28+AM28+AO28+AQ28)/2 -> 0 | AT28: =IF(AQ28=0, 0, AR28/AQ28) -> 0 | AU28: =IF(AR28> 1, IF(AR28 = AS28, "100%", AR28 & "%"), IF(AR28 <= 0.01, "0%", AR28 * 100 & "%")) -> 0% | AV28: =IF(AR28=0, 0, AS28/AR28) -> 0 | AW28: NP | AY28: 0 | BA28: 0 | BC28: 0 | BE28: 0 | BG28: =(AY28+BA28+BC28+BE28) -> 0 | BH28: =(AZ28+BB28+BD28+BF28) -> 0 | BI28: =IF(BF28> 1, IF(BF28 = BG28, "100%", BF28 & "%"), IF(BF28 <= 0.01, "0%", BF28 * 100 & "%")) -> 0% | BJ28: =IF(BF28=0, 0, BG28/BF28) -> 0 | BK28: =IF(BG28=0, 0, BH28/BG28) -> 0 | BL28: NP | BM28: Meta 27.docx | BN28: 0 | BO28: 0 | BP28: 0 | BQ28: 0 | BR28: =+BN28+BP28 -> 0 | BS28: =+BO28+BQ28 -> 0 | BT28: =IFERROR(BS28/BR28, "") | BU28: 0 | BV28: 0 | BW28: 0 | BX28: 0 | BY28: =IFERROR(BW28/BV28, "") | BZ28: 110000000 | CA28: 0 | CB28: 0 | CC28: 0 | CD28: 110000000
A29: Eje 1. Ambiente, Conectividad y Ordenamiento y servicios públicos | B29: 0.235 | D29: 40 | E29: 4003 | F29: 5 | G29: Programa Integral de Innovación de Servicios Públicos de Acuedcto, Alcantarillado y Aseo (PISAAA) (Acceso de la población a los servicios de agua potable y saneamiento básico) | H29: 1400 | I29: 5.1 | J29: Es el tiempo de Agua Potable con Calidad | K29: 5.1.1 | L29: Incrementar al 99% la calidad y continuidad del servicio de acueducto | M29: Porcentaje de calidad y continuidad del servicios de acueducto incrementado | N29: % en el municipio 97,93 % en la cabecera municipal 99,58 % Centros poblados y rural disperso 96,73 Fuente: Dane.mapa.argis.com | O29: 4003017 | P29: 2024257990005 | Q29: Optimización del programa integral para el acceso de la población a los serivicios de agua potable y saneamiento básico en el municipio de Tenjo Cundinamarca | R29: 28 | S29: Construir 4 tanques de almacenamiento de agua potable para la distribución y continuidad del servicio en la zona rural del municipio | T29: 1 | U29: Número | V29: I | W29: Tanques de almacenamiento construidos | X29: Sec. Infraestructura y Obra Pública | Y29: SI | Z29: =SUM(AF29:AI29) -> 4 | AA29: =AS29/Z29 -> 0.05 | AB29: =BI29/Z29 -> 0.25 | AE29: =SUMPRODUCT(AA29:AD29, {0.15,0.35,0.35,0.15}) -> 0.095 | AF29: 1 | AG29: 1 | AH29: 1 | AI29: 1 | AN29: 0.1 | AO29: 0.1 | AP29: 0.1 | AQ29: 0.1 | AR29: =(AJ29+AL29+AN29+AP29) -> 0.2 | AS29: =(AK29+AM29+AO29+AQ29) -> 0.2 | AT29: =AS29/AR29 -> 1 | AU29: =MIN((AR29 /AR29) * 100, 100) & "%" -> 100% | AV29: =IF(AR29=0, 0, AS29/AR29) -> 1 | AW29: P | AX29: META 28.docx | AY29: 0 | AZ29: 0 | BA29: 0.86 | BB29: 0.86 | BC29: 0.14 | BD29: 0.14 | BE29: 0 | BG29: =(AY29+BA29+BC29+BE29) -> 1 | BH29: =(AZ29+BB29+BD29+BF29) -> 1 | BI29: =BH29/BG29 -> 1 | BJ29: =MIN((BG29 /BG29) * 100, 100) & "%" -> 100% | BK29: =IF(BG29=0, 0, BH29/BG29) -> 1 | BL29: P | BM29: Meta 28.docx | BN29: 850000000 | BO29: 0 | BP29: 1100000000 | BQ29: 1100000000 | BR29: =+BN29+BP29 -> 1950000000 | BS29: =+BO29+BQ29 -> 1100000000 | BT29: =IFERROR(BS29/BR29, "") -> 0.56410256 | BU29: 350000000 | BV29: 850000000 | BW29: 849627668 | BX29: 849627668 | BY29: =IFERROR(BW29/BV29, "") -> 0.99956196 | BZ29: 400000000 | CA29: 430000000 | CB29: 450000000 | CC29: 470000000 | CD29: 1750000000
A30: Eje 1. Ambiente, Conectividad y Ordenamiento y servicios públicos | B30: 0.235 | D30: 40 | E30: 4003 | F30: 5 | G30: Programa Integral de Innovación de Servicios Públicos de Acuedcto, Alcantarillado y Aseo (PISAAA) (Acceso de la población a los servicios de agua potable y saneamiento básico) | H30: 1400 | I30: 5.1 | J30: Es el tiempo de Agua Potable con Calidad | K30: 5.1.1 | L30: Incrementar al 99% la calidad y continuidad del servicio de acueducto | M30: Porcentaje de calidad y continuidad del servicios de acueducto incrementado | N30: % en el municipio 97,93 % en la cabecera municipal 99,58 % Centros poblados y rural disperso 96,73 Fuente: Dane.mapa.argis.com | O30: 4003017 | P30: 2024257990005 | Q30: Optimización del programa integral para el acceso de la población a los serivicios de agua potable y saneamiento básico en el municipio de Tenjo Cundinamarca | R30: 29 | S30: Realizar los estudios tecnicos y diseños que garanticen la extracción de agua de un pozo profundo | T30: 0 | U30: Número | V30: I | W30: Estudios técnicos y diseños realizados | X30: Sec. Infraestructura y Obra Pública | Y30: SI | Z30: =SUM(AF30:AI30) -> 1 | AA30: =AS30/Z30 -> 0.6 | AB30: =BI30/Z30 -> 0 | AE30: =SUMPRODUCT(AA30:AD30, {0.15,0.35,0.35,0.15}) -> 0.09 | AF30: 1 | AG30: 0 | AH30: 0 | AI30: 0 | AN30: 0.1 | AO30: 0.1 | AP30: 0.9 | AQ30: 0.5 | AR30: =(AJ30+AL30+AN30+AP30) -> 1 | AS30: =(AK30+AM30+AO30+AQ30) -> 0.6 | AT30: =AS30/AR30 -> 0.6 | AU30: =MIN((AR30 /AR30) * 100, 100) & "%" -> 100% | AV30: =IF(AR30=0, 0, AS30/AR30) -> 0.6 | AW30: P | AX30: META 29.docx | AY30: 0 | BA30: 0 | BC30: 0 | BE30: 0 | BG30: =(AY30+BA30+BC30+BE30) -> 0 | BH30: =(AZ30+BB30+BD30+BF30) -> 0 | BI30: =IF(BF30> 1, IF(BF30 = BG30, "100%", BF30 & "%"), IF(BF30 <= 0.01, "0%", BF30 * 100 & "%")) -> 0% | BJ30: =IF(BF30=0, 0, BG30/BF30) -> 0 | BK30: =IF(BG30=0, 0, BH30/BG30) -> 0 | BL30: NP | BM30: Meta 29.docx | BN30: 20780404 | BO30: 0 | BP30: 1200000000 | BQ30: 1200000000 | BR30: =+BN30+BP30 -> 1220780404 | BS30: =+BO30+BQ30 -> 1200000000 | BT30: =IFERROR(BS30/BR30, "") -> 0.98297777 | BU30: 0 | BV30: 0 | BW30: 0 | BX30: 0 | BY30: =IFERROR(BW30/BV30, "") | BZ30: 1000000000 | CA30: 0 | CB30: 0 | CC30: 0 | CD30: 1000000000
A31: Eje 1. Ambiente, Conectividad y Ordenamiento y servicios públicos | B31: 0.235 | D31: 40 | E31: 4003 | F31: 5 | G31: Programa Integral de Innovación de Servicios Públicos de Acuedcto, Alcantarillado y Aseo (PISAAA) (Acceso de la población a los servicios de agua potable y saneamiento básico) | H31: 1400 | I31: 5.1 | J31: Es el tiempo de Agua Potable con Calidad | K31: 5.1.1 | L31: Incrementar al 99% la calidad y continuidad del servicio de acueducto | M31: Porcentaje de calidad y continuidad del servicios de acueducto incrementado | N31: % en el municipio 97,93 % en la cabecera municipal 99,58 % Centros poblados y rural disperso 96,73 Fuente: Dane.mapa.argis.com | O31: 4003053 | P31: 2024257990005 | Q31: Optimización del programa integral para el acceso de la población a los serivicios de agua potable y saneamiento básico en el municipio de Tenjo Cundinamarca | R31: 30 | S31: Mejorar al 100% la capacidad de equipos de bombeo y potabilización | T31: 0.8 | U31: Porcentaje | V31: I | W31: Porcentaje de capacidad mejorada | X31: Sec. Infraestructura y Obra Pública | Y31: SI | Z31: =SUM(AF31:AI31)/4 -> 1 | AA31: =AS31/Z31 -> 1 | AB31: =BI31/Z31 -> 1 | AE31: =SUMPRODUCT(AA31:AD31, {0.15,0.35,0.35,0.15}) -> 0.5 | AF31: 1 | AG31: 1 | AH31: 1 | AI31: 1 | AN31: 0.1 | AO31: 0.1 | AP31: 0.9 | AQ31: 0.9 | AR31: =(AJ31+AL31+AN31+AP31) -> 1 | AS31: =(AK31+AM31+AO31+AQ31) -> 1 | AT31: =AS31/AR31 -> 1 | AU31: =MIN((AR31 /AR31) * 100, 100) & "%" -> 100% | AV31: =IF(AR31=0, 0, AS31/AR31) -> 1 | AW31: P | AX31: META 30.docx | AY31: 0 | AZ31: 0 | BA31: 0.05 | BB31: 0.05 | BC31: 0.05 | BD31: 0.05 | BE31: 0 | BG31: =(AY31+BA31+BC31+BE31) -> 0.1 | BH31: =(AZ31+BB31+BD31+BF31) -> 0.1 | BI31: =BH31/BG31 -> 1 | BJ31: =MIN((BG31 /BG31) * 100, 100) & "%" -> 100% | BK31: =IF(BG31=0, 0, BH31/BG31) -> 1 | BL31: P | BM31: Meta 30.docx | BN31: 400000000 | BO31: 0 | BP31: 1100000000 | BQ31: 1100000000 | BR31: =+BN31+BP31 -> 1500000000 | BS31: =+BO31+BQ31 -> 1100000000 | BT31: =IFERROR(BS31/BR31, "") -> 0.73333333 | BU31: 400000000 | BV31: 420780404 | BW31: 0 | BX31: 0 | BY31: =IFERROR(BW31/BV31, "") -> 0 | BZ31: 60000000 | CA31: 0 | CB31: 0 | CC31: 0 | CD31: 60000000
A32: Eje 1. Ambiente, Conectividad y Ordenamiento y servicios públicos | B32: 0.235 | D32: 40 | E32: 4003 | F32: 5 | G32: Programa Integral de Innovación de Servicios Públicos de Acuedcto, Alcantarillado y Aseo (PISAAA) (Acceso de la población a los servicios de agua potable y saneamiento básico) | H32: 1400 | I32: 5.1 | J32: Es el tiempo de Agua Potable con Calidad | K32: 5.1.1 | L32: Incrementar al 99% la calidad y continuidad del servicio de acueducto | M32: Porcentaje de calidad y continuidad del servicios de acueducto incrementado | N32: % en el municipio 97,93 % en la cabecera municipal 99,58 % Centros poblados y rural disperso 96,73 Fuente: Dane.mapa.argis.com | O32: 4003017 | P32: 2024257990005 | Q32: Optimización del programa integral para el acceso de la población a los serivicios de agua potable y saneamiento básico en el municipio de Tenjo Cundinamarca | R32: 31 | S32: Ampliar mínimo en 60% la capacidad de almacenaje de agua potable de los tanques existentes | T32: 0 | U32: Porcentaje | V32: I | W32: Porcentaje de capacidad ampliada | X32: Sec. Infraestructura y Obra Pública | Y32: SI | Z32: =SUM(AF32:AI32) -> 0.6 | AA32: =AS32/Z32 -> 0 | AB32: =BI32/Z32 -> 1.6666667 | AE32: =SUMPRODUCT(AA32:AD32, {0.15,0.35,0.35,0.15}) -> 0.58333333 | AF32: 0 | AG32: 0.1 | AH32: 0.4 | AI32: 0.1 | AN32: 0 | AO32: 0 | AP32: 0 | AQ32: 0 | AR32: 0 | AS32: =(AK32+AM32+AO32+AQ32)/2 -> 0 | AT32: =IF(AQ32=0, 0, AR32/AQ32) -> 0 | AU32: =IF(AR32> 1, IF(AR32 = AS32, "100%", AR32 & "%"), IF(AR32 <= 0.01, "0%", AR32 * 100 & "%")) -> 0% | AV32: =IF(AR32=0, 0, AS32/AR32) -> 0 | AW32: NP | AY32: 0 | AZ32: 0 | BA32: 0.03 | BB32: 0.03 | BC32: 0.07 | BD32: 0.07 | BE32: 0 | BG32: =(AY32+BA32+BC32+BE32) -> 0.1 | BH32: =(AZ32+BB32+BD32+BF32) -> 0.1 | BI32: =BH32/BG32 -> 1 | BJ32: =MIN((BG32 /BG32) * 100, 100) & "%" -> 100% | BK32: =IF(BG32=0, 0, BH32/BG32) -> 1 | BL32: P | BM32: Meta 31.docx | BN32: 300000000 | BO32: 0 | BP32: 0 | BQ32: 0 | BR32: =+BN32+BP32 -> 300000000 | BS32: =+BO32+BQ32 -> 0 | BT32: =IFERROR(BS32/BR32, "") -> 0 | BU32: 300000000 | BV32: 300000000 | BW32: 0 | BX32: 0 | BY32: =IFERROR(BW32/BV32, "") -> 0 | BZ32: 200000000 | CA32: 204000000 | CB32: 200000000 | CC32: 206000000 | CD32: 810000000
A33: Eje 1. Ambiente, Conectividad y Ordenamiento y servicios públicos | B33: 0.235 | D33: 40 | E33: 4003 | F33: 5 | G33: Programa Integral de Innovación de Servicios Públicos de Acuedcto, Alcantarillado y Aseo (PISAAA) (Acceso de la población a los servicios de agua potable y saneamiento básico) | H33: 1400 | I33: 5.1 | J33: Es el tiempo de Agua Potable con Calidad | K33: 5.1.1 | L33: Incrementar al 99% la calidad y continuidad del servicio de acueducto | M33: Porcentaje de calidad y continuidad del servicios de acueducto incrementado | N33: % en el municipio 97,93 % en la cabecera municipal 99,58 % Centros poblados y rural disperso 96,73 Fuente: Dane.mapa.argis.com | O33: 4003038 | P33: 2024257990005 | Q33: Optimización del programa integral para el acceso de la población a los serivicios de agua potable y saneamiento básico en el municipio de Tenjo Cundinamarca | R33: 32 | S33: Actualizar el catastro de usuarios del municipio | T33: 1 | U33: Número | V33: M | W33: Catastro de usuarios redes realizado | X33: Sec. Infraestructura y Obra Pública | Y33: SI | Z33: =SUM(AF33:AI33) -> 1 | AA33: =AS33/Z33 -> 0.3 | AB33: =BI33/Z33 -> 0 | AE33: =SUMPRODUCT(AA33:AD33, {0.15,0.35,0.35,0.15}) -> 0.045 | AF33: 0.3 | AG33: 0.7 | AH33: 0 | AI33: 0 | AN33: 0.2 | AO33: 0.2 | AP33: 0.8 | AQ33: 0.1 | AR33: =(AJ33+AL33+AN33+AP33) -> 1 | AS33: =(AK33+AM33+AO33+AQ33) -> 0.3 | AT33: =AS33/AR33 -> 0.3 | AU33: =MIN((AR33 /AR33) * 100, 100) & "%" -> 100% | AV33: =IF(AR33=0, 0, AS33/AR33) -> 0.3 | AW33: P | AX33: META 32.docx | AY33: 0 | AZ33: 0 | BA33: 0 | BB33: 0 | BC33: 0 | BE33: 0 | BG33: =(AY33+BA33+BC33+BE33) -> 0 | BH33: =(AZ33+BB33+BD33+BF33) -> 0 | BI33: =IF(BF33> 1, IF(BF33 = BG33, "100%", BF33 & "%"), IF(BF33 <= 0.01, "0%", BF33 * 100 & "%")) -> 0% | BJ33: =IF(BF33=0, 0, BG33/BF33) -> 0 | BK33: =IF(BG33=0, 0, BH33/BG33) -> 0 | BL33: NP | BM33: Meta 32.docx | BN33: 0 | BO33: 0 | BP33: 1300000000 | BQ33: 1300000000 | BR33: =+BN33+BP33 -> 1300000000 | BS33: =+BO33+BQ33 -> 1300000000 | BT33: =IFERROR(BS33/BR33, "") -> 1 | BU33: 0 | BV33: 0 | BW33: 0 | BX33: 0 | BY33: =IFERROR(BW33/BV33, "") | BZ33: 800000000 | CA33: 0 | CB33: 0 | CC33: 0 | CD33: 800000000
A34: Eje 1. Ambiente, Conectividad y Ordenamiento y servicios públicos | B34: 0.235 | D34: 40 | E34: 4003 | F34: 5 | G34: Programa Integral de Innovación de Servicios Públicos de Acuedcto, Alcantarillado y Aseo (PISAAA) (Acceso de la población a los servicios de agua potable y saneamiento básico) | H34: 1400 | I34: 5.1 | J34: Es el tiempo de Agua Potable con Calidad | K34: 5.1.1 | L34: Incrementar al 99% la calidad y continuidad del servicio de acueducto | M34: Porcentaje de calidad y continuidad del servicios de acueducto incrementado | N34: % en el municipio 97,93 % en la cabecera municipal 99,58 % Centros poblados y rural disperso 96,73 Fuente: Dane.mapa.argis.com | O34: 4003016 | P34: 2024257990005 | Q34: Optimización del programa integral para el acceso de la población a los serivicios de agua potable y saneamiento básico en el municipio de Tenjo Cundinamarca | R34: 33 | S34: Incrementar a 4000 metros lineales de redes de acueducto del municipio | T34: 2000 mts | U34: Mts | V34: I | W34: Metros lineales de redes de acueducto ampliadas | X34: Sec. Infraestructura y Obra Pública | Y34: SI | Z34: =SUM(AF34:AI34) -> 4000 | AA34: =AS34/Z34 -> 0.075 | AB34: =BI34/Z34 -> 0.00025 | AE34: =SUMPRODUCT(AA34:AD34, {0.15,0.35,0.35,0.15}) -> 0.0113375 | AF34: 1000 | AG34: 1000 | AH34: 1000 | AI34: 1000 | AN34: 200 | AO34: 200 | AP34: 1000 | AQ34: 100 | AR34: =(AJ34+AL34+AN34+AP34) -> 1200 | AS34: =(AK34+AM34+AO34+AQ34) -> 300 | AT34: =AS34/AR34 -> 0.25 | AU34: =MIN((AR34 /AR34) * 100, 100) & "%" -> 100% | AV34: =IF(AR34=0, 0, AS34/AR34) -> 0.25 | AW34: P | AX34: META 33.docx | AY34: 0 | AZ34: 0 | BA34: 0 | BB34: 0 | BC34: 100 | BD34: 100 | BE34: 0 | BG34: =(AY34+BA34+BC34+BE34)*0.1 -> 10 | BH34: =(AZ34+BB34+BD34+BF34)*0.1 -> 10 | BI34: =BH34/BG34 -> 1 | BJ34: =MIN((BG34 /BG34) * 100, 100) & "%" -> 100% | BK34: =IF(BG34=0, 0, BH34/BG34) -> 1 | BL34: P | BM34: Meta 33.docx | BN34: 300000000 | BO34: 0 | BP34: 159200788 | BQ34: 159200788 | BR34: =+BN34+BP34 -> 459200788 | BS34: =+BO34+BQ34 -> 159200788 | BT34: =IFERROR(BS34/BR34, "") -> 0.34669102 | BU34: 300000000 | BV34: 300000000 | BW34: 0 | BX34: 0 | BY34: =IFERROR(BW34/BV34, "") -> 0 | BZ34: 500000000 | CA34: 394325070 | CB34: 417174986 | CC34: 0 | CD34: 1311500055
A35: Eje 1. Ambiente, Conectividad y Ordenamiento y servicios públicos | B35: 0.235 | D35: 40 | E35: 4003 | F35: 5 | G35: Programa Integral de Innovación de Servicios Públicos de Acuedcto, Alcantarillado y Aseo (PISAAA) (Acceso de la población a los servicios de agua potable y saneamiento básico) | H35: 1400 | I35: 5.1 | J35: Es el tiempo de Agua Potable con Calidad | K35: 5.1.1 | L35: Incrementar al 99% la calidad y continuidad del servicio de acueducto | M35: Porcentaje de calidad y continuidad del servicios de acueducto incrementado | N35: % en el municipio 97,93 % en la cabecera municipal 99,58 % Centros poblados y rural disperso 96,73 Fuente: Dane.mapa.argis.com | O35: 4003048 | P35: 2024257990005 | Q35: Optimización del programa integral para el acceso de la población a los serivicios de agua potable y saneamiento básico en el municipio de Tenjo Cundinamarca | R35: 34 | S35: Desarrollar un proceso de adquisición de equipos tecnologícos y de transporte de agua que garanticen el acceso universal al liquido en el municipio | T35: 0 | U35: Número | V35: I | W35: Proceso de adquisición desarrollado | X35: Sec. Infraestructura y Obra Pública | Y35: SI | Z35: =SUM(AF35:AI35) -> 1 | AA35: =AS35/Z35 -> 1 | AB35: =BI35/Z35 -> 1 | AE35: =SUMPRODUCT(AA35:AD35, {0.15,0.35,0.35,0.15}) -> 0.5 | AF35: 0.5 | AG35: 0.5 | AH35: 0 | AI35: 0 | AN35: 0.1 | AO35: 0.1 | AP35: 0.9 | AQ35: 0.9 | AR35: =(AJ35+AL35+AN35+AP35) -> 1 | AS35: =(AK35+AM35+AO35+AQ35) -> 1 | AT35: =AS35/AR35 -> 1 | AU35: =MIN((AR35 /AR35) * 100, 100) & "%" -> 100% | AV35: =IF(AR35=0, 0, AS35/AR35) -> 1 | AW35: P | AX35: META 34.docx | AY35: 0 | AZ35: 0 | BA35: 0.01 | BB35: 0.01 | BC35: 0.01 | BD35: 0.01 | BE35: 0.02 | BF35: 0.02 | BG35: =(AY35+BA35+BC35+BE35) -> 0.04 | BH35: =(AZ35+BB35+BD35+BF35) -> 0.04 | BI35: =BH35/BG35 -> 1 | BJ35: =MIN((BG35 /BG35) * 100, 100) & "%" -> 100% | BK35: =IF(BG35=0, 0, BH35/BG35) -> 1 | BL35: P | BM35: Meta 34.docx | BN35: 130000000 | BO35: 0 | BP35: 824441743 | BQ35: 824441743 | BR35: =+BN35+BP35 -> 954441743 | BS35: =+BO35+BQ35 -> 824441743 | BT35: =IFERROR(BS35/BR35, "") -> 0.86379473 | BU35: 130000000 | BV35: 130000000 | BW35: 0 | BX35: 0 | BY35: =IFERROR(BW35/BV35, "") -> 0 | BZ35: 700000000 | CC35: 0 | CD35: 700000000
A36: Eje 1. Ambiente, Conectividad y Ordenamiento y servicios públicos | B36: 0.235 | D36: 40 | E36: 4003 | F36: 5 | G36: Programa Integral de Innovación de Servicios Públicos de Acuedcto, Alcantarillado y Aseo (PISAAA) (Acceso de la población a los servicios de agua potable y saneamiento básico) | H36: 1400 | I36: 5.1 | J36: Es el tiempo de Agua Potable con Calidad | K36: 5.1.2 | L36: Ejecutar al 100% la acciones de inspección, vigilancia, control y ahorro de agua | M36: Porcentaje de acciones de inspección, vigilancia, control y ahorro del agua ejecutadas | N36: 0.91 | O36: 4003009 | P36: 2024257990005 | Q36: Optimización del programa integral para el acceso de la población a los serivicios de agua potable y saneamiento básico en el municipio de Tenjo Cundinamarca | R36: 35 | S36: Ejecutar al 100% acciones de vigilancia y control de la calidad del agua para el consumo humano | T36: 1 | U36: Porcentaje | V36: M | W36: Porcentaje de acciones de vigilancia y control ejecutadas | X36: Empresa de Servicios Públicos de Tenjo EMSERTENJO SA ESP | Y36: SI | Z36: =SUM(AF36:AI36)/4 -> 1 | AA36: =AS36/Z36 -> 0.975 | AB36: =BI36/Z36 -> 0.45 | AE36: =SUMPRODUCT(AA36:AD36, {0.15,0.35,0.35,0.15}) -> 0.30375 | AF36: 1 | AG36: 1 | AH36: 1 | AI36: 1 | AN36: 1 | AO36: 1 | AP36: 1 | AQ36: 0.95 | AR36: =(AJ36+AL36+AN36+AP36)/2 -> 1 | AS36: =(AK36+AM36+AO36+AQ36)/2 -> 0.975 | AT36: =AS36/AR36 -> 0.975 | AU36: =IF(AR36> 1, IF(AR36 = AS36, "100%", AR36 & "%"), IF(AR36 <= 0.01, "0%", AR36 * 100 & "%")) -> 100% | AV36: =IF(AR36=0, 0, AS36/AR36) -> 0.975 | AW36: P | AX36: META 35.docx | AY36: 0.15 | AZ36: 0.15 | BA36: 0.3 | BB36: 0.3 | BC36: 0.3 | BE36: 0.25 | BG36: =(AY36+BA36+BC36+BE36) -> 1 | BH36: =(AZ36+BB36+BD36+BF36) -> 0.45 | BI36: =BH36/BG36 -> 0.45 | BJ36: =MIN((BG36 /BG36) * 100, 100) & "%" -> 100% | BK36: =IF(BG36=0, 0, BH36/BG36) -> 0.45 | BL36: P | BM36: Meta 35.docx | BN36: 0 | BO36: 0 | BP36: 0 | BQ36: 0 | BR36: =+BN36+BP36 -> 0 | BS36: =+BO36+BQ36 -> 0 | BT36: =IFERROR(BS36/BR36, "") | BU36: 0 | BV36: 0 | BW36: 0 | BX36: 0 | BY36: =IFERROR(BW36/BV36, "") | BZ36: 0 | CA36: 90000000 | CB36: 91800000 | CC36: 94554000 | CD36: 276354000
A37: Eje 1. Ambiente, Conectividad y Ordenamiento y servicios públicos | B37: 0.235 | D37: 40 | E37: 4003 | F37: 5 | G37: Programa Integral de Innovación de Servicios Públicos de Acuedcto, Alcantarillado y Aseo (PISAAA) (Acceso de la población a los servicios de agua potable y saneamiento básico) | H37: 1400 | I37: 5.1 | J37: Es el tiempo de Agua Potable con Calidad | K37: 5.1.2 | L37: Ejecutar al 100% la acciones de inspección, vigilancia, control y ahorro de agua | M37: Porcentaje de acciones de inspección, vigilancia, control y ahorro del agua ejecutadas | N37: 0.91 | O37: 4003009 | P37: 2024257990005 | Q37: Optimización del programa integral para el acceso de la población a los serivicios de agua potable y saneamiento básico en el municipio de Tenjo Cundinamarca | R37: 36 | S37: Ejecutar el 40% EL Programa de Uso Eficiente y Ahorro del Agua PUEAA | T37: 0.2 | U37: Porcentaje | V37: I | W37: Porcentaje de programa ejecutado | X37: Empresa de Servicios Públicos de Tenjo EMSERTENJO SA ESP | Y37: SI | Z37: =SUM(AF37:AI37) -> 0.4 | AA37: =AS37/Z37 -> 0.2 | AB37: =BI37/Z37 -> 0.25 | AE37: =SUMPRODUCT(AA37:AD37, {0.15,0.35,0.35,0.15}) -> 0.1175 | AF37: 0.1 | AG37: 0.1 | AH37: 0.1 | AI37: 0.1 | AN37: 0.03 | AO37: 0.03 | AP37: 0.07 | AQ37: 0.05 | AR37: =(AJ37+AL37+AN37+AP37) -> 0.1 | AS37: =(AK37+AM37+AO37+AQ37) -> 0.08 | AT37: =AS37/AR37 -> 0.8 | AU37: =IF(AR37> 1, IF(AR37 = AS37, "100%", AR37 & "%"), IF(AR37 <= 0.01, "0%", AR37 * 100 & "%")) -> 10% | AV37: =IF(AR37=0, 0, AS37/AR37) -> 0.8 | AW37: P | AX37: META 36.docx | AY37: 0 | AZ37: 0 | BA37: 0.03 | BB37: 0.01 | BC37: 0.02 | BD37: 0 | BE37: 0.05 | BG37: =(AY37+BA37+BC37+BE37) -> 0.1 | BH37: =(AZ37+BB37+BD37+BF37) -> 0.01 | BI37: =BH37/BG37 -> 0.1 | BJ37: =MIN((BG37 /BG37) * 100, 100) & "%" -> 100% | BK37: =IF(BG37=0, 0, BH37/BG37) -> 0.1 | BL37: P | BM37: Meta 36.docx | BN37: 60000000 | BO37: 0 | BP37: 60000000 | BQ37: 60000000 | BR37: =+BN37+BP37 -> 120000000 | BS37: =+BO37+BQ37 -> 60000000 | BT37: =IFERROR(BS37/BR37, "") -> 0.5 | BU37: 60000000 | BV37: 60000000 | BW37: 0 | BX37: 0 | BY37: =IFERROR(BW37/BV37, "") -> 0 | BZ37: 55000000 | CA37: 60000000 | CB37: 62000000 | CC37: 65000000 | CD37: 242000000
A38: Eje 1. Ambiente, Conectividad y Ordenamiento y servicios públicos | B38: 0.235 | D38: 40 | E38: 4003 | F38: 5 | G38: Programa Integral de Innovación de Servicios Públicos de Acuedcto, Alcantarillado y Aseo (PISAAA) (Acceso de la población a los servicios de agua potable y saneamiento básico) | H38: 1400 | I38: 5.1 | J38: Es el tiempo de Agua Potable con Calidad | K38: 5.1.2 | L38: Ejecutar al 100% la acciones de inspección, vigilancia, control y ahorro de agua | M38: Porcentaje de acciones de inspección, vigilancia, control y ahorro del agua ejecutadas | N38: 0.91 | O38: 4003029 | P38: 2024257990005 | Q38: Optimización del programa integral para el acceso de la población a los serivicios de agua potable y saneamiento básico en el municipio de Tenjo Cundinamarca | R38: 37 | S38: Mantener el IRCA- Índice de Calidad del Agua Potable sin Riesgo | T38: Irca en riesgo medio | U38: Número | V38: M | W38: IRCA sin riesgo | X38: Empresa de Servicios Públicos de Tenjo EMSERTENJO SA ESP | Y38: SI | Z38: =SUM(AF38:AI38)/4 -> 1 | AA38: =AS38/Z38 -> 0.95 | AB38: =BI38/Z38 -> 2 | AE38: =SUMPRODUCT(AA38:AD38, {0.15,0.35,0.35,0.15}) -> 0.8425 | AF38: 1 | AG38: 1 | AH38: 1 | AI38: 1 | AN38: 1 | AO38: 1 | AP38: 1 | AQ38: 0.9 | AR38: =(AJ38+AL38+AN38+AP38)/2 -> 1 | AS38: =(AK38+AM38+AO38+AQ38)/2 -> 0.95 | AT38: =AS38/AR38 -> 0.95 | AU38: =IF(AR38> 1, IF(AR38 = AS38, "100%", AR38 & "%"), IF(AR38 <= 0.01, "0%", AR38 * 100 & "%")) -> 100% | AV38: =IF(AR38=0, 0, AS38/AR38) -> 0.95 | AW38: P | AX38: META 37.docx | AY38: 1 | AZ38: 1 | BA38: 1 | BB38: 1 | BC38: 1 | BE38: 1 | BG38: =(AY38+BA38+BC38+BE38)/4 -> 1 | BH38: =(AZ38+BB38+BD38+BF38) -> 2 | BI38: =BH38/BG38 -> 2 | BJ38: =MIN((BG38 /BG38) * 100, 100) & "%" -> 100% | BK38: =IF(BG38=0, 0, BH38/BG38) -> 2 | BL38: P | BM38: Meta 37.docx | BN38: 10000000 | BO38: 0 | BP38: 0 | BQ38: 0 | BR38: =+BN38+BP38 -> 10000000 | BS38: =+BO38+BQ38 -> 0 | BT38: =IFERROR(BS38/BR38, "") -> 0 | BU38: 10000000 | BV38: 10000000 | BW38: 0 | BX38: 0 | BY38: =IFERROR(BW35/BV35, "") -> 0 | BZ38: 10000000 | CA38: 10000000 | CB38: 10000000 | CC38: 10000000 | CD38: 40000000
A39: Eje 1. Ambiente, Conectividad y Ordenamiento y servicios públicos | B39: 0.235 | D39: 40 | E39: 4003 | F39: 5 | G39: Programa Integral de Innovación de Servicios Públicos de Acuedcto, Alcantarillado y Aseo (PISAAA) (Acceso de la población a los servicios de agua potable y saneamiento básico) | H39: 1400 | I39: 5.1 | J39: Es el tiempo de Agua Potable con Calidad | K39: 5.1.2 | L39: Ejecutar al 100% la acciones de inspección, vigilancia, control y ahorro de agua | M39: Porcentaje de acciones de inspección, vigilancia, control y ahorro del agua ejecutadas | N39: 0.91 | O39: 4003029 | P39: 2024257990005 | Q39: Optimización del programa integral para el acceso de la población a los serivicios de agua potable y saneamiento básico en el municipio de Tenjo Cundinamarca | R39: 38 | S39: Generar el 100% de los reportes al Sistema Único de Información oficial del sector de servicios públicos domiciliarios | T39: 1 | U39: Porcentaje | V39: M | W39: Reportes generados | X39: Sec. de Planeación y Desarrollo Territorial | Y39: SI | Z39: =SUM(AF39:AI39)/4 -> 1 | AA39: =AS39/Z39 -> 1 | AB39: =BI39/Z39 -> 0.95 | AE39: =SUMPRODUCT(AA39:AD39, {0.15,0.35,0.35,0.15}) -> 0.4825 | AF39: 1 | AG39: 1 | AH39: 1 | AI39: 1 | AN39: 0.7 | AO39: 0.7 | AP39: 0.3 | AQ39: 0.3 | AR39: =(AJ39+AL39+AN39+AP39) -> 1 | AS39: =(AK39+AM39+AO39+AQ39) -> 1 | AT39: =AS39/AR39 -> 1 | AU39: =MIN((AR39 /AR39) * 100, 100) & "%" -> 100% | AV39: =IF(AR39=0, 0, AS39/AR39) -> 1 | AW39: P | AX39: Meta 38.docx | AY39: 0.4 | AZ39: 0.4 | BA39: 0.3 | BB39: 0.3 | BC39: 0.25 | BD39: 0.25 | BE39: 0.05 | BG39: =(AY39+BA39+BC39+BE39) -> 1 | BH39: =(AZ39+BB39+BD39+BF39) -> 0.95 | BI39: =BH39/BG39 -> 0.95 | BJ39: =MIN((BG39 /BG39) * 100, 100) & "%" -> 100% | BK39: =IF(BG39=0, 0, BH39/BG39) -> 0.95 | BL39: P | BM39: Meta 38.docx | BN39: 36000000 | BO39: 35000000 | BP39: 6800000 | BQ39: 6800000 | BR39: =+BN39+BP39 -> 42800000 | BS39: =+BO39+BQ39 -> 41800000 | BT39: =IFERROR(BS39/BR39, "") -> 0.97663551 | BU39: 36000000 | BV39: 36000000 | BW39: 35000000 | BX39: 26716666 | BY39: =IFERROR(BW39/BV39, "") -> 0.97222222 | BZ39: 30000000 | CA39: 30600000 | CB39: 31212000 | CC39: 32148360 | CD39: 123960360
A40: Eje 1. Ambiente, Conectividad y Ordenamiento y servicios públicos | B40: 0.235 | D40: 40 | E40: 4003 | F40: 5 | G40: Programa Integral de Innovación de Servicios Públicos de Acuedcto, Alcantarillado y Aseo (PISAAA) (Acceso de la población a los servicios de agua potable y saneamiento básico) | H40: 1400 | I40: 5.1 | J40: Es el tiempo de Agua Potable con Calidad | K40: 5.1.2 | L40: Ejecutar al 100% la acciones de inspección, vigilancia, control y ahorro de agua | M40: Porcentaje de acciones de inspección, vigilancia, control y ahorro del agua ejecutadas | N40: 0.91 | O40: 4003009 | P40: 2024257990005 | Q40: Optimización del programa integral para el acceso de la población a los serivicios de agua potable y saneamiento básico en el municipio de Tenjo Cundinamarca | R40: 39 | S40: Desarrollar en un 80% un proceso de seguimiento, identificación, medición y control de pérdidas de agua potable. | T40: 0,2 | U40: Número | V40: I | W40: Porcentaje de proceso de seguimiento desarrollado | X40: Sec. Infraestructura y Obra Pública | Y40: SI | Z40: =SUM(AF40:AI40) -> 0.8 | AA40: =AS40/Z40 -> 0 | AB40: =BI40/Z40 -> 1.25 | AE40: =SUMPRODUCT(AA40:AD40, {0.15,0.35,0.35,0.15}) -> 0.4375 | AF40: 0.1 | AG40: 0.1 | AH40: 0.4 | AI40: 0.2 | AN40: 0 | AO40: 0 | AP40: 0 | AR40: 0 | AS40: 0 | AT40: 0 | AU40: =IF(AR40> 1, IF(AR40 = AS40, "100%", AR40 & "%"), IF(AR40 <= 0.01, "0%", AR40 * 100 & "%")) -> 0% | AV40: =IF(AR40=0, 0, AS40/AR40) -> 0 | AW40: NP | AY40: 0 | AZ40: 0 | BA40: 0 | BB40: 0 | BC40: 0 | BD40: 0 | BE40: 0.1 | BF40: 0.1 | BG40: =(AY40+BA40+BC40+BE40) -> 0.1 | BH40: =(AZ40+BB40+BD40+BF40) -> 0.1 | BI40: =BH40/BG40 -> 1 | BJ40: =MIN((BG40 /BG40) * 100, 100) & "%" -> 100% | BK40: =IF(BG40=0, 0, BH40/BG40) -> 1 | BL40: P | BM40: Meta 39.docx | BN40: 50000000 | BO40: 0 | BP40: 120000000 | BQ40: 120000000 | BR40: =+BN40+BP40 -> 170000000 | BS40: =+BO40+BQ40 -> 120000000 | BT40: =IFERROR(BS40/BR40, "") -> 0.70588235 | BU40: 50000000 | BV40: 50000000 | BW40: 0 | BX40: 0 | BY40: =IFERROR(BW40/BV40, "") -> 0 | BZ40: 0 | CA40: 180000000 | CB40: 183600000 | CC40: 189108000 | CD40: 552708000
A41: Eje 1. Ambiente, Conectividad y Ordenamiento y servicios públicos | B41: 0.235 | D41: 40 | E41: 4003 | F41: 5 | G41: Programa Integral de Innovación de Servicios Públicos de Acuedcto, Alcantarillado y Aseo (PISAAA) (Acceso de la población a los servicios de agua potable y saneamiento básico) | H41: 1400 | I41: 5.1 | J41: Es el tiempo de Agua Potable con Calidad | K41: 5.1.3 | L41: Garantizar al 100% la transferencia de recursos que fortalezcan el acceso universal, equitativo al servicio de agua potable | M41: Porcentaje de transferecencia de recursos garanizados | N41: 1 | O41: 4003008 | P41: 2024257990005 | Q41: Optimización del programa integral para el acceso de la población a los serivicios de agua potable y saneamiento básico en el municipio de Tenjo Cundinamarca | R41: 40 | S41: Transferir el 100% de los recursos necesarios para el Plan Departamental de Aguas de Cundinamarca | T41: 1 | U41: Porcentaje | V41: M | W41: Recursos transferidos | X41: Sec. Infraestructura y Obra Pública | Y41: SI | Z41: =SUM(AF41:AI41)/4 -> 1 | AA41: =AS41/Z41 -> 2 | AB41: =BI41/Z41 -> 0.4 | AE41: =SUMPRODUCT(AA41:AD41, {0.15,0.35,0.35,0.15}) -> 0.44 | AF41: 1 | AG41: 1 | AH41: 1 | AI41: 1 | AN41: 1 | AO41: 1 | AP41: 1 | AQ41: 1 | AR41: =(AJ41+AL41+AN41+AP41)/2 -> 1 | AS41: =(AK41+AM41+AO41+AQ41) -> 2 | AT41: =AS41/AR41 -> 2 | AU41: =MIN((AR41 /AR41) * 100, 100) & "%" -> 100% | AV41: =IF(AR41=0, 0, AS41/AR41) -> 2 | AW41: P | AX41: META 40.docx | AY41: 0 | AZ41: 0 | BA41: 0.4 | BB41: 0.4 | BC41: 0.3 | BD41: 0 | BE41: 0.3 | BG41: =(AY41+BA41+BC41+BE41) -> 1 | BH41: =(AZ41+BB41+BD41+BF41) -> 0.4 | BI41: =BH41/BG41 -> 0.4 | BJ41: =MIN((BG41 /BG41) * 100, 100) & "%" -> 100% | BK41: =IF(BG41=0, 0, BH41/BG41) -> 0.4 | BL41: P | BM41: Meta 40.docx | BN41: 756666724 | BO41: 0 | BP41: 717283755 | BQ41: 717283755 | BR41: =+BN41+BP41 -> 1473950479 | BS41: =+BO41+BQ41 -> 717283755 | BT41: =IFERROR(BS41/BR41, "") -> 0.48664034 | BU41: 717283756 | BV41: 756666724 | BW41: 0 | BX41: 0 | BY41: =IFERROR(BW41/BV41, "") -> 0 | BZ41: 541655315 | CA41: 568738082 | CB41: 597174986 | CC41: 627033735 | CD41: 2334602117
A42: Eje 1. Ambiente, Conectividad y Ordenamiento y servicios públicos | B42: 0.235 | D42: 40 | E42: 4003 | F42: 5 | G42: Programa Integral de Innovación de Servicios Públicos de Acuedcto, Alcantarillado y Aseo (PISAAA) (Acceso de la población a los servicios de agua potable y saneamiento básico) | H42: 1400 | I42: 5.1 | J42: Es el tiempo de Agua Potable con Calidad | K42: 5.1.3 | L42: Garantizar al 100% la transferencia de recursos que fortalezcan el acceso universal, equitativo al servicio de agua potable | M42: Porcentaje de transferecencia de recursos garanizados | N42: 1 | O42: 4003047 | P42: 2024257990005 | Q42: Optimización del programa integral para el acceso de la población a los serivicios de agua potable y saneamiento básico en el municipio de Tenjo Cundinamarca | R42: 41 | S42: Transferir el 100% de los recursos necesarios para subsidiar la prestación del servicio acueducto, alcantarillado y aseo | T42: 1 | U42: Porcentaje | V42: M | W42: Recursos transferidos | X42: Sec. de Planeación y Desarrollo Territorial | Y42: SI | Z42: =SUM(AF42:AI42)/4 -> 1 | AA42: =AS42/Z42 -> 1 | AB42: =BI42/Z42 -> 0.7 | AE42: =SUMPRODUCT(AA42:AD42, {0.15,0.35,0.35,0.15}) -> 0.395 | AF42: 1 | AG42: 1 | AH42: 1 | AI42: 1 | AN42: 0.4 | AO42: 0.4 | AP42: 0.6 | AQ42: 0.6 | AR42: =(AJ42+AL42+AN42+AP42) -> 1 | AS42: =(AK42+AM42+AO42+AQ42) -> 1 | AT42: =AS42/AR42 -> 1 | AU42: =MIN((AR42 /AR42) * 100, 100) & "%" -> 100% | AV42: =IF(AR42=0, 0, AS42/AR42) -> 1 | AW42: P | AX42: Meta 41.docx | AY42: 0.05 | AZ42: 0.05 | BA42: 0.3 | BB42: 0.3 | BC42: 0.35 | BD42: 0.35 | BE42: 0.3 | BG42: =(AY42+BA42+BC42+BE42) -> 1 | BH42: =(AZ42+BB42+BD42+BF42) -> 0.7 | BI42: =BH42/BG42 -> 0.7 | BJ42: =MIN((BG42 /BG42) * 100, 100) & "%" -> 100% | BK42: =IF(BG42=0, 0, BH42/BG42) -> 0.7 | BL42: P | BM42: Meta 41.docx | BN42: 8178228371 | BO42: 2240818101 | BP42: 410021624 | BQ42: 410021624 | BR42: =+BN42+BP42 -> 8588249995 | BS42: =+BO42+BQ42 -> 2650839725 | BT42: =IFERROR(BS42/BR42, "") -> 0.30865889 | BU42: 2240818101 | BV42: 8178228371 | BW42: 2240818101 | BX42: 492843745 | BY42: =IFERROR(BW42/BV42, "") -> 0.27399799 | BZ42: 2724894363 | CA42: 2864930668 | CB42: 3005043539 | CC42: 3156295716 | CD42: 11751164285
A43: Eje 1. Ambiente, Conectividad y Ordenamiento y servicios públicos | B43: 0.235 | D43: 40 | E43: 4003 | F43: 5 | G43: Programa Integral de Innovación de Servicios Públicos de Acuedcto, Alcantarillado y Aseo (PISAAA) (Acceso de la población a los servicios de agua potable y saneamiento básico) | H43: 1400 | I43: 5.2 | J43: Saneamiento básico con proyección | K43: 5.2.1 | L43: Incrementar al 74% los hogares la calidad de acceso al servicio de alcantarillado y saneamiento básico | M43: Porcentaje de hogares con servicio de alcatarillado y saneamiento básico | N43: % de hogares en el municipio 63,81 % en la cabecera municipal 98,47 % en los centros poblados y rural disperso 38,48 Fuente: Fuente: Dane.mapa.argis.com | O43: 4003040 | P43: 2024257990005 | Q43: Optimización del programa integral para el acceso de la población a los serivicios de agua potable y saneamiento básico en el municipio de Tenjo Cundinamarca | R43: 42 | S43: Ampliar la capacidad de las Plantas de Tratamiento de Agua Residual, a 40lts por segundo, unificando la planta norte y la planta sur – PTAR de la vereda La Punta | T43: 18 Lts*Seg | U43: Lts | V43: I | W43: Capacidad de las PTAR ampliadas | X43: Sec. Infraestructura y Obra Pública | Y43: SI | Z43: =SUM(AF43:AI43) -> 40 | AA43: =AS43/Z43 -> 0.0055 | AB43: =BI43/Z43 -> 0.025 | AE43: =SUMPRODUCT(AA43:AD43, {0.15,0.35,0.35,0.15}) -> 0.009575 | AF43: 4 | AG43: 16 | AH43: 16 | AI43: 4 | AN43: 0.02 | AO43: 0.02 | AP43: 0.2 | AQ43: 0.2 | AR43: =(AJ43+AL43+AN43+AP43) -> 0.22 | AS43: =(AK43+AM43+AO43+AQ43) -> 0.22 | AT43: =AS43/AR43 -> 1 | AU43: =MIN((AR43 /AR43) * 100, 100) & "%" -> 100% | AV43: =IF(AR43=0, 0, AS43/AR43) -> 1 | AW43: P | AX43: META 42.docx | AY43: 0 | AZ43: 0 | BA43: 0 | BB43: 0 | BC43: 3 | BD43: 3 | BE43: 13 | BF43: 13 | BG43: =(AY43+BA43+BC43+BE43) -> 16 | BH43: =(AZ43+BB43+BD43+BF43) -> 16 | BI43: =BH43/BG43 -> 1 | BJ43: =MIN((BG43 /BG43) * 100, 100) & "%" -> 100% | BK43: =IF(BG43=0, 0, BH43/BG43) -> 1 | BL43: P | BM43: Meta 42.docx | BN43: 500000000 | BO43: 0 | BP43: 0 | BQ43: 0 | BR43: =+BN43+BP43 -> 500000000 | BS43: =+BO43+BQ43 -> 0 | BT43: =IFERROR(BS43/BR43, "") -> 0 | BU43: 500000000 | BV43: 500000000 | BW43: 0 | BX43: 0 | BY43: =IFERROR(BW43/BV43, "") -> 0 | BZ43: 2000000000 | CA43: 0 | CB43: 0 | CC43: 0 | CD43: 2000000000
A44: Eje 1. Ambiente, Conectividad y Ordenamiento y servicios públicos | B44: 0.235 | D44: 40 | E44: 4003 | F44: 5 | G44: Programa Integral de Innovación de Servicios Públicos de Acuedcto, Alcantarillado y Aseo (PISAAA) (Acceso de la población a los servicios de agua potable y saneamiento básico) | H44: 1400 | I44: 5.2 | J44: Saneamiento básico con proyección | K44: 5.2.1 | L44: Incrementar al 74% los hogares la calidad de acceso al servicio de alcantarillado y saneamiento básico | M44: Porcentaje de hogares con servicio de alcatarillado y saneamiento básico | N44: % de hogares en el municipio 63,81 % en la cabecera municipal 98,47 % en los centros poblados y rural disperso 38,48 Fuente: Fuente: Dane.mapa.argis.com | O44: 4003020 | P44: 2024257990005 | Q44: Optimización del programa integral para el acceso de la población a los serivicios de agua potable y saneamiento básico en el municipio de Tenjo Cundinamarca | R44: 43 | S44: Optimizar el 40% de las redes de alcantarillado donde se tiene cobertura | T44: 500 mts intervenidos 2020-2023 37,15 Km (20,8 Sanitario 16,35 Pluvial) | U44: Porcentaje | V44: I | W44: Porcentaje de redes de alcantarillado optimizadas | X44: Sec. Infraestructura y Obra Pública | Y44: SI | Z44: =SUM(AF44:AI44) -> 14.86 | AA44: =AS44/Z44 -> 0.30282638 | AB44: =BI44/Z44 -> 0.0067294751 | AE44: =SUMPRODUCT(AA44:AD44, {0.15,0.35,0.35,0.15}) -> 0.047779273 | AF44: 0 | AG44: 5 | AH44: 7.36 | AI44: 2.5 | AN44: 0.01 | AO44: 0 | AP44: 4.5 | AQ44: 4.5 | AR44: =(AJ44+AL44+AN44+AP44) -> 4.51 | AS44: =(AK44+AM44+AO44+AQ44) -> 4.5 | AT44: =AS44/AR44 -> 0.99778271 | AU44: =MIN((AR44 /AR44) * 100, 100) & "%" -> 100% | AV44: =IF(AR44=0, 0, AS44/AR44) -> 0.99778271 | AW44: P | AX44: META 43.docx | AY44: 0 | AZ44: 0 | BA44: 0 | BB44: 0 | BC44: 2 | BD44: 0.5 | BE44: 3 | BG44: =(AY44+BA44+BC44+BE44) -> 5 | BH44: =(AZ44+BB44+BD44+BF44) -> 0.5 | BI44: =BH44/BG44 -> 0.1 | BJ44: =MIN((BG44 /BG44) * 100, 100) & "%" -> 100% | BK44: =IF(BG44=0, 0, BH44/BG44) -> 0.1 | BL44: P | BM44: Meta 43.docx | BN44: 525624066 | BO44: 0 | BP44: 4333333 | BQ44: 4333333 | BR44: =+BN44+BP44 -> 529957399 | BS44: =+BO44+BQ44 -> 4333333 | BT44: =IFERROR(BS44/BR44, "") -> 0.0081767572 | BU44: 502098629 | BV44: 525624066 | BW44: 0 | BX44: 0 | BY44: =IFERROR(BW44/BV44, "") -> 0 | BZ44: 0 | CA44: 750000000 | CB44: 0 | CC44: 0 | CD44: 750000000
A45: Eje 1. Ambiente, Conectividad y Ordenamiento y servicios públicos | B45: 0.235 | D45: 40 | E45: 4003 | F45: 5 | G45: Programa Integral de Innovación de Servicios Públicos de Acuedcto, Alcantarillado y Aseo (PISAAA) (Acceso de la población a los servicios de agua potable y saneamiento básico) | H45: 1400 | I45: 5.2 | J45: Saneamiento básico con proyección | K45: 5.2.1 | L45: Incrementar al 74% los hogares la calidad de acceso al servicio de alcantarillado y saneamiento básico | M45: Porcentaje de hogares con servicio de alcatarillado y saneamiento básico | N45: % de hogares en el municipio 63,81 % en la cabecera municipal 98,47 % en los centros poblados y rural disperso 38,48 Fuente: Fuente: Dane.mapa.argis.com | O45: 4003020 | P45: 2024257990005 | Q45: Optimización del programa integral para el acceso de la población a los serivicios de agua potable y saneamiento básico en el municipio de Tenjo Cundinamarca | R45: 44 | S45: Optimizar 2 Plantas de tratamiento (una en la vereda la punta y una en la vereda chucua pertenecientes al municipio de Tenjo) | T45: 0 | U45: Número | V45: I | W45: Plantas de tratamiento optimizadas | X45: Sec. Infraestructura y Obra Pública | Y45: SI | Z45: =SUM(AF45:AI45) -> 2 | AA45: =AS45/Z45 -> 0.05 | AB45: =BI45/Z45 -> 0.25 | AE45: =SUMPRODUCT(AA45:AD45, {0.15,0.35,0.35,0.15}) -> 0.095 | AF45: 0.1 | AG45: 0.9 | AH45: 0.5 | AI45: 0.5 | AN45: 0.01 | AO45: 0.01 | AP45: 0.09 | AQ45: 0.09 | AR45: =(AJ45+AL45+AN45+AP45) -> 0.1 | AS45: =(AK45+AM45+AO45+AQ45) -> 0.1 | AT45: =AS45/AR45 -> 1 | AU45: =MIN((AR45 /AR45) * 100, 100) & "%" -> 100% | AV45: =IF(AR45=0, 0, AS45/AR45) -> 1 | AW45: P | AX45: META 44.docx | AY45: 0 | AZ45: 0 | BA45: 0.3 | BB45: 0.3 | BC45: 0.1 | BD45: 0.1 | BE45: 0.4 | BG45: =(AY45+BA45+BC45+BE45) -> 0.8 | BH45: =(AZ45+BB45+BD45+BF45) -> 0.4 | BI45: =BH45/BG45 -> 0.5 | BJ45: =MIN((BG45 /BG45) * 100, 100) & "%" -> 100% | BK45: =IF(BG45=0, 0, BH45/BG45) -> 0.5 | BL45: P | BM45: Meta 44.docx | BN45: 300000000 | BO45: 0 | BP45: 2683307320 | BQ45: 2683307320 | BR45: =+BN45+BP45 -> 2983307320 | BS45: =+BO45+BQ45 -> 2683307320 | BT45: =IFERROR(BS45/BR45, "") -> 0.89944046 | BU45: 300000000 | BV45: 300000000 | BW45: 182930950 | BX45: 179847070 | BY45: =IFERROR(BW45/BV45, "") -> 0.60976983 | BZ45: 2400000000 | CA45: 0 | CB45: 0 | CC45: 0 | CD45: 2400000000
A46: Eje 1. Ambiente, Conectividad y Ordenamiento y servicios públicos | B46: 0.235 | D46: 40 | E46: 4003 | F46: 5 | G46: Programa Integral de Innovación de Servicios Públicos de Acuedcto, Alcantarillado y Aseo (PISAAA) (Acceso de la población a los servicios de agua potable y saneamiento básico) | H46: 1400 | I46: 5.3 | J46: Es el tiempo de la gestión innovadora de los residuos sólidos | K46: 5.3.1 | L46: Mantener al 100% el servicio de aseo, recolección y manejo de resiudos promoviendo la cultura de aprovechamiento y manejo de residuos sólidos | M46: Porcentaje de servcio de aseo, recolección y manejo de aprovechamiento de residuos sólidos | N46: % municipio 98% %Cabecera municipal 99,50 %Centros poblados y rural disperson | O46: 4003022 | P46: 2024257990005 | Q46: Optimización del programa integral para el acceso de la población a los serivicios de agua potable y saneamiento básico en el municipio de Tenjo Cundinamarca | R46: 45 | S46: Ejecutar el 40% del Programa de gestión integral de residuos sólidos | T46: 20% Fuente CAR 2023 | U46: Porcentaje | V46: I | W46: Entregar el PGIRS con un avance del 60% | X46: Secretaría de Desarrollo Económico y Medio Ambiente o quien haga sus veces | Y46: SI | Z46: =SUM(AF46:AI46) -> 0.4 | AA46: =AS46/Z46 -> 0.2 | AB46: =BI46/Z46 -> 2.125 | AE46: =SUMPRODUCT(AA46:AD46, {0.15,0.35,0.35,0.15}) -> 0.77375 | AF46: 0.08 | AG46: 0.2 | AH46: 0.06 | AI46: 0.06 | AN46: 0.08 | AO46: 0.08 | AP46: 0.08 | AQ46: 0.08 | AR46: =(AJ46+AL46+AN46+AP46)/2 -> 0.08 | AS46: =(AK46+AM46+AO46+AQ46)/2 -> 0.08 | AT46: =AS46/AR46 -> 1 | AU46: =MIN((AR46 /AR46) * 100, 100) & "%" -> 100% | AV46: =IF(AR46=0, 0, AS46/AR46) -> 1 | AW46: P | AX46: META 45 | AY46: 0 | AZ46: 0 | BA46: 0.05 | BB46: 0.05 | BC46: 0.12 | BD46: 0.12 | BE46: 0.03 | BG46: =(AY46+BA46+BC46+BE46) -> 0.2 | BH46: =(AZ46+BB46+BD46+BF46) -> 0.17 | BI46: =BH46/BG46 -> 0.85 | BJ46: =MIN((BG46 /BG46) * 100, 100) & "%" -> 100% | BK46: =IF(BG46=0, 0, BH46/BG46) -> 0.85 | BL46: P | BM46: Meta 45.docx | BN46: 485262909 | BO46: 0 | BP46: 0 | BQ46: 0 | BR46: =+BN46+BP46 -> 485262909 | BS46: =+BO46+BQ46 -> 0 | BT46: =IFERROR(BS46/BR46, "") -> 0 | BU46: 416660695 | BV46: 485262909 | BW46: 399999400 | BX46: 399999400 | BY46: =IFERROR(BW46/BV46, "") -> 0.8242942 | BZ46: 350000000 | CA46: 350048275 | CB46: 357080688 | CC46: 367815123 | CD46: 1424944086
A47: Eje 1. Ambiente, Conectividad y Ordenamiento y servicios públicos | B47: 0.235 | D47: 40 | E47: 4003 | F47: 5 | G47: Programa Integral de Innovación de Servicios Públicos de Acuedcto, Alcantarillado y Aseo (PISAAA) (Acceso de la población a los servicios de agua potable y saneamiento básico) | H47: 1400 | I47: 5.3 | J47: Es el tiempo de la gestión innovadora de los residuos sólidos | K47: 5.3.1 | L47: Mantener al 100% el servicio de aseo, recolección y manejo de resiudos promoviendo la cultura de aprovechamiento y manejo de residuos sólidos | M47: Porcentaje de servcio de aseo, recolección y manejo de aprovechamiento de residuos sólidos | N47: % municipio 98% %Cabecera municipal 99,50 %Centros poblados y rural disperson | O47: 4003022 | P47: 2024257990005 | Q47: Optimización del programa integral para el acceso de la población a los serivicios de agua potable y saneamiento básico en el municipio de Tenjo Cundinamarca | R47: 46 | S47: Instalar 3 Contenedores de reciclaje inteligentes | T47: 0 | U47: Número | V47: I | W47: Contenedores instalados | X47: Sec. Infraestructura y Obra Pública | Y47: SI | Z47: =SUM(AF47:AI47) -> 3 | AA47: =AS47/Z47 -> 0.33 | AB47: =BI47/Z47 -> 0.33333333 | AE47: =SUMPRODUCT(AA47:AD47, {0.15,0.35,0.35,0.15}) -> 0.16616667 | AF47: 1 | AG47: 1 | AH47: 1 | AI47: 0 | AN47: 0.2 | AO47: 0.2 | AP47: 0.8 | AQ47: 0.79 | AR47: =(AJ47+AL47+AN47+AP47) -> 1 | AS47: =(AK47+AM47+AO47+AQ47) -> 0.99 | AT47: =AS47/AR47 -> 0.99 | AU47: =MIN((AR47 /AR47) * 100, 100) & "%" -> 100% | AV47: =IF(AR47=0, 0, AS47/AR47) -> 0.99 | AW47: P | AX47: META 46.docx | AY47: 0.1 | AZ47: 0.1 | BA47: 0.9 | BB47: 0.9 | BC47: 0 | BD47: 0 | BE47: 0 | BG47: =(AY47+BA47+BC47+BE47) -> 1 | BH47: =(AZ47+BB47+BD47+BF47) -> 1 | BI47: =BH47/BG47 -> 1 | BJ47: =MIN((BG47 /BG47) * 100, 100) & "%" -> 100% | BK47: =IF(BG47=0, 0, BH47/BG47) -> 1 | BL47: P | BM47: Meta 46.docx | BN47: 200000000 | BO47: 0 | BP47: 300631997 | BQ47: 300631997 | BR47: =+BN47+BP47 -> 500631997 | BS47: =+BO47+BQ47 -> 300631997 | BT47: =IFERROR(BS47/BR47, "") -> 0.60050496 | BU47: 200000000 | BV47: 0 | BW47: 0 | BX47: 0 | BY47: =IFERROR(BW47/BV47, "") | BZ47: 300000000 | CA47: 0 | CB47: 0 | CC47: 0 | CD47: 300000000
A48: Eje 1. Ambiente, Conectividad y Ordenamiento y servicios públicos | B48: 0.235 | D48: 21 | E48: 2102 | F48: 6 | G48: Programa Integral de Innovación de Servicios Públicos domiciliarios de Tenjo (PIMSEPT) (Consolidación productiva del sector de energía eléctrica) | H48: 1900 | I48: 6.1 | J48: Es el tiempo de la mejora en gas natural domiciliario y alumbrado público | K48: 6.1.1 | L48: Aumentar en 30% la eficiencia energética y la sosteniblilidad en el sistema de Alumbrado Público en el municipio, reduciendo el consumo de energia y mejorando la percepción de seguiridad y satisfacción de los ciudadanos co la iluminación LED | M48: Porcentaje de eficiencia energética aumentado | N48: 0 | O48: 2102010 | P48: 2024257990006 | Q48: Ampliacion de la cobertura de gas natural y consolidación productiva del sector de energía eléctrica en el Municipio de Tenjo | R48: 47 | S48: Implementar el cambio de 5000 luminarias de alumbrado público a tecnología LED y/o sostenible en la zona rural y urbana | T48: 0 | U48: Número | V48: I | W48: Metros de redes de alumbrado público ampliado | X48: Sec. Infraestructura y Obra Pública | Y48: SI | Z48: =SUM(AF48:AI48) -> 5000 | AA48: =AS48/Z48 -> 0.7482 | AB48: =BI48/Z48 -> 0 | AE48: =SUMPRODUCT(AA48:AD48, {0.15,0.35,0.35,0.15}) -> 0.11223 | AF48: 5000 | AG48: 0 | AH48: 0 | AI48: 0 | AN48: 3245 | AO48: 3245 | AP48: 496 | AQ48: 496 | AR48: =(AJ48+AL48+AN48+AP48) -> 3741 | AS48: =(AK48+AM48+AO48+AQ48) -> 3741 | AT48: =AS48/AR48 -> 1 | AU48: =MIN((AR48 /AR48) * 100, 100) & "%" -> 100% | AV48: =IF(AR48=0, 0, AS48/AR48) -> 1 | AW48: P | AX48: META 47.docx | AY48: 0 | BA48: 0 | BC48: 0 | BE48: 0 | BG48: =(AY48+BA48+BC48+BE48) -> 0 | BH48: =(AZ48+BB48+BD48+BF48) -> 0 | BI48: =IF(BF48> 1, IF(BF48 = BG48, "100%", BF48 & "%"), IF(BF48 <= 0.01, "0%", BF48 * 100 & "%")) -> 0% | BJ48: =IF(BF48=0, 0, BG48/BF48) -> 0 | BK48: =IF(BG48=0, 0, BH48/BG48) -> 0 | BL48: NP | BM48: Meta 47.docx | BN48: 0 | BO48: 0 | BP48: 0 | BQ48: 0 | BR48: =+BN48+BP48 -> 0 | BS48: =+BO48+BQ48 -> 0 | BT48: =IFERROR(BS48/BR48, "") | BU48: 0 | BV48: 0 | BW48: 0 | BX48: 0 | BY48: =IFERROR(BW48/BV48, "") | BZ48: 6700000 | CA48: 6834000 | CB48: 6970680 | CC48: 7179800 | CD48: 27684480
A49: Eje 1. Ambiente, Conectividad y Ordenamiento y servicios públicos | B49: 0.235 | D49: 21 | E49: 2102 | F49: 6 | G49: Programa Integral de Innovación de Servicios Públicos domiciliarios de Tenjo (PIMSEPT) (Consolidación productiva del sector de energía eléctrica) | H49: 1900 | I49: 6.1 | J49: Es el tiempo de la mejora en gas natural domiciliario y alumbrado público | K49: 6.1.1 | L49: Aumentar en 30% la eficiencia energética y la sosteniblilidad en el sistema de Alumbrado Público en el municipio, reduciendo el consumo de energia y mejorando la percepción de seguiridad y satisfacción de los ciudadanos co la iluminación LED | M49: Porcentaje de eficiencia energética aumentado | N49: 0 | O49: 2102010 | P49: 2024257990006 | Q49: Ampliacion de la cobertura de gas natural y consolidación productiva del sector de energía eléctrica en el Municipio de Tenjo | R49: 48 | S49: Realizar en las 15 veredas expansión del alumbrado público pasando a tecnología LED y/o sostenible | T49: 0 | U49: Número | V49: I | W49: Número de veredas con expansión de alumbrado público | X49: Sec. Infraestructura y Obra Pública | Z49: =SUM(AF49:AI49) -> 15 | AA49: =AS49/Z49 -> 0.13333333 | AB49: =BI49/Z49 -> 0 | AE49: =SUMPRODUCT(AA49:AD49, {0.15,0.35,0.35,0.15}) -> 0.02 | AF49: 2 | AG49: 7 | AH49: 4 | AI49: 2 | AN49: 2 | AO49: 2 | AP49: 0 | AQ49: 0 | AR49: =(AJ49+AL49+AN49+AP49) -> 2 | AS49: =(AK49+AM49+AO49+AQ49) -> 2 | AT49: =AS49/AR49 -> 1 | AU49: =MIN((AR49 /AR49) * 100, 100) & "%" -> 100% | AV49: =IF(AR49=0, 0, AS49/AR49) -> 1 | AW49: P | AX49: META 48.docx | AY49: 0 | BA49: 0 | BC49: 0 | BE49: 0 | BG49: =(AY49+BA49+BC49+BE49) -> 0 | BH49: =(AZ49+BB49+BD49+BF49) -> 0 | BI49: =IF(BF49> 1, IF(BF49 = BG49, "100%", BF49 & "%"), IF(BF49 <= 0.01, "0%", BF49 * 100 & "%")) -> 0% | BJ49: =IF(BF49=0, 0, BG49/BF49) -> 0 | BK49: =IF(BG49=0, 0, BH49/BG49) -> 0 | BL49: NP | BM49: Meta 48.docx | BN49: 0 | BO49: 0 | BP49: 0 | BQ49: 0 | BR49: =+BN49+BP49 -> 0 | BS49: =+BO49+BQ49 -> 0 | BT49: =IFERROR(BS49/BR49, "") | BU49: 0 | BV49: 0 | BW49: 0 | BX49: 0 | BY49: =IFERROR(BW49/BV49, "") | BZ49: 0 | CA49: 0 | CB49: 0 | CC49: 0 | CD49: 0
A50: Eje 1. Ambiente, Conectividad y Ordenamiento y servicios públicos | B50: 0.235 | D50: 21 | E50: 2102 | F50: 6 | G50: Programa Integral de Innovación de Servicios Públicos domiciliarios de Tenjo (PIMSEPT) (Consolidación productiva del sector de energía eléctrica) | H50: 1900 | I50: 6.1 | J50: Es el tiempo de la mejora en gas natural domiciliario y alumbrado público | K50: 6.1.1 | L50: Aumentar en 30% la eficiencia energética y la sosteniblilidad en el sistema de Alumbrado Público en el municipio, reduciendo el consumo de energia y mejorando la percepción de seguiridad y satisfacción de los ciudadanos co la iluminación LED | M50: Porcentaje de eficiencia energética aumentado | N50: 0 | O50: 2102011 | P50: 2024257990006 | Q50: Ampliacion de la cobertura de gas natural y consolidación productiva del sector de energía eléctrica en el Municipio de Tenjo | R50: 49 | S50: Garantizar al 100% el Costo de Administración Operación, Mantenimiento y del sistema de Alumbrado Público | T50: 0 | U50: Porcentaje | V50: I | W50: CAOM AP garantizado | X50: Sec. Infraestructura y Obra Pública | Z50: =SUM(AF50:AI50)/4 -> 1 | AA50: =AS50/Z50 -> 1 | AB50: =BI50/Z50 -> 0.4 | AE50: =SUMPRODUCT(AA50:AD50, {0.15,0.35,0.35,0.15}) -> 0.29 | AF50: 1 | AG50: 1 | AH50: 1 | AI50: 1 | AN50: 1 | AO50: 1 | AP50: 1 | AQ50: 1 | AR50: =(AJ50+AL50+AN50+AP50)/2 -> 1 | AS50: =(AK50+AM50+AO50+AQ50)/2 -> 1 | AT50: =AS50/AR50 -> 1 | AU50: =MIN((AR50 /AR50) * 100, 100) & "%" -> 100% | AV50: =IF(AR50=0, 0, AS50/AR50) -> 1 | AW50: P | AX50: META 49.docx | AY50: 0 | AZ50: 0 | BA50: 0.5 | BB50: 0.4 | BC50: 0.3 | BD50: 0 | BE50: 0.2 | BG50: =(AY50+BA50+BC50+BE50) -> 1 | BH50: =(AZ50+BB50+BD50+BF50) -> 0.4 | BI50: =BH50/BG50 -> 0.4 | BJ50: =MIN((BG50 /BG50) * 100, 100) & "%" -> 100% | BK50: =IF(BG50=0, 0, BH50/BG50) -> 0.4 | BL50: P | BM50: Meta 49.docx | BN50: 3251611798 | BO50: 0 | BP50: 1503082651 | BQ50: 1503082651 | BR50: =+BN50+BP50 -> 4754694449 | BS50: =+BO50+BQ50 -> 1503082651 | BT50: =IFERROR(BS50/BR50, "") -> 0.31612602 | BU50: 1400000000 | BV50: 3251611798 | BW50: 1975578209 | BX50: 1975578209 | BY50: =IFERROR(BW50/BV50, "") -> 0.6075689 | BZ50: 2302503603 | CA50: 2417628783 | CB50: 2538510222 | CC50: 2665435733 | CD50: 9924078341
A51: Eje 1. Ambiente, Conectividad y Ordenamiento y servicios públicos | B51: 0.235 | D51: 21 | E51: 2102 | F51: 6 | G51: Programa Integral de Innovación de Servicios Públicos domiciliarios de Tenjo (PIMSEPT) (Consolidación productiva del sector de energía eléctrica) | H51: 1900 | I51: 6.1 | J51: Es el tiempo de la mejora en gas natural domiciliario y alumbrado público | K51: 6.1.1 | L51: Aumentar en 30% la eficiencia energética y la sosteniblilidad en el sistema de Alumbrado Público en el municipio, reduciendo el consumo de energia y mejorando la percepción de seguiridad y satisfacción de los ciudadanos co la iluminación LED | M51: Porcentaje de eficiencia energética aumentado | N51: 0 | O51: 2102069 | P51: 2024257990006 | Q51: Ampliacion de la cobertura de gas natural y consolidación productiva del sector de energía eléctrica en el Municipio de Tenjo | R51: 50 | S51: Garantizar al 100% el Costo de suminsitro energia del sistema de Alumbrado Público | T51: 1 | U51: Porcentaje | V51: M | W51: Suminsitro AP garantizado | X51: Sec. Infraestructura y Obra Pública | Z51: =SUM(AF51:AI51)/4 -> 1 | AA51: =AS51/Z51 -> 1 | AB51: =BI51/Z51 -> 1 | AE51: =SUMPRODUCT(AA51:AD51, {0.15,0.35,0.35,0.15}) -> 0.5 | AF51: 1 | AG51: 1 | AH51: 1 | AI51: 1 | AN51: 0.001 | AO51: 0 | AP51: 1 | AQ51: 1 | AR51: =(AJ51+AL51+AN51+AP51) -> 1.001 | AS51: =(AK51+AM51+AO51+AQ51) -> 1 | AT51: =AS51/AR51 -> 0.999001 | AU51: =MIN((AR51 /AR51) * 100, 100) & "%" -> 100% | AV51: =IF(AR51=0, 0, AS51/AR51) -> 0.999001 | AW51: P | AX51: META 50.docx | AY51: 1 | AZ51: 1 | BA51: 1 | BB51: 1 | BC51: 1 | BD51: 1 | BE51: 1 | BG51: =(AY51+BA51+BC51+BE51)/4 -> 1 | BH51: =(AZ51+BB51+BD51+BF51)/3 -> 1 | BI51: =BH51/BG51 -> 1 | BJ51: =MIN((BG51 /BG51) * 100, 100) & "%" -> 100% | BK51: =IF(BG51=0, 0, BH51/BG51) -> 1 | BL51: P | BM51: Meta 50.docx | BN51: 2300000000 | BO51: 0 | BP51: 0 | BQ51: 0 | BR51: =+BN51+BP51 -> 2300000000 | BS51: =+BO51+BQ51 -> 0 | BT51: =IFERROR(BS51/BR51, "") -> 0 | BU51: 2300000000 | BV51: 2300000000 | BW51: 761853887 | BX51: 761853887 | BY51: =IFERROR(BW51/BV51, "") -> 0.33124082 | BZ51: 1000000000 | CA51: 500000000 | CB51: 500000000 | CC51: 515000000 | CD51: 2515000000
A52: Eje 1. Ambiente, Conectividad y Ordenamiento y servicios públicos | B52: 0.235 | D52: 21 | E52: 2102 | F52: 6 | G52: Programa Integral de Innovación de Servicios Públicos domiciliarios de Tenjo (PIMSEPT) (Consolidación productiva del sector de energía eléctrica) | H52: 1900 | I52: 6.1 | J52: Es el tiempo de la mejora en gas natural domiciliario y alumbrado público | K52: 6.1.1 | L52: Aumentar en 30% la eficiencia energética y la sosteniblilidad en el sistema de Alumbrado Público en el municipio, reduciendo el consumo de energia y mejorando la percepción de seguiridad y satisfacción de los ciudadanos co la iluminación LED | M52: Porcentaje de eficiencia energética aumentado | N52: 0 | O52: 2102069 | P52: 2024257990006 | Q52: Ampliacion de la cobertura de gas natural y consolidación productiva del sector de energía eléctrica en el Municipio de Tenjo | R52: 51 | S52: Realizar un un estudio técnico de referencia que determine el costo-beneficio del impuesto de Alumbrado Público de acuerdo con el Art 351 de Ley 1819 de 2016 | T52: 0 | U52: Número | V52: I | W52: Estudio técnico realizado | X52: Sec. Infraestructura y Obra Pública | Z52: =SUM(AF52:AI52) -> 1 | AA52: =AS52/Z52 -> 0 | AB52: =BI52/Z52 -> 0 | AE52: =SUMPRODUCT(AA52:AD52, {0.15,0.35,0.35,0.15}) -> 0 | AF52: 0 | AG52: 0 | AH52: 1 | AI52: 0 | AN52: 0 | AO52: 0 | AP52: 0 | AQ52: 0 | AR52: 0 | AS52: =(AK52+AM52+AO52+AQ52)/2 -> 0 | AT52: =IF(AQ52=0, 0, AR52/AQ52) -> 0 | AU52: =IF(AR52<= 0.01, "0%", IF(AR52 > 1, AR52, AR52 * 100) & "%") -> 0% | AV52: =IF(AR52=0, 0, AS52/AR52) -> 0 | AW52: NP | AY52: 0 | BA52: 0 | BC52: 0 | BE52: 0 | BG52: =(AY52+BA52+BC52+BE52) -> 0 | BH52: =(AZ52+BB52+BD52+BF52) -> 0 | BI52: =IF(BF52> 1, IF(BF52 = BG52, "100%", BF52 & "%"), IF(BF52 <= 0.01, "0%", BF52 * 100 & "%")) -> 0% | BJ52: =IF(BF52=0, 0, BG52/BF52) -> 0 | BK52: =IF(BG52=0, 0, BH52/BG52) -> 0 | BL52: NP | BM52: Meta 51.docx | BN52: 0 | BO52: 0 | BP52: 0 | BQ52: 0 | BR52: =+BN52+BP52 -> 0 | BS52: =+BO52+BQ52 -> 0 | BT52: =IFERROR(BS52/BR52, "") | BU52: 0 | BV52: 0 | BW52: 0 | BX52: 0 | BY52: =IFERROR(BW52/BV52, "") | BZ52: 0 | CA52: 0 | CB52: 300000000 | CC52: 0 | CD52: 300000000
A53: Eje 1. Ambiente, Conectividad y Ordenamiento y servicios públicos | B53: 0.235 | D53: 21 | E53: 2102 | F53: 6 | G53: Programa Integral de Innovación de Servicios Públicos domiciliarios de Tenjo (PIMSEPT) (Consolidación productiva del sector de energía eléctrica) | H53: 1900 | I53: 6.1 | J53: Es el tiempo de la mejora en gas natural domiciliario y alumbrado público | K53: 6.1.2 | L53: Incrementar en 26% los nuevos usuarios del servicio de gas natural | M53: Porcentaje de nuevos usuarios de gas natural | N53: 420 Fuente: Vanti-Gas Natural 2023 | O53: 2102071 | P53: 2024257990006 | Q53: Ampliacion de la cobertura de gas natural y consolidación productiva del sector de energía eléctrica en el Municipio de Tenjo | R53: 52 | S53: Aumentar en 570 nuevos usuarios la cobertura de gas natural en el municipio de Tenjo | T53: 420 2020-2023 | U53: Número | V53: I | W53: Número de nuevos usuarios con cobertura de gas natural | X53: Sec. Infraestructura y Obra Pública | Z53: =SUM(AF53:AI53) -> 151 | AA53: =AS53/Z53 -> 0.86092715 | AB53: =BI53/Z53 -> 0 | AE53: =SUMPRODUCT(AA53:AD53, {0.15,0.35,0.35,0.15}) -> 0.12913907 | AF53: 130 | AG53: 21 | AH53: 0 | AI53: 0 | AN53: 0.001 | AO53: 0 | AP53: 130 | AQ53: 130 | AR53: =(AJ53+AL53+AN53+AP53) -> 130.001 | AS53: =(AK53+AM53+AO53+AQ53) -> 130 | AT53: =AS53/AR53 -> 0.99999231 | AU53: =MIN((AR53 /AR53) * 100, 100) & "%" -> 100% | AV53: =IF(AR53=0, 0, AS53/AR53) -> 0.99999231 | AW53: P | AX53: META 52.docx | AY53: 0 | BA53: 0 | BC53: 0 | BE53: 0 | BG53: =(AY53+BA53+BC53+BE53) -> 0 | BH53: =(AZ53+BB53+BD53+BF53) -> 0 | BI53: =IF(BF53> 1, IF(BF53 = BG53, "100%", BF53 & "%"), IF(BF53 <= 0.01, "0%", BF53 * 100 & "%")) -> 0% | BJ53: =IF(BF53=0, 0, BG53/BF53) -> 0 | BK53: =IF(BG53=0, 0, BH53/BG53) -> 0 | BL53: NP | BM53: Meta 52.docx | BN53: 30500000 | BO53: 0 | BP53: 114000000 | BQ53: 114000000 | BR53: =+BN53+BP53 -> 144500000 | BS53: =+BO53+BQ53 -> 114000000 | BT53: =IFERROR(BS53/BR53, "") -> 0.78892734 | BU53: 30500000 | BV53: 0 | BW53: 0 | BX53: 0 | BY53: =IFERROR(BW53/BV53, "") | BZ53: 114000000 | CA53: 0 | CB53: 0 | CC53: 0 | CD53: 114000000
A54: Eje 1. Ambiente, Conectividad y Ordenamiento y servicios públicos | B54: 0.235 | D54: 24 | E54: 2402 | F54: 7 | G54: Es el tiempo del Mejoramiento de vial (Infraestrcutura red vial regional) | H54: 0600 | I54: 7.1 | J54: Es tiempo del Mejoramiento y Mantenimiento Vial | K54: 7.1.1 | L54: Incrementar en 5% la construcción, mejoramiento, mantenimiento y optimización de la red vial en el municipio | M54: Porcentaje de construcción, mejoramiento, mantenimiento y optimización de la red vial en el municipio incrementado | N54: 125,838 mts lineales Fuente: Informe emplame 2023 | O54: 2402042 | P54: 2024257990007 | Q54: Mejoramiento de la infraestructura red vial regional inteligente y sostenible del Municipio de Tenjo Cundinamarca | R54: 53 | S54: Construir 2.000 metros lineales de placas huella para el mejoramiento de la malla vial rural del municipio de Tenjo. | T54: 1402 mts lineales | U54: Mts | V54: I | W54: Metros lineales de placa huellas construidas | X54: Sec. Infraestructura y Obra Pública | Z54: =SUM(AF54:AI54) -> 2000 | AA54: =AS54/Z54 -> 0.8155 | AB54: =BI54/Z54 -> 0.0001 | AE54: =SUMPRODUCT(AA54:AD54, {0.15,0.35,0.35,0.15}) -> 0.12236 | AF54: 1500 | AG54: 500 | AH54: 0 | AI54: 0 | AN54: 1500 | AO54: 1631 | AP54: 0 | AQ54: 0 | AR54: =(AJ54+AL54+AN54+AP54) -> 1500 | AS54: =(AK54+AM54+AO54+AQ54) -> 1631 | AT54: =AS54/AR54 -> 1.0873333 | AU54: =MIN((AR54 /AR54) * 100, 100) & "%" -> 100% | AV54: =IF(AR54=0, 0, AS54/AR54) -> 1.0873333 | AW54: P | AX54: META 53.docx | AY54: 0 | AZ54: 0 | BA54: 0 | BB54: 0 | BC54: 200 | BD54: 100 | BE54: 300 | BG54: =(AY54+BA54+BC54+BE54) -> 500 | BH54: =(AZ54+BB54+BD54+BF54) -> 100 | BI54: =BH54/BG54 -> 0.2 | BJ54: =MIN((BG54 /BG54) * 100, 100) & "%" -> 100% | BK54: =IF(BG54=0, 0, BH54/BG54) -> 0.2 | BL54: P | BM54: Meta 53.docx | BN54: 500000000 | BO54: 20750000 | BP54: 10833334 | BQ54: 10833334 | BR54: =+BN54+BP54 -> 510833334 | BS54: =+BO54+BQ54 -> 31583334 | BT54: =IFERROR(BS54/BR54, "") -> 0.061827081 | BU54: 500000000 | BV54: 20750000 | BW54: 20750000 | BX54: 15219950 | BY54: =IFERROR(BW54/BV54, "") -> 1 | BZ54: 900000000 | CA54: 1200000000 | CB54: 2300000000 | CC54: 1200000000 | CD54: 5600000000
A55: Eje 1. Ambiente, Conectividad y Ordenamiento y servicios públicos | B55: 0.235 | D55: 24 | E55: 2402 | F55: 7 | G55: Es el tiempo del Mejoramiento de vial (Infraestrcutura red vial regional) | H55: 0600 | I55: 7.1 | J55: Es tiempo del Mejoramiento y Mantenimiento Vial | K55: 7.1.1 | L55: Incrementar en 5% la construcción, mejoramiento, mantenimiento y optimización de la red vial en el municipio | M55: Porcentaje de construcción, mejoramiento, mantenimiento y optimización de la red vial en el municipio incrementado | N55: 125,838 mts lineales Fuente: Informe emplame 2023 | O55: 2402112 | P55: 2024257990007 | Q55: Mejoramiento de la infraestructura red vial regional inteligente y sostenible del Municipio de Tenjo Cundinamarca | R55: 54 | S55: Intervenir anualmente con mantenimiento 113 kilómetros de vías rurales | T55: 113 km | U55: Km | V55: I | W55: Kilómetros de vías terciarias mantenidas | X55: Sec. Infraestructura y Obra Pública | Z55: =SUM(AF55:AI55)/4 -> 113 | AA55: =AS55/Z55 -> 0.75221239 | AB55: =BI55/Z55 -> 0.0089122093 | AE55: =SUMPRODUCT(AA55:AD55, {0.15,0.35,0.35,0.15}) -> 0.11595113 | AF55: 113 | AG55: 113 | AH55: 113 | AI55: 113 | AN55: 17 | AO55: 17 | AP55: 96 | AQ55: 68 | AR55: =(AJ55+AL55+AN55+AP55) -> 113 | AS55: =(AK55+AM55+AO55+AQ55) -> 85 | AT55: =AS55/AR55 -> 0.75221239 | AU55: =MIN((AR55 /AR55) * 100, 100) & "%" -> 100% | AV55: =IF(AR55=0, 0, AS55/AR55) -> 0.75221239 | AW55: P | AX55: META 54.docx | AY55: 15 | AZ55: 15.8 | BA55: 30 | BB55: 30 | BC55: 68 | BD55: 68 | BE55: 0 | BG55: =(AY55+BA55+BC55+BE55) -> 113 | BH55: =(AZ55+BB55+BD55+BF55) -> 113.8 | BI55: =BH55/BG55 -> 1.0070796 | BJ55: =MIN((BG55 /BG55) * 100, 100) & "%" -> 100% | BK55: =IF(BG55=0, 0, BH55/BG55) -> 1.0070796 | BL55: P | BM55: Meta 54.docx | BN55: 2814425187 | BO55: 402705000 | BP55: 585161616 | BQ55: 585161616 | BR55: =+BN55+BP55 -> 3399586803 | BS55: =+BO55+BQ55 -> 987866616 | BT55: =IFERROR(BS55/BR55, "") -> 0.29058432 | BU55: 2214425187 | BV55: 2814425187 | BW55: 2187255501 | BX55: 1206781056 | BY55: =IFERROR(BW55/BV55, "") -> 0.77715887 | BZ55: 2000000000 | CA55: 2040000000 | CB55: 2080800000 | CC55: 2143224000 | CD55: 8264024000
A56: Eje 1. Ambiente, Conectividad y Ordenamiento y servicios públicos | B56: 0.235 | D56: 24 | E56: 2402 | F56: 7 | G56: Es el tiempo del Mejoramiento de vial (Infraestrcutura red vial regional) | H56: 0600 | I56: 7.1 | J56: Es tiempo del Mejoramiento y Mantenimiento Vial | K56: 7.1.1 | L56: Incrementar en 5% la construcción, mejoramiento, mantenimiento y optimización de la red vial en el municipio | M56: Porcentaje de construcción, mejoramiento, mantenimiento y optimización de la red vial en el municipio incrementado | N56: 125,838 mts lineales Fuente: Informe emplame 2023 | O56: 2402115 | P56: 2024257990007 | Q56: Mejoramiento de la infraestructura red vial regional inteligente y sostenible del Municipio de Tenjo Cundinamarca | R56: 55 | S56: Intervenir con mantenimiento 16.5 kilómetros de vías urbanas | T56: 10,8 Km | U56: Km | V56: I | W56: Kilómetros de vías urbanas mantenidas | X56: Sec. Infraestructura y Obra Pública | Z56: =SUM(AF56:AI56) -> 16500 | AA56: =AS56/Z56 -> 0.072727273 | AB56: =BI56/Z56 -> 2.698685e-05 | AE56: =SUMPRODUCT(AA56:AD56, {0.15,0.35,0.35,0.15}) -> 0.010918536 | AF56: 1200 | AG56: 5300 | AH56: 8000 | AI56: 2000 | AN56: 0.001 | AO56: 0 | AP56: 1200 | AQ56: 1200 | AR56: =(AJ56+AL56+AN56+AP56) -> 1200.001 | AS56: =(AK56+AM56+AO56+AQ56) -> 1200 | AT56: =AS56/AR56 -> 0.99999917 | AU56: =MIN((AR56 /AR56) * 100, 100) & "%" -> 100% | AV56: =IF(AR56=0, 0, AS56/AR56) -> 0.99999917 | AW56: P | AX56: META 55.docx | AY56: 0.3 | AZ56: 0.36 | BA56: 3 | BB56: 2 | BC56: 1 | BD56: 0 | BE56: 1 | BG56: =(AY56+BA56+BC56+BE56) -> 5.3 | BH56: =(AZ56+BB56+BD56+BF56) -> 2.36 | BI56: =BH56/BG56 -> 0.44528302 | BJ56: =MIN((BG56 /BG56) * 100, 100) & "%" -> 100% | BK56: =IF(BG56=0, 0, BH56/BG56) -> 0.44528302 | BL56: P | BM56: Meta 55.docx | BN56: 720758148 | BO56: 53750000 | BP56: 12000000 | BQ56: 12000000 | BR56: =+BN56+BP56 -> 732758148 | BS56: =+BO56+BQ56 -> 65750000 | BT56: =IFERROR(BS56/BR56, "") -> 0.08972947 | BU56: 720758148 | BV56: 1469360479 | BW56: 1466429358 | BX56: 41625000 | BY56: =IFERROR(BW56/BV56, "") -> 0.99800517 | BZ56: 1900108917 | CA56: 1941115895 | CB56: 1983209903 | CC56: 2034496383 | CD56: 7858931099
A57: Eje 1. Ambiente, Conectividad y Ordenamiento y servicios públicos | B57: 0.235 | D57: 24 | E57: 2402 | F57: 7 | G57: Es el tiempo del Mejoramiento de vial (Infraestrcutura red vial regional) | H57: 0600 | I57: 7.1 | J57: Es tiempo del Mejoramiento y Mantenimiento Vial | K57: 7.1.1 | L57: Incrementar en 5% la construcción, mejoramiento, mantenimiento y optimización de la red vial en el municipio | M57: Porcentaje de construcción, mejoramiento, mantenimiento y optimización de la red vial en el municipio incrementado | N57: 125,838 mts lineales Fuente: Informe emplame 2023 | O57: 2402113 | P57: 2024257990007 | Q57: Mejoramiento de la infraestructura red vial regional inteligente y sostenible del Municipio de Tenjo Cundinamarca | R57: 56 | S57: Construir 700 metros lineales de vías urbanas en el municipio de Tenjo | T57: 635 mts | U57: Mts | V57: I | W57: Metros de vías urbanas construidas | X57: Sec. Infraestructura y Obra Pública | Z57: =SUM(AF57:AI57) -> 700 | AA57: =AS57/Z57 -> 0 | AB57: =BI57/Z57 -> 0.00042857143 | AE57: =SUMPRODUCT(AA57:AD57, {0.15,0.35,0.35,0.15}) -> 0.00015 | AF57: 0 | AG57: 200 | AH57: 300 | AI57: 200 | AN57: 0 | AO57: 0 | AP57: 0 | AQ57: 0 | AR57: 0 | AS57: =(AK57+AM57+AO57+AQ57)/2 -> 0 | AT57: =IF(AQ57=0, 0, AR57/AQ57) -> 0 | AU57: =IF(AR57> 1, IF(AR57 = AS57, "100%", AR57 & "%"), IF(AR57 <= 0.01, "0%", AR57 * 100 & "%")) -> 0% | AV57: =IF(AR57=0, 0, AS57/AR57) -> 0 | AW57: NP | AY57: 0 | AZ57: 0 | BA57: 0 | BB57: 0 | BC57: 100 | BD57: 60 | BE57: 100 | BG57: =(AY57+BA57+BC57+BE57) -> 200 | BH57: =(AZ57+BB57+BD57+BF57) -> 60 | BI57: =BH57/BG57 -> 0.3 | BJ57: =MIN((BG57 /BG57) * 100, 100) & "%" -> 100% | BK57: =IF(BG57=0, 0, BH57/BG57) -> 0.3 | BL57: P | BM57: Meta 56.docx | BN57: 584868720 | BO57: 20000000 | BP57: 21166667 | BQ57: 21166667 | BR57: =+BN57+BP57 -> 606035387 | BS57: =+BO57+BQ57 -> 41166667 | BT57: =IFERROR(BS57/BR57, "") -> 0.067927827 | BU57: 584868720 | BV57: 1126106501 | BW57: 1126106501 | BX57: 20000000 | BY57: =IFERROR(BW57/BV57, "") -> 1 | BZ57: 2724545117 | CA57: 2520772373 | CB57: 2315363237 | CC57: 2728414041 | CD57: 10289094768
A58: Eje 1. Ambiente, Conectividad y Ordenamiento y servicios públicos | B58: 0.235 | D58: 24 | E58: 2402 | F58: 7 | G58: Es el tiempo del Mejoramiento de vial (Infraestrcutura red vial regional) | H58: 0600 | I58: 7.1 | J58: Es tiempo del Mejoramiento y Mantenimiento Vial | K58: 7.1.1 | L58: Incrementar en 5% la construcción, mejoramiento, mantenimiento y optimización de la red vial en el municipio | M58: Porcentaje de construcción, mejoramiento, mantenimiento y optimización de la red vial en el municipio incrementado | N58: 125,838 mts lineales Fuente: Informe emplame 2023 | O58: 2402041 | P58: 2024257990007 | Q58: Mejoramiento de la infraestructura red vial regional inteligente y sostenible del Municipio de Tenjo Cundinamarca | R58: 57 | S58: Suscribir minímo 1 convenio interadministrativo con entidades e instituciones a nivel local, departamental y/o nacional para el desarrollo de proyectos de infraestructura | T58: 1 | U58: Número | V58: I | W58: Numero de convenios suscritos | X58: Sec. Infraestructura y Obra Pública | Z58: =SUM(AF58:AI58)/3 -> 1 | AA58: =AS58/Z58 -> 0 | AB58: =BI58/Z58 -> 0 | AE58: =SUMPRODUCT(AA58:AD58, {0.15,0.35,0.35,0.15}) -> 0 | AF58: 0 | AG58: 1 | AH58: 1 | AI58: 1 | AN58: 0 | AO58: 0 | AP58: 0 | AQ58: 0 | AR58: 0 | AS58: =(AK58+AM58+AO58+AQ58) -> 0 | AT58: =IF(AQ58=0, 0, AR58/AQ58) -> 0 | AU58: =IF(AR58> 1, IF(AR58 = AS58, "100%", AR58 & "%"), IF(AR58 <= 0.01, "0%", AR58 * 100 & "%")) -> 0% | AV58: =IF(AR58=0, 0, AS58/AR58) -> 0 | AW58: NP | AY58: 0 | AZ58: 0 | BA58: 0 | BB58: 0 | BC58: 0 | BD58: 0 | BE58: 0 | BF58: 0 | BG58: =(AY58+BA58+BC58+BE58) -> 0 | BH58: =(AZ58+BB58+BD58+BF58) -> 0 | BI58: =IF(BF58> 1, IF(BF58 = BG58, "100%", BF58 & "%"), IF(BF58 <= 0.01, "0%", BF58 * 100 & "%")) -> 0% | BJ58: =IF(BF58=0, 0, BG58/BF58) -> 0 | BK58: =IF(BG58=0, 0, BH58/BG58) -> 0 | BL58: NP | BM58: Meta 57.docx | BN58: 0 | BO58: 0 | BP58: 0 | BQ58: 0 | BR58: =+BN58+BP58 -> 0 | BS58: =+BO58+BQ58 -> 0 | BT58: =IFERROR(BS58/BR58, "") | BU58: 0 | BV58: 0 | BW58: 0 | BX58: 0 | BY58: =IFERROR(BW58/BV58, "") | BZ58: 0 | CA58: 3500000000 | CB58: 1500000000 | CC58: 2000000000 | CD58: 7000000000
A59: Eje 1. Ambiente, Conectividad y Ordenamiento y servicios públicos | B59: 0.235 | D59: 24 | E59: 2402 | F59: 7 | G59: Es el tiempo del Mejoramiento de vial (Infraestrcutura red vial regional) | H59: 0600 | I59: 7.1 | J59: Es tiempo del Mejoramiento y Mantenimiento Vial | K59: 7.1.1 | L59: Incrementar en 5% la construcción, mejoramiento, mantenimiento y optimización de la red vial en el municipio | M59: Porcentaje de construcción, mejoramiento, mantenimiento y optimización de la red vial en el municipio incrementado | N59: 125,838 mts lineales Fuente: Informe emplame 2023 | O59: 2402056 | P59: 2024257990007 | Q59: Mejoramiento de la infraestructura red vial regional inteligente y sostenible del Municipio de Tenjo Cundinamarca | R59: 58 | S59: Realizar 3 procesos de intervención en los corredores viales principales | T59: SD | U59: Número | V59: I | W59: Número de corredores viales con procesos de intervención realizados | X59: Sec. Infraestructura y Obra Pública | Z59: =SUM(AF59:AI59) -> 3 | AA59: =AS59/Z59 -> 0.33333333 | AB59: =BI59/Z59 -> 0 | AE59: =SUMPRODUCT(AA59:AD59, {0.15,0.35,0.35,0.15}) -> 0.05 | AF59: 1 | AG59: 0 | AH59: 1 | AI59: 1 | AN59: 0.001 | AO59: 0 | AP59: 1 | AQ59: 1 | AR59: =(AJ59+AL59+AN59+AP59) -> 1.001 | AS59: =(AK59+AM59+AO59+AQ59) -> 1 | AT59: =IF(AQ59=0, 0, AR59/AQ59) -> 1.001 | AU59: =MIN((AR59 /AR59) * 100, 100) & "%" -> 100% | AV59: =IF(AR59=0, 0, AS59/AR59) -> 0.999001 | AW59: P | AX59: META 58.docx | AY59: 0 | BA59: 0 | BC59: 0 | BE59: 0 | BG59: =(AY59+BA59+BC59+BE59) -> 0 | BH59: =(AZ59+BB59+BD59+BF59) -> 0 | BI59: =IF(BF59> 1, IF(BF59 = BG59, "100%", BF59 & "%"), IF(BF59 <= 0.01, "0%", BF59 * 100 & "%")) -> 0% | BJ59: =IF(BF59=0, 0, BG59/BF59) -> 0 | BK59: =IF(BG59=0, 0, BH59/BG59) -> 0 | BL59: NP | BM59: Meta 58.docx | BN59: 0 | BO59: 0 | BP59: 0 | BQ59: 0 | BR59: =+BN59+BP59 -> 0 | BS59: =+BO59+BQ59 -> 0 | BT59: =IFERROR(BS59/BR59, "") | BU59: 0 | BV59: 0 | BW59: 0 | BX59: 0 | BY59: =IFERROR(BW59/BV59, "") | BZ59: 0 | CA59: 0 | CB59: 0 | CC59: 7000000000 | CD59: 7000000000
A60: Eje 1. Ambiente, Conectividad y Ordenamiento y servicios públicos | B60: 0.235 | D60: 24 | E60: 2402 | F60: 7 | G60: Es el tiempo del Mejoramiento de vial (Infraestrcutura red vial regional) | H60: 0600 | I60: 7.1 | J60: Es tiempo del Mejoramiento y Mantenimiento Vial | K60: 7.1.1 | L60: Incrementar en 5% la construcción, mejoramiento, mantenimiento y optimización de la red vial en el municipio | M60: Porcentaje de construcción, mejoramiento, mantenimiento y optimización de la red vial en el municipio incrementado | N60: 125,838 mts lineales Fuente: Informe emplame 2023 | O60: 2402125 | P60: 2024257990007 | Q60: Mejoramiento de la infraestructura red vial regional inteligente y sostenible del Municipio de Tenjo Cundinamarca | R60: 59 | S60: Modernizar en mínimo 2 unidades la maquinaria amarilla para el desarrollo de mantenimientos viales e infraestructura | T60: 0 | U60: Número | V60: I | W60: Número de unidades de maquinaria modernizados | X60: Sec. Infraestructura y Obra Pública | Z60: =SUM(AF60:AI60) -> 2 | AA60: =AS60/Z60 -> 1 | AB60: =BI60/Z60 -> 0 | AE60: =SUMPRODUCT(AA60:AD60, {0.15,0.35,0.35,0.15}) -> 0.15 | AF60: 2 | AG60: 0 | AH60: 0 | AI60: 0 | AN60: 0.1 | AO60: 0.1 | AP60: 1.9 | AQ60: 1.9 | AR60: =(AJ60+AL60+AN60+AP60) -> 2 | AS60: =(AK60+AM60+AO60+AQ60) -> 2 | AT60: =AS60/AR60 -> 1 | AU60: =MIN((AR60 /AR60) * 100, 100) & "%" -> 100% | AV60: =IF(AR60=0, 0, AS60/AR60) -> 1 | AW60: P | AX60: META 59.docx | AY60: 0 | AZ60: 0 | BA60: 0 | BB60: 0 | BC60: 0 | BE60: 0 | BG60: =(AY60+BA60+BC60+BE60) -> 0 | BH60: =(AZ60+BB60+BD60+BF60) -> 0 | BI60: =IF(BF60> 1, IF(BF60 = BG60, "100%", BF60 & "%"), IF(BF60 <= 0.01, "0%", BF60 * 100 & "%")) -> 0% | BJ60: =IF(BF62=0, 0, BG62/BF62) -> 0 | BK60: =IF(BG60=0, 0, BH60/BG60) -> 0 | BL60: NP | BM60: Meta 59.docx | BN60: 600000000 | BO60: 0 | BP60: 1151203977 | BQ60: 1151203977 | BR60: =+BN60+BP60 -> 1751203977 | BS60: =+BO60+BQ60 -> 1151203977 | BT60: =IFERROR(BS60/BR60, "") -> 0.65737858 | BU60: 600000000 | BV60: 0 | BW60: 0 | BX60: 0 | BY60: =IFERROR(BW60/BV60, "") | BZ60: 0 | CA60: 1500000000 | CB60: 0 | CC60: 0 | CD60: 1500000000
A61: Eje 1. Ambiente, Conectividad y Ordenamiento y servicios públicos | B61: 0.235 | D61: 24 | E61: 2402 | F61: 8 | G61: Movilidad Inteligente y Sostenible de Tenjo (MIST) (Infraestrcutura red vial regional) | H61: 0600 | I61: 8.1 | J61: Promoción de la Movilidad Sostenible y Educación Vial | K61: 8.1.1 | L61: Implementar al 100% el subprograma de Movilidad Sostenible y Educación vial | M61: Porcentaje de subprograma implementado | N61: 0 | O61: 2402033 | P61: 2024257990008 | Q61: Desarrollar Infraestructura red vial regional | R61: 60 | S61: Construir 1.000 metros lineales de ciclo rutas en el casco urbano y rural del municipio de Tenjo. | T61: 0 | U61: Mts | V61: I | W61: Metros lineales construidos de ciclo rutas | X61: Sec. Infraestructura y Obra Pública | Z61: =SUM(AF61:AI61) -> 1000 | AA61: =AS61/Z61 -> 0.220001 | AB61: =BI61/Z61 -> 0.0003 | AE61: =SUMPRODUCT(AA61:AD61, {0.15,0.35,0.35,0.15}) -> 0.03310515 | AF61: 220 | AG61: 220 | AH61: 440 | AI61: 120 | AN61: 0.001 | AO61: 0.001 | AP61: 220 | AQ61: 220 | AR61: =(AJ61+AL61+AN61+AP61) -> 220.001 | AS61: =(AK61+AM61+AO61+AQ61) -> 220.001 | AT61: =AS61/AR61 -> 1 | AU61: =IF(AR61> 1, IF(AR61 = AS61, "100%", AR61 & "%"), IF(AR61 <= 0.01, "0%", AR61 * 100 & "%")) -> 100% | AV61: =IF(AR61=0, 0, AS61/AR61) -> 1 | AW61: P | AX61: META 60.docx | AY61: 0 | AZ61: 0 | BA61: 0 | BB61: 0 | BC61: 100 | BD61: 60 | BE61: 100 | BG61: =(AY61+BA61+BC61+BE61) -> 200 | BH61: =(AZ61+BB61+BD61+BF61) -> 60 | BI61: =BH61/BG61 -> 0.3 | BJ61: =MIN((BG61 /BG61) * 100, 100) & "%" -> 100% | BK61: =IF(BG61=0, 0, BH61/BG61) -> 0.3 | BL61: P | BM61: Meta 60.docx | BN61: 88515586 | BO61: 0 | BP61: 99296561 | BQ61: 99296561 | BR61: =+BN61+BP61 -> 187812147 | BS61: =+BO61+BQ61 -> 99296561 | BT61: =IFERROR(BS61/BR61, "") -> 0.52870148 | BU61: 88515586 | BV61: 522527805 | BW61: 522527805 | BX61: 0 | BY61: =IFERROR(BW61/BV61, "") -> 1 | BZ61: 1019794652 | CA61: 220898748 | CB61: 421943685 | CC61: 523040869 | CD61: 2185677954
A62: Eje 1. Ambiente, Conectividad y Ordenamiento y servicios públicos | B62: 0.235 | D62: 24 | E62: 2402 | F62: 8 | G62: Movilidad Inteligente y Sostenible de Tenjo (MIST) (Infraestrcutura red vial regional) | H62: 0600 | I62: 8.1 | J62: Promoción de la Movilidad Sostenible y Educación Vial | K62: 8.1.1 | L62: Implementar al 100% el subprograma de Movilidad Sostenible y Educación vial | M62: Porcentaje de subprograma implementado | N62: 0 | O62: 2402033 | P62: 2024257990008 | Q62: Desarrollar Infraestructura red vial regional | R62: 61 | S62: Definir un carril exclusivo para el uso de la bicicleta y de fomento de medios alternativos de movilización | T62: 0 | U62: Número | V62: I | W62: Carril exclusivo definido | X62: Sec. Infraestructura y Obra Pública | Z62: =SUM(AF62:AI62) -> 1 | AA62: =AS62/Z62 -> 0 | AB62: =BI62/Z62 -> 0 | AE62: =SUMPRODUCT(AA62:AD62, {0.15,0.35,0.35,0.15}) -> 0 | AF62: 0 | AG62: 0 | AH62: 0.7 | AI62: 0.3 | AN62: 0 | AO62: 0 | AP62: 0 | AQ62: 0 | AR62: 0 | AS62: =(AK62+AM62+AO62+AQ62)/2 -> 0 | AT62: =IF(AQ62=0, 0, AR62/AQ62) -> 0 | AU62: =IF(AR62> 1, IF(AR62 = AS62, "100%", AR62 & "%"), IF(AR62 <= 0.01, "0%", AR62 * 100 & "%")) -> 0% | AV62: =IF(AR62=0, 0, AS62/AR62) -> 0 | AW62: NP | AY62: 0 | BA62: 0 | BC62: 0 | BE62: 0 | BG62: =(AY62+BA62+BC62+BE62) -> 0 | BH62: =(AZ62+BB62+BD62+BF62) -> 0 | BI62: =IF(BF62> 1, IF(BF62 = BG62, "100%", BF62 & "%"), IF(BF62 <= 0.01, "0%", BF62 * 100 & "%")) -> 0% | BJ62: =IF(BF62=0, 0, BG62/BF62) -> 0 | BK62: =IF(BG62=0, 0, BH62/BG62) -> 0 | BL62: NP | BM62: Meta 61.docx | BN62: 0 | BO62: 0 | BP62: 0 | BQ62: 0 | BR62: =+BN62+BP62 -> 0 | BS62: =+BO62+BQ62 -> 0 | BT62: =IFERROR(BS62/BR62, "") | BU62: 0 | BV62: 0 | BW62: 0 | BX62: 0 | BY62: =IFERROR(BW62/BV62, "") | BZ62: 0 | CA62: 300000000 | CB62: 309000000 | CC62: 318270000 | CD62: 927270000
A63: Eje 1. Ambiente, Conectividad y Ordenamiento y servicios públicos | B63: 0.235 | D63: 24 | E63: 2402 | F63: 8 | G63: Movilidad Inteligente y Sostenible de Tenjo (MIST) (Infraestrcutura red vial regional) | H63: 0600 | I63: 8.1 | J63: Promoción de la Movilidad Sostenible y Educación Vial | K63: 8.1.1 | L63: Implementar al 100% el subprograma de Movilidad Sostenible y Educación vial | M63: Porcentaje de subprograma implementado | N63: 0 | O63: 2402129 | P63: 2024257990008 | Q63: Desarrollar Infraestructura red vial regional | R63: 62 | S63: Establecer un circuito de sistema de bicicletas compartidas | T63: 0 | U63: Número | V63: I | W63: Número de circuitos establecidos | X63: Sec. Infraestructura y Obra Pública | Z63: =SUM(AF63:AI63) -> 1 | AA63: =AS63/Z63 -> 0 | AB63: =BI63/Z63 -> 0 | AE63: =SUMPRODUCT(AA63:AD63, {0.15,0.35,0.35,0.15}) -> 0 | AF63: 0 | AG63: 0.7 | AH63: 0.3 | AI63: 0 | AN63: 0 | AO63: 0 | AP63: 0 | AQ63: 0 | AR63: 0 | AS63: =(AK63+AM63+AO63+AQ63)/2 -> 0 | AT63: =IF(AQ63=0, 0, AR63/AQ63) -> 0 | AU63: =IF(AR63> 1, IF(AR63 = AS63, "100%", AR63 & "%"), IF(AR63 <= 0.01, "0%", AR63 * 100 & "%")) -> 0% | AV63: =IF(AR63=0, 0, AS63/AR63) -> 0 | AW63: NP | AY63: 0 | BA63: 0 | BC63: 0 | BE63: 0 | BG63: =(AY63+BA63+BC63+BE63) -> 0 | BH63: =(AZ63+BB63+BD63+BF63) -> 0 | BI63: =IF(BF63> 1, IF(BF63 = BG63, "100%", BF63 & "%"), IF(BF63 <= 0.01, "0%", BF63 * 100 & "%")) -> 0% | BJ63: =IF(BF63=0, 0, BG63/BF63) -> 0 | BK63: =IF(BG63=0, 0, BH63/BG63) -> 0 | BL63: NP | BM63: Meta 62.docx | BN63: 0 | BO63: 0 | BP63: 0 | BQ63: 0 | BR63: =+BN63+BP63 -> 0 | BS63: =+BO63+BQ63 -> 0 | BT63: =IFERROR(BS63/BR63, "") | BU63: 0 | BV63: 0 | BW63: 0 | BX63: 0 | BY63: =IFERROR(BW63/BV63, "") | BZ63: 0 | CA63: 200000000 | CB63: 200000000 | CC63: 200000000 | CD63: 600000000
A64: Eje 1. Ambiente, Conectividad y Ordenamiento y servicios públicos | B64: 0.235 | D64: 24 | E64: 2402 | F64: 8 | G64: Movilidad Inteligente y Sostenible de Tenjo (MIST) (Infraestrcutura red vial regional) | H64: 0600 | I64: 8.1 | J64: Promoción de la Movilidad Sostenible y Educación Vial | K64: 8.1.1 | L64: Implementar al 100% el subprograma de Movilidad Sostenible y Educación vial | M64: Porcentaje de subprograma implementado | N64: 0 | O64: 2402104 | P64: 2024257990008 | Q64: Desarrollar Infraestructura red vial regional | R64: 63 | S64: Desarrollar dos programas de educación vial dirigidos a la comunidad, con especial enfoque en los usuarios de ciclo rutas y peatones. | T64: 0 | U64: Número | V64: I | W64: Número de programas desarrollados | X64: Sec. Gobierno y convivencia ciudadana o quien haga sus veces | Z64: =SUM(AF64:AI64) -> 2 | AA64: =AS64/Z64 -> 0 | AB64: =BI64/Z64 -> 0 | AE64: =SUMPRODUCT(AA64:AD64, {0.15,0.35,0.35,0.15}) -> 0 | AF64: 0 | AG64: 0 | AH64: 1 | AI64: 1 | AN64: 0 | AO64: 0 | AP64: 0 | AQ64: 0 | AR64: 0 | AS64: =(AK64+AM64+AO64+AQ64)/2 -> 0 | AT64: =IF(AQ64=0, 0, AR64/AQ64) -> 0 | AU64: =IF(AR64> 1, IF(AR64 = AS64, "100%", AR64 & "%"), IF(AR64 <= 0.01, "0%", AR64 * 100 & "%")) -> 0% | AV64: =IF(AR64=0, 0, AS64/AR64) -> 0 | AW64: NP | AX64: Meta 63.docx | AY64: 0 | BA64: 0 | BC64: 0 | BE64: 0 | BG64: =(AY64+BA64+BC64+BE64) -> 0 | BH64: =(AZ64+BB64+BD64+BF64) -> 0 | BI64: =IF(BF64> 1, IF(BF64 = BG64, "100%", BF64 & "%"), IF(BF64 <= 0.01, "0%", BF64 * 100 & "%")) -> 0% | BJ64: =IF(BF64=0, 0, BG64/BF64) -> 0 | BK64: =IF(BG64=0, 0, BH64/BG64) -> 0 | BL64: NP | BM64: Meta 63.docx | BN64: 0 | BO64: 0 | BP64: 0 | BQ64: 0 | BR64: =+BN64+BP64 -> 0 | BS64: =+BO64+BQ64 -> 0 | BT64: =IFERROR(BS64/BR64, "") | BU64: 0 | BV64: 0 | BW64: 0 | BX64: 0 | BY64: =IFERROR(BW64/BV64, "") | BZ64: 0 | CA64: 30000000 | CB64: 30900000 | CC64: 31827000 | CD64: 92727000
A65: Eje 1. Ambiente, Conectividad y Ordenamiento y servicios públicos | B65: 0.235 | D65: 24 | E65: 2402 | F65: 8 | G65: Movilidad Inteligente y Sostenible de Tenjo (MIST) (Infraestrcutura red vial regional) | H65: 0600 | I65: 8.1 | J65: Promoción de la Movilidad Sostenible y Educación Vial | K65: 8.1.1 | L65: Implementar al 100% el subprograma de Movilidad Sostenible y Educación vial | M65: Porcentaje de subprograma implementado | N65: 0 | O65: 2402033 | P65: 2024257990008 | Q65: Desarrollar Infraestructura red vial regional | R65: 64 | S65: Generar dos iniciativas de movilidad sostenible, incluyendo el incentivo al uso de transporte público y bicicletas | T65: 0 | U65: Número | V65: I | W65: Número de iniciativas generadas | X65: Sec. Gobierno y convivencia ciudadana o quien haga sus veces | Z65: =SUM(AF65:AI65) -> 2 | AA65: =AS65/Z65 -> 0 | AB65: =BI65/Z65 -> 0 | AE65: =SUMPRODUCT(AA65:AD65, {0.15,0.35,0.35,0.15}) -> 0 | AF65: 0 | AG65: 0 | AH65: 1 | AI65: 1 | AN65: 0 | AO65: 0 | AP65: 0 | AQ65: 0 | AR65: 0 | AS65: =(AK65+AM65+AO65+AQ65)/2 -> 0 | AT65: =IF(AQ65=0, 0, AR65/AQ65) -> 0 | AU65: =IF(AR65> 1, IF(AR65 = AS65, "100%", AR65 & "%"), IF(AR65 <= 0.01, "0%", AR65 * 100 & "%")) -> 0% | AV65: =IF(AR65=0, 0, AS65/AR65) -> 0 | AW65: NP | AX65: Meta 64.docx | AY65: 0 | BA65: 0 | BC65: 0 | BE65: 0 | BG65: =(AY65+BA65+BC65+BE65) -> 0 | BH65: =(AZ65+BB65+BD65+BF65) -> 0 | BI65: =IF(BF65> 1, IF(BF65 = BG65, "100%", BF65 & "%"), IF(BF65 <= 0.01, "0%", BF65 * 100 & "%")) -> 0% | BJ65: =IF(BF65=0, 0, BG65/BF65) -> 0 | BK65: =IF(BG65=0, 0, BH65/BG65) -> 0 | BL65: NP | BM65: Meta 64.docx | BN65: 0 | BO65: 0 | BP65: 0 | BQ65: 0 | BR65: =+BN65+BP65 -> 0 | BS65: =+BO65+BQ65 -> 0 | BT65: =IFERROR(BS65/BR65, "") | BU65: 0 | BV65: 0 | BW65: 0 | BX65: 0 | BY65: =IFERROR(BW65/BV65, "") | BZ65: 0 | CA65: 30000000 | CB65: 30900000 | CC65: 31827000 | CD65: 92727000
A66: Eje 1. Ambiente, Conectividad y Ordenamiento y servicios públicos | B66: 0.235 | D66: 24 | E66: 2402 | F66: 8 | G66: Movilidad Inteligente y Sostenible de Tenjo (MIST) (Infraestrcutura red vial regional) | H66: 0600 | I66: 8.1 | J66: Promoción de la Movilidad Sostenible y Educación Vial | K66: 8.1.1 | L66: Implementar al 100% el subprograma de Movilidad Sostenible y Educación vial | M66: Porcentaje de subprograma implementado | N66: 0 | O66: 2402005 | P66: 2024257990008 | Q66: Desarrollar Infraestructura red vial regional | R66: 65 | S66: Instalar 3 paraderos inteligentes en la zona rural y urbana del municipio | T66: 0 | U66: Número | V66: I | W66: Número de paraderos inteligentes instalados | X66: Sec. Infraestructura y Obra Pública | Z66: =SUM(AF66:AI66) -> 3 | AA66: =AS66/Z66 -> 1 | AB66: =BI66/Z66 -> 0 | AE66: =SUMPRODUCT(AA66:AD66, {0.15,0.35,0.35,0.15}) -> 0.15 | AF66: 3 | AG66: 0 | AH66: 0 | AI66: 0 | AN66: 0.2 | AO66: 0.2 | AP66: 2.8 | AQ66: 2.8 | AR66: =(AJ66+AL66+AN66+AP66) -> 3 | AS66: =(AK66+AM66+AO66+AQ66) -> 3 | AT66: =AS66/AR66 -> 1 | AU66: =MIN((AR66 /AR66) * 100, 100) & "%" -> 100% | AV66: =IF(AR66=0, 0, AS66/AR66) -> 1 | AW66: P | AX66: META 65.docx | AY66: 0 | BA66: 0 | BC66: 0 | BE66: 0 | BG66: =(AY66+BA66+BC66+BE66) -> 0 | BH66: =(AZ66+BB66+BD66+BF66) -> 0 | BI66: =IF(BF66> 1, IF(BF66 = BG66, "100%", BF66 & "%"), IF(BF66 <= 0.01, "0%", BF66 * 100 & "%")) -> 0% | BJ66: =IF(BF66=0, 0, BG66/BF66) -> 0 | BK66: =IF(BG66=0, 0, BH66/BG66) -> 0 | BL66: NP | BM66: Meta 65.docx | BN66: 0 | BO66: 0 | BP66: 800000000 | BQ66: 800000000 | BR66: =+BN66+BP66 -> 800000000 | BS66: =+BO66+BQ66 -> 800000000 | BT66: =IFERROR(BS66/BR66, "") -> 1 | BU66: 0 | BV66: 0 | BW66: 0 | BX66: 0 | BY66: =IFERROR(BW66/BV66, "") | BZ66: 0 | CA66: 0 | CB66: 250000000 | CC66: 260000000 | CD66: 510000000
A67: Eje 1. Ambiente, Conectividad y Ordenamiento y servicios públicos | B67: 0.235 | D67: 24 | E67: 2402 | F67: 8 | G67: Movilidad Inteligente y Sostenible de Tenjo (MIST) (Infraestrcutura red vial regional) | H67: 0600 | I67: 8.1 | J67: Es tiempo de la Movilidad y Seguridad Vial | K67: 8.1.2 | L67: Incrementar a 100% los procesos de señalización viale instalación de barreras de protección | M67: Porcentaje de procesos incrementados | N67: 0 | O67: 2402002 | P67: 2024257990008 | Q67: Desarrollar Infraestructura red vial regional | R67: 66 | S67: Realizar 2 procesos de compra e instalación de señalización vial en el casco urbano y las 15 veredas del municipio de Tenjo. | T67: 1 | U67: Número | V67: I | W67: Número de procesos de compra realizados | X67: Sec. Infraestructura y Obra Pública | Z67: =SUM(AF67:AI67) -> 2 | AA67: =AS67/Z67 -> 0 | AB67: =BI67/Z67 -> 0.1 | AE67: =SUMPRODUCT(AA67:AD67, {0.15,0.35,0.35,0.15}) -> 0.035 | AF67: 0 | AG67: 1 | AH67: 1 | AI67: 0 | AN67: 0 | AO67: 0 | AP67: 0 | AQ67: 0 | AR67: 0 | AS67: =(AK67+AM67+AO67+AQ67)/2 -> 0 | AT67: =IF(AQ67=0, 0, AR67/AQ67) -> 0 | AU67: =IF(AR67> 1, IF(AR67 = AS67, "100%", AR67 & "%"), IF(AR67 <= 0.01, "0%", AR67 * 100 & "%")) -> 0% | AV67: =IF(AR67=0, 0, AS67/AR67) -> 0 | AW67: NP | AY67: 0 | AZ67: 0 | BA67: 0 | BB67: 0 | BC67: 0.3 | BD67: 0.2 | BE67: 0.7 | BG67: =(AY67+BA67+BC67+BE67) -> 1 | BH67: =(AZ67+BB67+BD67+BF67) -> 0.2 | BI67: =BH67/BG67 -> 0.2 | BJ67: =MIN((BG67 /BG67) * 100, 100) & "%" -> 100% | BK67: =IF(BG67=0, 0, BH67/BG67) -> 0.2 | BL67: P | BM67: Meta 66.docx | BN67: 100000000 | BO67: 0 | BP67: 0 | BQ67: 0 | BR67: =+BN67+BP67 -> 100000000 | BS67: =+BO67+BQ67 -> 0 | BT67: =IFERROR(BS67/BR67, "") -> 0 | BU67: 100000000 | BV67: 100000000 | BW67: 100000000 | BX67: 0 | BY67: =IFERROR(BW67/BV67, "") -> 1 | BZ67: 0 | CA67: 200000000 | CB67: 180000000 | CC67: 180000000 | CD67: 560000000
A68: Eje 1. Ambiente, Conectividad y Ordenamiento y servicios públicos | B68: 0.235 | D68: 24 | E68: 2402 | F68: 8 | G68: Movilidad Inteligente y Sostenible de Tenjo (MIST) (Infraestrcutura red vial regional) | H68: 0600 | I68: 8.1 | J68: Es tiempo de la Movilidad y Seguridad Vial | K68: 8.1.2 | L68: Incrementar a 100% los procesos de señalización viale instalación de barreras de protección | M68: Porcentaje de procesos incrementados | N68: 0 | O68: 2402135 | P68: 2024257990008 | Q68: Desarrollar Infraestructura red vial regional | R68: 67 | S68: Suministrar e Instalar 1000 metros lineales de barreras metálicas de protección vial | T68: 0 | U68: Mts | V68: I | W68: Metros lineales de barreras de protección vial instalada | X68: Sec. Infraestructura y Obra Pública | Z68: =SUM(AF68:AI68) -> 1000 | AA68: =AS68/Z68 -> 0 | AB68: =BI68/Z68 -> 0 | AE68: =SUMPRODUCT(AA68:AD68, {0.15,0.35,0.35,0.15}) -> 0 | AF68: 0 | AG68: 0 | AH68: 700 | AI68: 300 | AN68: 0 | AO68: 0 | AP68: 0 | AQ68: 0 | AR68: 0 | AS68: =(AK68+AM68+AO68+AQ68)/2 -> 0 | AT68: =IF(AQ68=0, 0, AR68/AQ68) -> 0 | AU68: =IF(AR68> 1, IF(AR68 = AS68, "100%", AR68 & "%"), IF(AR68 <= 0.01, "0%", AR68 * 100 & "%")) -> 0% | AV68: =IF(AR68=0, 0, AS68/AR68) -> 0 | AW68: NP | AY68: 0 | BA68: 0 | BC68: 0 | BE68: 0 | BG68: =(AY68+BA68+BC68+BE68) -> 0 | BH68: =(AZ68+BB68+BD68+BF68) -> 0 | BI68: =IF(BF68> 1, IF(BF68 = BG68, "100%", BF68 & "%"), IF(BF68 <= 0.01, "0%", BF68 * 100 & "%")) -> 0% | BJ68: =IF(BF68=0, 0, BG68/BF68) -> 0 | BK68: =IF(BG68=0, 0, BH68/BG68) -> 0 | BL68: NP | BM68: Meta 67.docx | BN68: 0 | BO68: 0 | BP68: 0 | BQ68: 0 | BR68: =+BN68+BP68 -> 0 | BS68: =+BO68+BQ68 -> 0 | BT68: =IFERROR(BS68/BR68, "") | BU68: 0 | BV68: 0 | BW68: 0 | BX68: 0 | BY68: =IFERROR(BW68/BV68, "") | BZ68: 250000000 | CA68: 300000000 | CB68: 0 | CC68: 0 | CD68: 550000000
A69: Eje 1. Ambiente, Conectividad y Ordenamiento y servicios públicos | B69: 0.235 | D69: 24 | E69: 2402 | F69: 8 | G69: Movilidad Inteligente y Sostenible de Tenjo (MIST) (Infraestrcutura red vial regional) | H69: 0600 | I69: 8.1 | J69: Es tiempo de la Movilidad y Seguridad Vial | K69: 8.1.3 | L69: Incrementar a 100% las acciones de planificación, seguridad y monitoreo que mejoren las condciones de tránsito y movilidad | M69: Porcentaje de acciones incrementadas | N69: 0.25 | O69: 2402104 | P69: 2024257990008 | Q69: Desarrollar Infraestructura red vial regional | R69: 68 | S69: Formular e implementar en un 40% el plan vial municipal | T69: 1 | U69: Número | V69: M | W69: Plan vial formulado e implementado | X69: Sec. Gobierno y convivencia ciudadana o quien haga sus veces | Z69: =SUM(AF69:AI69) -> 0.4 | AA69: =AS69/Z69 -> 0 | AB69: =BI69/Z69 -> 2.3648649 | AE69: =SUMPRODUCT(AA69:AD69, {0.15,0.35,0.35,0.15}) -> 0.8277027 | AF69: 0 | AG69: 0.2 | AH69: 0.1 | AI69: 0.1 | AN69: 0 | AO69: 0 | AP69: 0 | AQ69: 0 | AR69: 0 | AS69: =(AK69+AM69+AO69+AQ69)/2 -> 0 | AT69: =IF(AQ69=0, 0, AR69/AQ69) -> 0 | AU69: =IF(AR69> 1, IF(AR69 = AS69, "100%", AR69 & "%"), IF(AR69 <= 0.01, "0%", AR69 * 100 & "%")) -> 0% | AV69: =IF(AR69=0, 0, AS69/AR69) -> 0 | AW69: NP | AX69: Meta 68.docx | AY69: 0 | AZ69: 0 | BA69: 0.05 | BB69: 0.05 | BC69: 0.3 | BD69: 0.3 | BE69: 0.02 | BG69: =(AY69+BA69+BC69+BE69) -> 0.37 | BH69: =(AZ69+BB69+BD69+BF69) -> 0.35 | BI69: =BH69/BG69 -> 0.94594595 | BJ69: =MIN((BG69 /BG69) * 100, 100) & "%" -> 100% | BK69: =IF(BG69=0, 0, BH69/BG69) -> 0.94594595 | BL69: P | BM69: Meta 68.docx | BN69: 400000000 | BO69: 0 | BP69: 0 | BQ69: 0 | BR69: =+BN69+BP69 -> 400000000 | BS69: =+BO69+BQ69 -> 0 | BT69: =IFERROR(BS69/BR69, "") -> 0 | BU69: 250000000 | BV69: 400000000 | BW69: 400000000 | BX69: 0 | BY69: =IFERROR(BW69/BV69, "") -> 1 | BZ69: 600000000 | CA69: 0 | CB69: 0 | CC69: 0 | CD69: 600000000
A70: Eje 1. Ambiente, Conectividad y Ordenamiento y servicios públicos | B70: 0.235 | D70: 24 | E70: 2402 | F70: 8 | G70: Movilidad Inteligente y Sostenible de Tenjo (MIST) (Infraestrcutura red vial regional) | H70: 0600 | I70: 8.1 | J70: Es tiempo de la Movilidad y Seguridad Vial | K70: 8.1.3 | L70: Incrementar a 100% las acciones de planificación, seguridad y monitoreo que mejoren las condciones de tránsito y movilidad | M70: Porcentaje de acciones incrementadas | N70: 0.25 | O70: 2402104 | P70: 2024257990008 | Q70: Desarrollar Infraestructura red vial regional | R70: 69 | S70: Actualizar el Plan de Movilidad implementando las acciones que mejoren las condiciones de movilidad y seguridad vial | T70: 1 | U70: Número | V70: I | W70: Plan de Movilidad Actualizado | X70: Sec. Gobierno y convivencia ciudadana o quien haga sus veces | Z70: =SUM(AF70:AI70) -> 1 | AA70: =AS70/Z70 -> 0.05 | AB70: =BI70/Z70 -> 0.59375 | AE70: =SUMPRODUCT(AA70:AD70, {0.15,0.35,0.35,0.15}) -> 0.2153125 | AF70: 0.05 | AG70: 0.33 | AH70: 0.33 | AI70: 0.29 | AN70: 0.02 | AO70: 0.02 | AP70: 0.03 | AQ70: 0.03 | AR70: =(AJ70+AL70+AN70+AP70) -> 0.05 | AS70: =(AK70+AM70+AO70+AQ70) -> 0.05 | AT70: =AS70/AR70 -> 1 | AU70: =MIN((AR70 /AR70) * 100, 100) & "%" -> 100% | AV70: =IF(AR70=0, 0, AS70/AR70) -> 1 | AW70: P | AX70: Meta 69.docx | AY70: 0 | AZ70: 0 | BA70: 0.05 | BB70: 0.05 | BC70: 0.14 | BD70: 0.14 | BE70: 0.13 | BG70: =(AY70+BA70+BC70+BE70) -> 0.32 | BH70: =(AZ70+BB70+BD70+BF70) -> 0.19 | BI70: =BH70/BG70 -> 0.59375 | BJ70: =MIN((BG70 /BG70) * 100, 100) & "%" -> 100% | BK70: =IF(BG70=0, 0, BH70/BG70) -> 0.59375 | BL70: NP | BM70: Meta 69.docx | BN70: 0 | BO70: 0 | BP70: 0 | BQ70: 0 | BR70: =+BN70+BP70 -> 0 | BS70: =+BO70+BQ70 -> 0 | BT70: =IFERROR(BS70/BR70, "") | BU70: 0 | BV70: 0 | BW70: 0 | BX70: 0 | BY70: =IFERROR(BW70/BV70, "") | BZ70: 500000000 | CA70: 350000000 | CB70: 300000000 | CC70: 400000000 | CD70: 1550000000
A71: Eje 1. Ambiente, Conectividad y Ordenamiento y servicios públicos | B71: 0.235 | D71: 24 | E71: 2402 | F71: 8 | G71: Movilidad Inteligente y Sostenible de Tenjo (MIST) (Infraestrcutura red vial regional) | H71: 0600 | I71: 8.1 | J71: Es tiempo de la Movilidad y Seguridad Vial | K71: 8.1.3 | L71: Incrementar a 100% las acciones de planificación, seguridad y monitoreo que mejoren las condciones de tránsito y movilidad | M71: Porcentaje de acciones incrementadas | N71: 0.25 | O71: 2402129 | P71: 2024257990008 | Q71: Desarrollar Infraestructura red vial regional | R71: 70 | S71: Implementar un sistema de monitoreo y gestión de tráfico en tiempo real que utilice analítica de datos, reconocimiento de placas de vehículos y reconocimiento facial, en los principales corredores viales de Tenjo. | T71: 0 | U71: Número | V71: I | W71: Sistema de monitoreo y gestión implementado | X71: Sec. Gobierno y convivencia ciudadana o quien haga sus veces | Z71: =SUM(AF71:AI71) -> 0.99 | AA71: =AS71/Z71 -> 0 | AB71: =BI71/Z71 -> 0 | AE71: =SUMPRODUCT(AA71:AD71, {0.15,0.35,0.35,0.15}) -> 0 | AF71: 0 | AG71: 0.33 | AH71: 0.33 | AI71: 0.33 | AN71: 0 | AO71: 0 | AP71: 0 | AQ71: 0 | AR71: 0 | AS71: =(AK71+AM71+AO71+AQ71)/2 -> 0 | AT71: =IF(AQ71=0, 0, AR71/AQ71) -> 0 | AU71: =IF(AR71> 1, IF(AR71 = AS71, "100%", AR71 & "%"), IF(AR71 <= 0.01, "0%", AR71 * 100 & "%")) -> 0% | AV71: =IF(AR71=0, 0, AS71/AR71) -> 0 | AW71: NP | AX71: Meta 70.docx | AY71: 0 | BA71: 0 | BC71: 0 | BE71: 0 | BG71: =(AY71+BA71+BC71+BE71) -> 0 | BH71: =(AZ71+BB71+BD71+BF71) -> 0 | BI71: =IF(BF71> 1, IF(BF71 = BG71, "100%", BF71 & "%"), IF(BF71 <= 0.01, "0%", BF71 * 100 & "%")) -> 0% | BJ71: =IF(BF71=0, 0, BG71/BF71) -> 0 | BK71: =IF(BG71=0, 0, BH71/BG71) -> 0 | BL71: NP | BM71: Meta 70.docx | BN71: 0 | BO71: 0 | BP71: 0 | BQ71: 0 | BR71: =+BN71+BP71 -> 0 | BS71: =+BO71+BQ71 -> 0 | BT71: =IFERROR(BS71/BR71, "") | BU71: 0 | BV71: 0 | BW71: 0 | BX71: 0 | BY71: =IFERROR(BW71/BV71, "") | BZ71: 500000000 | CA71: 120000000 | CB71: 150000000 | CC71: 150000000 | CD71: 920000000
A72: Eje 1. Ambiente, Conectividad y Ordenamiento y servicios públicos | B72: 0.235 | D72: 24 | E72: 2402 | F72: 8 | G72: Movilidad Inteligente y Sostenible de Tenjo (MIST) (Infraestrcutura red vial regional) | H72: 0600 | I72: 8.1 | J72: Es tiempo de la Movilidad y Seguridad Vial | K72: 8.1.3 | L72: Incrementar a 100% las acciones de planificación, seguridad y monitoreo que mejoren las condciones de tránsito y movilidad | M72: Porcentaje de acciones incrementadas | N72: 0.25 | O72: 2402120 | P72: 2024257990008 | Q72: Desarrollar Infraestructura red vial regional | R72: 71 | S72: Implementar 8 acciones para mejorar las condiciones de tránsito | T72: SD | U72: Número | V72: I | W72: Número de acciones implementadas | X72: Sec. Gobierno y convivencia ciudadana o quien haga sus veces | Z72: =SUM(AF72:AI72) -> 8 | AA72: =AS72/Z72 -> 0.125 | AB72: =BI72/Z72 -> 0.10625 | AE72: =SUMPRODUCT(AA72:AD72, {0.15,0.35,0.35,0.15}) -> 0.0559375 | AF72: 1 | AG72: 2 | AH72: 3 | AI72: 2 | AN72: 0.4 | AO72: 0.4 | AP72: 0.6 | AQ72: 0.6 | AR72: =(AJ72+AL72+AN72+AP72) -> 1 | AS72: =(AK72+AM72+AO72+AQ72) -> 1 | AT72: =AS72/AR72 -> 1 | AU72: =MIN((AR72 /AR72) * 100, 100) & "%" -> 100% | AV72: =IF(AR72=0, 0, AS72/AR72) -> 1 | AW72: P | AX72: Meta 71.docx | AY72: 0 | AZ72: 0 | BA72: 0 | BB72: 0 | BC72: 1.7 | BD72: 1.7 | BE72: 0.3 | BG72: =(AY72+BA72+BC72+BE72) -> 2 | BH72: =(AZ72+BB72+BD72+BF72) -> 1.7 | BI72: =BH72/BG72 -> 0.85 | BJ72: =MIN((BG72 /BG72) * 100, 100) & "%" -> 100% | BK72: =IF(BG72=0, 0, BH72/BG72) -> 0.85 | BL72: P | BM72: Meta 71.docx | BN72: 360000000 | BO72: 0 | BP72: 0 | BQ72: 0 | BR72: =+BN72+BP72 -> 360000000 | BS72: =+BO72+BQ72 -> 0 | BT72: =IFERROR(BS72/BR72, "") -> 0 | BU72: 360000000 | BV72: 360000000 | BW72: 320000000 | BX72: 0 | BY72: =IFERROR(BW72/BV72, "") -> 0.88888889 | BZ72: 500000000 | CA72: 100000000 | CB72: 150000000 | CC72: 150000000 | CD72: 900000000
A73: Eje 1. Ambiente, Conectividad y Ordenamiento y servicios públicos | B73: 0.235 | D73: 40 | E73: 4002 | F73: 9 | G73: Es el tiempo de espacio público innovador (Ordenamiento territorial y desarrollo urbano) | H73: 1400 | I73: 9.1 | J73: Un espacio para todos | K73: 9.1.1. | L73: Incrementar en 0,31% el índice de espacio público del municipio | M73: Índice de espacio público | N73: 349.200 mts Fuente: Sec Urbanismo | O73: 4002019 | P73: 2024257990009 | Q73: Mejoramiento del espacio público innovador del municipio de Tenjo Cundinamarca | R73: 72 | S73: Mejorar y/o construir 600 metros cuadrados de andenes en el municipio de Tenjo | T73: 226 mts | U73: Mts 2 | V73: I | W73: Número de metros cuadrados de andenes construidos | X73: Sec. Infraestructura y Obra Pública | Z73: =SUM(AF73:AI73) -> 600 | AA73: =AS73/Z73 -> 0 | AB73: =BI73/Z73 -> 0.00043859649 | AE73: =SUMPRODUCT(AA73:AD73, {0.15,0.35,0.35,0.15}) -> 0.00015350877 | AF73: 0 | AG73: 380 | AH73: 120 | AI73: 100 | AN73: 0 | AO73: 0 | AP73: 0 | AQ73: 0 | AR73: 0 | AS73: =(AK73+AM73+AO73+AQ73)/2 -> 0 | AT73: =IF(AQ73=0, 0, AR73/AQ73) -> 0 | AU73: =IF(AR73> 1, IF(AR73 = AS73, "100%", AR73 & "%"), IF(AR73 <= 0.01, "0%", AR73 * 100 & "%")) -> 0% | AV73: =IF(AR73=0, 0, AS73/AR73) -> 0 | AW73: NP | AY73: 0 | AZ73: 0 | BA73: 0 | BB73: 0 | BC73: 120 | BD73: 100 | BE73: 260 | BG73: =(AY73+BA73+BC73+BE73) -> 380 | BH73: =(AZ73+BB73+BD73+BF73) -> 100 | BI73: =BH73/BG73 -> 0.26315789 | BJ73: =MIN((BG73 /BG73) * 100, 100) & "%" -> 100% | BK73: =IF(BG73=0, 0, BH73/BG73) -> 0.26315789 | BL73: P | BM73: Meta 72.docx | BN73: 100000000 | BO73: 26500000 | BP73: 17813333 | BQ73: 17813333 | BR73: =+BN73+BP73 -> 117813333 | BS73: =+BO73+BQ73 -> 44313333 | BT73: =IFERROR(BS73/BR73, "") -> 0.37613173 | BU73: 100000000 | BV73: 714722669 | BW73: 712360169 | BX73: 21477550 | BY73: =IFERROR(BW73/BV73, "") -> 0.99669452 | BZ73: 2500000000 | CA73: 0 | CB73: 0 | CC73: 0 | CD73: 2500000000
A74: Eje 1. Ambiente, Conectividad y Ordenamiento y servicios públicos | B74: 0.235 | D74: 40 | E74: 4002 | F74: 9 | G74: Es el tiempo de espacio público innovador (Ordenamiento territorial y desarrollo urbano) | H74: 1400 | I74: 9.1 | J74: Un espacio para todos | K74: 9.1.1. | L74: Incrementar en 0,31% el índice de espacio público del municipio | M74: Índice de espacio público | N74: 349.200 mts Fuente: Sec Urbanismo | O74: 4002019 | P74: 2024257990009 | Q74: Mejoramiento del espacio público innovador del municipio de Tenjo Cundinamarca | R74: 73 | S74: Construir 500 metros cuadrados de alameda en el casco urbano del municipio de Tenjo | T74: 0 | U74: Mts 2 | V74: I | W74: Número de alameda construidos | X74: Sec. Infraestructura y Obra Pública | Y74: SI | Z74: =SUM(AF74:AI74) -> 500 | AA74: =AS74/Z74 -> 0 | AB74: =BI74/Z74 -> 0.0004 | AE74: =SUMPRODUCT(AA74:AD74, {0.15,0.35,0.35,0.15}) -> 0.00014 | AF74: 0 | AG74: 100 | AH74: 100 | AI74: 300 | AN74: 0 | AO74: 0 | AP74: 0 | AQ74: 0 | AR74: 0 | AS74: =(AK74+AM74+AO74+AQ74)/2 -> 0 | AT74: =IF(AQ74=0, 0, AR74/AQ74) -> 0 | AU74: =IF(AR74> 1, IF(AR74 = AS74, "100%", AR74 & "%"), IF(AR74 <= 0.01, "0%", AR74 * 100 & "%")) -> 0% | AV74: =IF(AR74=0, 0, AS74/AR74) -> 0 | AW74: NP | AY74: 0 | AZ74: 0 | BA74: 0 | BB74: 0 | BC74: 40 | BD74: 20 | BE74: 60 | BG74: =(AY74+BA74+BC74+BE74) -> 100 | BH74: =(AZ74+BB74+BD74+BF74) -> 20 | BI74: =BH74/BG74 -> 0.2 | BJ74: =MIN((BG74 /BG74) * 100, 100) & "%" -> 100% | BK74: =IF(BG74=0, 0, BH74/BG74) -> 0.2 | BL74: P | BM74: Meta 73.docx | BN74: 1129476420 | BO74: 0 | BP74: 0 | BQ74: 0 | BR74: =+BN74+BP74 -> 1129476420 | BS74: =+BO74+BQ74 -> 0 | BT74: =IFERROR(BS74/BR74, "") -> 0 | BU74: 300000000 | BV74: 1129476420 | BW74: 1129476420 | BX74: 0 | BY74: =IFERROR(BW74/BV74, "") -> 1 | BZ74: 2500000000 | CA74: 0 | CB74: 0 | CC74: 0 | CD74: 2500000000
A75: Eje 1. Ambiente, Conectividad y Ordenamiento y servicios públicos | B75: 0.235 | D75: 40 | E75: 4001 | F75: 10 | G75: Es el tiempo de la vivienda y Desarrollo Sostenible para Tenjo (Acceso a soluciones de vivienda) | H75: 1400 | I75: 10.1 | J75: Mejoramiento Habitacional | K75: 10.1.1 | L75: Reducir a 8,97 el déficit cualitativo de vivienda del municipio | M75: Déficit cualitativo de viviedna | N75: 12.5 Fuente: Dane VIHOPE 4258 viviendas con destino habitacional Fuente: Sec. Planeación 2024 | O75: 4001032 | P75: 2024257990010 | Q75: Mejoramiento habitacional y acceso a la vivienda y desarrollo sostenible en el Municipio de Tenjo Cundinamarca | R75: 74 | S75: Realizar al 100% los estudios técnicos y jurídicos para los beneficiaros de mejoras de vivienda, solicitados por los interesados. | T75: 1 | U75: Porcentaje | V75: M | W75: Porcentaje de estudios técnicos y jurídicos realizados | X75: Sec. de Urbanismo | Z75: =SUM(AF75:AI75) -> 1 | AA75: =AS75/Z75 -> 0 | AB75: =BI75/Z75 -> 0 | AE75: =SUMPRODUCT(AA75:AD75, {0.15,0.35,0.35,0.15}) -> 0 | AF75: 0 | AG75: 0.3 | AH75: 0.4 | AI75: 0.3 | AN75: 0 | AO75: 0 | AP75: 0 | AQ75: 0 | AR75: 0 | AS75: =(AK75+AM75+AO75+AQ75)/2 -> 0 | AT75: =IF(AQ75=0, 0, AR75/AQ75) -> 0 | AU75: =IF(AR75> 1, IF(AR75 = AS75, "100%", AR75 & "%"), IF(AR75 <= 0.01, "0%", AR75 * 100 & "%")) -> 0% | AV75: =IF(AR75=0, 0, AS75/AR75) -> 0 | AW75: NP | AY75: 0 | AZ75: 0 | BA75: 0 | BB75: 0 | BC75: 0 | BD75: 0 | BE75: 0 | BF75: 0 | BG75: =(AY75+BA75+BC75+BE75) -> 0 | BH75: =(AZ75+BB75+BD75+BF75) -> 0 | BI75: =IF(BF75> 1, IF(BF75 = BG75, "100%", BF75 & "%"), IF(BF75 <= 0.01, "0%", BF75 * 100 & "%")) -> 0% | BJ75: =MIN((BG75 /BG75) * 100, 100) & "%" -> #DIV/0! | BK75: =IF(BG75=0, 0, BH75/BG75) -> 0 | BL75: P | BM75: Meta 74.docx | BN75: 50000000 | BO75: 0 | BP75: 0 | BQ75: 0 | BR75: =+BN75+BP75 -> 50000000 | BS75: =+BO75+BQ75 -> 0 | BT75: =IFERROR(BS75/BR75, "") -> 0 | BU75: 50000000 | BV75: 50000000 | BW75: 0 | BX75: 0 | BY75: =IFERROR(BW75/BV75, "") -> 0 | BZ75: 50000000 | CA75: 51000000 | CB75: 52530000 | CC75: 54105900 | CD75: 207635900
A76: Eje 1. Ambiente, Conectividad y Ordenamiento y servicios públicos | B76: 0.235 | D76: 40 | E76: 4001 | F76: 10 | G76: Es el tiempo de la vivienda y Desarrollo Sostenible para Tenjo (Acceso a soluciones de vivienda) | H76: 1400 | I76: 10.1 | J76: Mejoramiento Habitacional | K76: 10.1.1 | L76: Reducir a 8,97 el déficit cualitativo de vivienda del municipio | M76: Déficit cualitativo de vivienda | N76: 12.5 Fuente: Dane VIHOPE 4258 viviendas con destino habitacional Fuente: Sec. Planeación 2024 | O76: 4001032 | P76: 2024257990010 | Q76: Mejoramiento habitacional y acceso a la vivienda y desarrollo sostenible en el Municipio de Tenjo Cundinamarca | R76: 75 | S76: Beneficiar a 150 familias a través del programa de mejoramientos de viviendas en el casco urbano y rural del municipio de Tenjo | T76: 75 | U76: Número | V76: I | W76: Número de familias beneficiadas | X76: Sec. Infraestructura y Obra Pública | Z76: =SUM(AF76:AI76) -> 150 | AA76: =AS76/Z76 -> 0.0066666667 | AB76: =BI76/Z76 -> 0 | AE76: =SUMPRODUCT(AA76:AD76, {0.15,0.35,0.35,0.15}) -> 0.001 | AF76: 1 | AG76: 49 | AH76: 50 | AI76: 50 | AN76: 0.5 | AO76: 0.5 | AP76: 0.5 | AQ76: 0.5 | AR76: =(AJ76+AL76+AN76+AP76) -> 1 | AS76: =(AK76+AM76+AO76+AQ76) -> 1 | AT76: =AS76/AR76 -> 1 | AU76: =IF(AR76> 1, IF(AR76 = AS76, "100%", AR76 & "%"), IF(AR76 <= 0.01, "0%", AR76 * 100 & "%")) -> 100% | AV76: =IF(AR76=0, 0, AS76/AR76) -> 1 | AW76: P | AX76: META 75.docx | AY76: 0 | AZ76: 0 | BA76: 0 | BB76: 0 | BC76: 0 | BE76: 0 | BG76: =(AY76+BA76+BC76+BE76) -> 0 | BH76: =(AZ76+BB76+BD76+BF76) -> 0 | BI76: =IF(BF76> 1, IF(BF76 = BG76, "100%", BF76 & "%"), IF(BF76 <= 0.01, "0%", BF76 * 100 & "%")) -> 0% | BJ76: =IF(BF78=0, 0, BG78/BF78) -> 0 | BK76: =IF(BG76=0, 0, BH76/BG76) -> 0 | BL76: NP | BM76: Meta 75.docx | BN76: 397500000 | BO76: 44175000 | BP76: 7000000 | BQ76: 7000000 | BR76: =+BN76+BP76 -> 404500000 | BS76: =+BO76+BQ76 -> 51175000 | BT76: =IFERROR(BS76/BR76, "") -> 0.12651422 | BU76: 397500000 | BV76: 44175000 | BW76: 44175000 | BX76: 27652500 | BY76: =IFERROR(BW76/BV76, "") -> 1 | BZ76: 150000000 | CA76: 153000000 | CB76: 160000000 | CC76: 0 | CD76: 463000000
A77: Eje 1. Ambiente, Conectividad y Ordenamiento y servicios públicos | B77: 0.235 | D77: 40 | E77: 4001 | F77: 10 | G77: Es el tiempo de la vivienda y Desarrollo Sostenible para Tenjo (Acceso a soluciones de vivienda) | H77: 1400 | I77: 10.1 | J77: Mejoramiento Habitacional | K77: 10.1.1 | L77: Reducir a 8,97 el déficit cualitativo de vivienda del municipio | M77: Déficit cualitativo de viviedna | N77: 12.5 Fuente: Dane VIHOPE 4258 viviendas con destino habitacional Fuente: Sec. Planeación 2024 | O77: 4001032 | P77: 2024257990010 | Q77: Mejoramiento habitacional y acceso a la vivienda y desarrollo sostenible en el Municipio de Tenjo Cundinamarca | R77: 76 | S77: Implementar un programa de capacitación en mantenimiento y reparaciones domésticas para el 50% de las familias beneficiarias de los programas de mejoramiento de vivienda. | T77: 0 | U77: Porcentaje | V77: I | W77: Número de programas implementados | X77: Sec. de Urbanismo | Z77: =SUM(AF77:AI77) -> 0.5 | AA77: =AS77/Z77 -> 0 | AB77: =BI77/Z77 -> 0 | AE77: =SUMPRODUCT(AA77:AD77, {0.15,0.35,0.35,0.15}) -> 0 | AF77: 0 | AG77: 0 | AH77: 0.35 | AI77: 0.15 | AN77: 0 | AO77: 0 | AP77: 0 | AQ77: 0 | AR77: 0 | AS77: =(AK77+AM77+AO77+AQ77)/2 -> 0 | AT77: =IF(AQ77=0, 0, AR77/AQ77) -> 0 | AU77: =IF(AR77> 1, IF(AR77 = AS77, "100%", AR77 & "%"), IF(AR77 <= 0.01, "0%", AR77 * 100 & "%")) -> 0% | AV77: =IF(AR77=0, 0, AS77/AR77) -> 0 | AW77: NP | AY77: 0 | AZ77: 0 | BA77: 0 | BB77: 0 | BC77: 0 | BD77: 0 | BE77: 0 | BF77: 0 | BG77: =(AY77+BA77+BC77+BE77) -> 0 | BH77: =(AZ77+BB77+BD77+BF77) -> 0 | BI77: =IF(BF77> 1, IF(BF77 = BG77, "100%", BF77 & "%"), IF(BF77 <= 0.01, "0%", BF77 * 100 & "%")) -> 0% | BJ77: =IF(BF79=0, 0, BG79/BF79) -> 0 | BK77: =IF(BG77=0, 0, BH77/BG77) -> 0 | BL77: NP | BM77: Meta 76.docx | BN77: 0 | BO77: 0 | BP77: 0 | BQ77: 0 | BR77: =+BN77+BP77 -> 0 | BS77: =+BO77+BQ77 -> 0 | BT77: =IFERROR(BS77/BR77, "") | BU77: 0 | BV77: 0 | BW77: 0 | BX77: 0 | BY77: =IFERROR(BW77/BV77, "") | BZ77: 50000000 | CA77: 51000000 | CB77: 52530000 | CC77: 54105900 | CD77: 207635900
A78: Eje 1. Ambiente, Conectividad y Ordenamiento y servicios públicos | B78: 0.235 | D78: 40 | E78: 4001 | F78: 10 | G78: Es el tiempo de la vivienda y Desarrollo Sostenible para Tenjo (Acceso a soluciones de vivienda) | H78: 1400 | I78: 10.2 | J78: Financiamiento y Acceso a la Vivienda | K78: 10.2.1 | L78: Ejecutar al 100% las acciones complementarias que faciliten el acceso a la vivienda y la implementación de políticas de sosteniblidad, adaptación al cambio climático y reducción de las huella de carbono | M78: Porcentaje de acciones complemantarias de acceso a vivienda y adaptación al cambio climático ejecutadas | N78: 1 | O78: 4001032 | P78: 2024257990010 | Q78: Mejoramiento habitacional y acceso a la vivienda y desarrollo sostenible en el Municipio de Tenjo Cundinamarca | R78: 77 | S78: Establecer una alianza con entidades financieras, organizaciones sin ánimo de lucro o de carácter privado que facilite el acceso a créditos de vivienda, o que articule este componente favorablemente para mínimo 30 familias del municipio de Tenjo | T78: 0 | U78: Número | V78: I | W78: Número de alianzas establecidas | X78: Sec. Infraestructura y Obra Pública | Z78: =SUM(AF78:AI78) -> 0.91 | AA78: =AS78/Z78 -> 0 | AB78: =BI78/Z78 -> 0.24420024 | AE78: =SUMPRODUCT(AA78:AD78, {0.15,0.35,0.35,0.15}) -> 0.085470085 | AF78: 0 | AG78: 0.9 | AH78: 0.01 | AI78: 0 | AN78: 0 | AO78: 0 | AP78: 0 | AQ78: 0 | AR78: 0 | AS78: =(AK78+AM78+AO78+AQ78)/2 -> 0 | AT78: =IF(AQ78=0, 0, AR78/AQ78) -> 0 | AU78: =IF(AR78> 1, IF(AR78 = AS78, "100%", AR78 & "%"), IF(AR78 <= 0.01, "0%", AR78 * 100 & "%")) -> 0% | AV78: =IF(AR78=0, 0, AS78/AR78) -> 0 | AW78: NP | AY78: 0.1 | AZ78: 0.1 | BA78: 0.1 | BB78: 0.1 | BC78: 0.3 | BD78: 0 | BE78: 0.4 | BG78: =(AY78+BA78+BC78+BE78) -> 0.9 | BH78: =(AZ78+BB78+BD78+BF78) -> 0.2 | BI78: =BH78/BG78 -> 0.22222222 | BJ78: =MIN((BG78 /BG78) * 100, 100) & "%" -> 100% | BK78: =IF(BG78=0, 0, BH78/BG78) -> 0.22222222 | BL78: P | BM78: Meta 77.docx | BN78: 3060000 | BO78: 3060000 | BP78: 0 | BQ78: 0 | BR78: =+BN78+BP78 -> 3060000 | BS78: =+BO78+BQ78 -> 3060000 | BT78: =IFERROR(BS78/BR78, "") -> 1 | BU78: 3060000 | BV78: 3060000 | BW78: 3060000 | BX78: 3060000 | BY78: =IFERROR(BW78/BV78, "") -> 1 | BZ78: 3000000 | CA78: 3060000 | CB78: 3151800 | CC78: 3246354 | CD78: 12458154
A79: Eje 1. Ambiente, Conectividad y Ordenamiento y servicios públicos | B79: 0.235 | D79: 40 | E79: 4001 | F79: 10 | G79: Es el tiempo de la vivienda y Desarrollo Sostenible para Tenjo (Acceso a soluciones de vivienda) | H79: 1400 | I79: 10.2 | J79: Financiamiento y Acceso a la Vivienda | K79: 10.2.1 | L79: Ejecutar al 100% las acciones complementarias que faciliten el acceso a la vivienda y la implementación de políticas de sosteniblidad, adaptación al cambio climático y reducción de las huella de carbono | M79: Porcentaje de acciones complemantarias de acceso a vivienda y adaptación al cambio climático ejecutadas | N79: 1 | O79: 4001032 | P79: 2024257990010 | Q79: Mejoramiento habitacional y acceso a la vivienda y desarrollo sostenible en el Municipio de Tenjo Cundinamarca | R79: 78 | S79: Desarrollar e implementar un plan de acción para la integración de tecnologías verdes y eficiencia energética en el 100% de los proyectos de mejoramiento de vivienda. | T79: 0 | U79: Número | V79: I | W79: Plan de acción desarrollado y establecido | X79: Secretaría de Desarrollo Económico y Medio Ambiente o quien haga sus veces | Z79: =SUM(AF79:AI79) -> 1 | AA79: =AS79/Z79 -> 0 | AB79: =BI79/Z79 -> 0 | AE79: =SUMPRODUCT(AA79:AD79, {0.15,0.35,0.35,0.15}) -> 0 | AF79: 0 | AG79: 0 | AH79: 0.8 | AI79: 0.2 | AN79: 0 | AO79: 0 | AP79: 0 | AQ79: 0 | AR79: 0 | AS79: =(AK79+AM79+AO79+AQ79)/2 -> 0 | AT79: =IF(AQ79=0, 0, AR79/AQ79) -> 0 | AU79: =IF(AR79> 1, IF(AR79 = AS79, "100%", AR79 & "%"), IF(AR79 <= 0.01, "0%", AR79 * 100 & "%")) -> 0% | AV79: =IF(AR79=0, 0, AS79/AR79) -> 0 | AW79: NP | AY79: 0 | AZ79: 0 | BA79: 0 | BC79: 0 | BE79: 0 | BG79: =(AY79+BA79+BC79+BE79) -> 0 | BH79: =(AZ79+BB79+BD79+BF79) -> 0 | BI79: =IF(BF79> 1, IF(BF79 = BG79, "100%", BF79 & "%"), IF(BF79 <= 0.01, "0%", BF79 * 100 & "%")) -> 0% | BJ79: =IF(BF79=0, 0, BG79/BF79) -> 0 | BK79: =IF(BG79=0, 0, BH79/BG79) -> 0 | BL79: NP | BN79: 0 | BO79: 0 | BP79: 0 | BQ79: 0 | BR79: =+BN79+BP79 -> 0 | BS79: =+BO79+BQ79 -> 0 | BT79: =IFERROR(BS79/BR79, "") | BU79: 0 | BV79: 0 | BW79: 0 | BX79: 0 | BY79: =IFERROR(BW79/BV79, "") | BZ79: 5000000 | CA79: 5100000 | CB79: 5253000 | CC79: 5410590 | CD79: 20763590
A80: Eje 2. Seguridad Convivencia y Participación Ciudadana | B80: 0.114 | D80: 45 | E80: 4501 | F80: 11 | G80: Ecosistema Inteligente de seguridad y convivencia (Fortalecimiento de la convivencia y seguridad ciudadana) | H80: 1000 | I80: 11.1 | J80: Seguridad inteligente | K80: 11.1.1 | L80: Incrementar a 60% la Percepción de Seguridad Ciudadana | M80: Percepción de Seguridad Ciudadana | N80: 45% Fuente: Encuesta dePercepción de Ciudadana- Sabana Centro Cómo Vámos 2023 | O80: 4501007 | P80: 2024257990011 | Q80: Fortalecimiento de la convivencia y seguridad ciudadana del municipio de Tenjo Cundinamarca | R80: 79 | S80: Realizar 5 actividades relacionadas con el mejoramiento de la infraestructura tecnológica en seguridad, convivencia ciudadana y orden público | T80: 90 cámaras 1 actividad | U80: Número | V80: M | W80: Número de actividades realizadas | X80: Sec. Gobierno y convivencia ciudadana o quien haga sus veces | Z80: =SUM(AF80:AI80) -> 5 | AA80: =AS80/Z80 -> 0.2 | AB80: =BI80/Z80 -> 0.2 | AE80: =SUMPRODUCT(AA80:AD80, {0.15,0.35,0.35,0.15}) -> 0.1 | AF80: 1 | AG80: 2 | AH80: 2 | AI80: 0 | AN80: 0.4 | AO80: 0.4 | AP80: 0.6 | AQ80: 0.6 | AR80: =(AJ80+AL80+AN80+AP80) -> 1 | AS80: =(AK80+AM80+AO80+AQ80) -> 1 | AT80: =AS80/AR80 -> 1 | AU80: =MIN((AR80 /AR80) * 100, 100) & "%" -> 100% | AV80: =IF(AR80=0, 0, AS80/AR80) -> 1 | AW80: P | AX80: Meta 79.docx | AY80: 1 | AZ80: 1 | BA80: 1 | BB80: 1 | BC80: 1 | BD80: 1 | BE80: 0 | BG80: =(AY80+BA80+BC80+BE80) -> 3 | BH80: =(AZ80+BB80+BD80+BF80) -> 3 | BI80: =BH80/BG80 -> 1 | BJ80: =MIN((BG80 /BG80) * 100, 100) & "%" -> 100% | BK80: =IF(BG80=0, 0, BH80/BG80) -> 1 | BL80: P | BM80: Meta 79.docx | BN80: 1573941260 | BO80: 376704465 | BP80: 691930224 | BQ80: 691930224 | BR80: =+BN80+BP80 -> 2265871484 | BS80: =+BO80+BQ80 -> 1068634689 | BT80: =IFERROR(BS80/BR80, "") -> 0.47162193 | BU80: 1378000000 | BV80: 1573941260 | BW80: 786309322 | BX80: 293465335 | BY80: =IFERROR(BW80/BV80, "") -> 0.49957984 | BZ80: 1400000000 | CA80: 1428000000 | CB80: 1456560000 | CC80: 1500256800 | CD80: 5784816800
A81: Eje 2. Seguridad Convivencia y Participación Ciudadana | B81: 0.114 | D81: 45 | E81: 4501 | F81: 11 | G81: Ecosistema Inteligente de seguridad y convivencia (Fortalecimiento de la convivencia y seguridad ciudadana) | H81: 1000 | I81: 11.1 | J81: Seguridad inteligente | K81: 11.1.1 | L81: Incrementar a 60% la Percepción de Seguridad Ciudadana | M81: Percepción de Seguridad Ciudadana | N81: 45% Fuente: Encuesta dePercepción de Ciudadana- Sabana Centro Cómo Vámos 2023 | O81: 4501026 | P81: 2024257990011 | Q81: Fortalecimiento de la convivencia y seguridad ciudadana del municipio de Tenjo Cundinamarca | R81: 80 | S81: Garantizar el cumplimiento al 100% del Plan Integral de Seguridad y Convivencia Ciudadana (PISCC) buscando el fortalecimiento de acciones de prevención, atención y respuesta en todo el territorio y en entornos educativos | T81: 1 | U81: Porcentaje | V81: M | W81: Porcentaje de cumplimiento garantizado | X81: Sec. Gobierno y convivencia ciudadana o quien haga sus veces | Y81: SI | Z81: =SUM(AF81:AI81)/4 -> 1 | AA81: =AS81/Z81 -> 0.5 | AB81: =BI81/Z81 -> 0.85 | AE81: =SUMPRODUCT(AA81:AD81, {0.15,0.35,0.35,0.15}) -> 0.3725 | AF81: 1 | AG81: 1 | AH81: 1 | AI81: 1 | AN81: 0.4 | AO81: 0.4 | AP81: 0.6 | AQ81: 0.6 | AR81: =(AJ81+AL81+AN81+AP81)/2 -> 0.5 | AS81: =(AK81+AM81+AO81+AQ81)/2 -> 0.5 | AT81: =AS81/AR81 -> 1 | AU81: =MIN((AR81 /AR81) * 100, 100) & "%" -> 100% | AV81: =IF(AR81=0, 0, AS81/AR81) -> 1 | AW81: P | AX81: Meta 80.docx | AY81: 0.15 | AZ81: 0.15 | BA81: 0.3 | BB81: 0.3 | BC81: 0.4 | BD81: 0.4 | BE81: 0.15 | BG81: =(AY81+BA81+BC81+BE81) -> 1 | BH81: =(AZ81+BB81+BD81+BF81) -> 0.85 | BI81: =BH81/BG81 -> 0.85 | BJ81: =MIN((BG81 /BG81) * 100, 100) & "%" -> 100% | BK81: =IF(BG81=0, 0, BH81/BG81) -> 0.85 | BL81: P | BM81: Meta 80.docx | BN81: 2260941593 | BO81: 1276527909 | BP81: 950167957 | BQ81: 950167957 | BR81: =+BN81+BP81 -> 3211109550 | BS81: =+BO81+BQ81 -> 2226695866 | BT81: =IFERROR(BS81/BR81, "") -> 0.69343504 | BU81: 1813453332 | BV81: 2570941593 | BW81: 1696634239 | BX81: 852713608 | BY81: =IFERROR(BW81/BV81, "") -> 0.65992718 | BZ81: 1919575503 | CA81: 2532953211 | CB81: 2501624594 | CC81: 2595591918 | CD81: 9549745226
A82: Eje 2. Seguridad Convivencia y Participación Ciudadana | B82: 0.114 | D82: 45 | E82: 4501 | F82: 11 | G82: Ecosistema Inteligente de seguridad y convivencia (Fortalecimiento de la convivencia y seguridad ciudadana) | H82: 1000 | I82: 11.1 | J82: Seguridad inteligente | K82: 11.1.1 | L82: Incrementar a 60% la Percepción de Seguridad Ciudadana | M82: Percepción de Seguridad Ciudadana | N82: 45% Fuente: Encuesta dePercepción de Ciudadana- Sabana Centro Cómo Vámos 2023 | O82: 4501001 | P82: 2024257990011 | Q82: Fortalecimiento de la convivencia y seguridad ciudadana del municipio de Tenjo Cundinamarca | R82: 81 | S82: Desarrollar 8 capacitaciones a actores clave sobre seguridad y convivencia ciudadana durante el cuatrienio. | T82: 0 | U82: Número | V82: I | W82: Número de capacitaciones desarrolladas | X82: Sec. Gobierno y convivencia ciudadana o quien haga sus veces | Z82: =SUM(AF82:AI82) -> 8 | AA82: =AS82/Z82 -> 0 | AB82: =BI82/Z82 -> 0.1 | AE82: =SUMPRODUCT(AA82:AD82, {0.15,0.35,0.35,0.15}) -> 0.035 | AF82: 0 | AG82: 1 | AH82: 3 | AI82: 4 | AN82: 0 | AO82: 0 | AP82: 0 | AQ82: 0 | AR82: 0 | AS82: =(AK82+AM82+AO82+AQ82)/2 -> 0 | AT82: =IF(AQ82=0, 0, AR82/AQ82) -> 0 | AU82: =IF(AR82> 1, IF(AR82 = AS82, "100%", AR82 & "%"), IF(AR82 <= 0.01, "0%", AR82 * 100 & "%")) -> 0% | AV82: =IF(AR82=0, 0, AS82/AR82) -> 0 | AW82: NP | AX82: Meta 81.docx | AY82: 0 | AZ82: 0 | BA82: 0 | BB82: 0 | BC82: 0.8 | BD82: 0.8 | BE82: 0.2 | BG82: =(AY82+BA82+BC82+BE82) -> 1 | BH82: =(AZ82+BB82+BD82+BF82) -> 0.8 | BI82: =BH82/BG82 -> 0.8 | BJ82: =MIN((BG82 /BG82) * 100, 100) & "%" -> 100% | BK82: =IF(BG82=0, 0, BH82/BG82) -> 0.8 | BL82: P | BM82: Meta 81.docx | BN82: 23026500 | BO82: 0 | BP82: 0 | BQ82: 0 | BR82: =+BN82+BP82 -> 23026500 | BS82: =+BO82+BQ82 -> 0 | BT82: =IFERROR(BS82/BR82, "") -> 0 | BU82: 23026500 | BV82: 23026500 | BW82: 0 | BX82: 0 | BY82: =IFERROR(BW82/BV82, "") -> 0 | BZ82: 0 | CA82: 50000000 | CB82: 51000000 | CC82: 52530000 | CD82: 153530000
A83: Eje 2. Seguridad Convivencia y Participación Ciudadana | B83: 0.114 | D83: 45 | E83: 4501 | F83: 11 | G83: Ecosistema Inteligente de seguridad y convivencia (Fortalecimiento de la convivencia y seguridad ciudadana) | H83: 1000 | I83: 11.1 | J83: Seguridad inteligente | K83: 11.1.1 | L83: Incrementar a 60% la Percepción de Seguridad Ciudadana | M83: Percepción de Seguridad Ciudadana | N83: 45% Fuente: Encuesta dePercepción de Ciudadana- Sabana Centro Cómo Vámos 2023 | O83: 4501032 | P83: 2024257990011 | Q83: Fortalecimiento de la convivencia y seguridad ciudadana del municipio de Tenjo Cundinamarca | R83: 82 | S83: Implementar la estrategia de mantenimiento y robustecimiento del pie de fuerza - Ejército Nacional y Policía Nacional - y seguridad privada con motorizados para el mejoramiento de las condiciones de seguridad ciudadana y orden público en el municipio. | T83: 1 | U83: Número | V83: M | W83: Porcentaje de estrategia implementada | X83: Sec. Gobierno y convivencia ciudadana o quien haga sus veces | Z83: =SUM(AF83:AI83)/4 -> 1 | AA83: =AS83/Z83 -> 1 | AB83: =BI83/Z83 -> 0.8 | AE83: =SUMPRODUCT(AA83:AD83, {0.15,0.35,0.35,0.15}) -> 0.43 | AF83: 1 | AG83: 1 | AH83: 1 | AI83: 1 | AN83: 0.7 | AO83: 0.7 | AP83: 0.3 | AQ83: 0.3 | AR83: =(AJ83+AL83+AN83+AP83) -> 1 | AS83: =(AK83+AM83+AO83+AQ83) -> 1 | AT83: =AS83/AR83 -> 1 | AU83: =MIN((AR83 /AR83) * 100, 100) & "%" -> 100% | AV83: =IF(AR83=0, 0, AS83/AR83) -> 1 | AW83: P | AX83: Meta 82.docx | AY83: 0 | AZ83: 0 | BA83: 0.3 | BB83: 0.3 | BC83: 0.5 | BD83: 0.5 | BE83: 0.2 | BG83: =(AY83+BA83+BC83+BE83) -> 1 | BH83: =(AZ83+BB83+BD83+BF83) -> 0.8 | BI83: =BH83/BG83 -> 0.8 | BJ83: =MIN((BG83 /BG83) * 100, 100) & "%" -> 100% | BK83: =IF(BG83=0, 0, BH83/BG83) -> 0.8 | BL83: P | BM83: Meta 82.docx | BN83: 1350000000 | BO83: 0 | BP83: 0 | BQ83: 0 | BR83: =+BN83+BP83 -> 1350000000 | BS83: =+BO83+BQ83 -> 0 | BT83: =IFERROR(BS83/BR83, "") -> 0 | BU83: 1200000000 | BV83: 1040000000 | BW83: 1038820607 | BX83: 592933967 | BY83: =IFERROR(BW83/BV83, "") -> 0.99886597 | BZ83: 1300000000 | CA83: 1800000000 | CB83: 1836000000 | CC83: 1891080000 | CD83: 6827080000
A84: Eje 2. Seguridad Convivencia y Participación Ciudadana | B84: 0.114 | D84: 45 | E84: 4501 | F84: 11 | G84: Ecosistema Inteligente de seguridad y convivencia (Fortalecimiento de la convivencia y seguridad ciudadana) | H84: 1000 | I84: 11.1 | J84: Seguridad inteligente | K84: 11.1.1 | L84: Incrementar a 60% la Percepción de Seguridad Ciudadana | M84: Percepción de Seguridad Ciudadana | N84: 45% Fuente: Encuesta dePercepción de Ciudadana- Sabana Centro Cómo Vámos 2023 | O84: 4501032 | P84: 2024257990011 | Q84: Fortalecimiento de la convivencia y seguridad ciudadana del municipio de Tenjo Cundinamarca | R84: 83 | S84: Garantizar al 100% el funcionamiento y mejoramiento de la atención integral de la Inspección de Policía junto con sus acciones de control urbanístico en el municipio | T84: 1 | U84: Porcentaje | V84: M | W84: Porcentaje de funcionamiento garantizado | X84: Sec. Gobierno y convivencia ciudadana o quien haga sus veces | Z84: =SUM(AF84:AI84)/4 -> 1 | AA84: =AS84/Z84 -> 0.5 | AB84: =BI84/Z84 -> 0.85 | AE84: =SUMPRODUCT(AA84:AD84, {0.15,0.35,0.35,0.15}) -> 0.3725 | AF84: 1 | AG84: 1 | AH84: 1 | AI84: 1 | AN84: 0.7 | AO84: 0.7 | AP84: 0.3 | AQ84: 0.3 | AR84: =(AJ84+AL84+AN84+AP84)/2 -> 0.5 | AS84: =(AK84+AM84+AO84+AQ84)/2 -> 0.5 | AT84: =AS84/AR84 -> 1 | AU84: =MIN((AR84 /AR84) * 100, 100) & "%" -> 100% | AV84: =IF(AR84=0, 0, AS84/AR84) -> 1 | AW84: P | AX84: Meta 83.docx | AY84: 0.15 | AZ84: 0.15 | BA84: 0.3 | BB84: 0.3 | BC84: 0.4 | BD84: 0.4 | BE84: 0.15 | BG84: =(AY84+BA84+BC84+BE84) -> 1 | BH84: =(AZ84+BB84+BD84+BF84) -> 0.85 | BI84: =BH84/BG84 -> 0.85 | BJ84: =MIN((BG84 /BG84) * 100, 100) & "%" -> 100% | BK84: =IF(BG84=0, 0, BH84/BG84) -> 0.85 | BL84: P | BM84: Meta 83.docx | BN84: 341943969 | BO84: 172749571 | BP84: 158074590 | BQ84: 158074590 | BR84: =+BN84+BP84 -> 500018559 | BS84: =+BO84+BQ84 -> 330824161 | BT84: =IFERROR(BS84/BR84, "") -> 0.66162376 | BU84: 341943969 | BV84: 341943969 | BW84: 262999700 | BX84: 212823962 | BY84: =IFERROR(BW84/BV84, "") -> 0.76913098 | BZ84: 300000000 | CA84: 306000000 | CB84: 312120000 | CC84: 321483600 | CD84: 1239603600
A85: Eje 2. Seguridad Convivencia y Participación Ciudadana | B85: 0.114 | D85: 45 | E85: 4501 | F85: 11 | G85: Ecosistema Inteligente de seguridad y convivencia (Fortalecimiento de la convivencia y seguridad ciudadana) | H85: 1000 | I85: 11.1 | J85: Seguridad inteligente | K85: 11.1.1 | L85: Incrementar a 60% la Percepción de Seguridad Ciudadana | M85: Percepción de Seguridad Ciudadana | N85: 45% Fuente: Encuesta dePercepción de Ciudadana- Sabana Centro Cómo Vámos 2023 | O85: 4501056 | P85: 2024257990011 | Q85: Fortalecimiento de la convivencia y seguridad ciudadana del municipio de Tenjo Cundinamarca | R85: 84 | S85: Establecer un mecanismo colaboración ciudadana mediante la implementación de recompensas, fortaleciendo a seguridad, la cofianza de la comunidad y la disuasión y reducción de hechos delictivos | T85: 1 | U85: Número | V85: I | W85: Mecanismo de colaboración ciudadana establecido | X85: Sec. Gobierno y convivencia ciudadana o quien haga sus veces | Z85: =SUM(AF85:AI85)/4 -> 1 | AA85: =AS85/Z85 -> 1 | AB85: =BI85/Z85 -> 0.8 | AE85: =SUMPRODUCT(AA85:AD85, {0.15,0.35,0.35,0.15}) -> 0.43 | AF85: 1 | AG85: 1 | AH85: 1 | AI85: 1 | AN85: 0.5 | AO85: 0.5 | AP85: 0.5 | AQ85: 0.5 | AR85: =(AJ85+AL85+AN85+AP85) -> 1 | AS85: =(AK85+AM85+AO85+AQ85) -> 1 | AT85: =AS85/AR85 -> 1 | AU85: =MIN((AR85 /AR85) * 100, 100) & "%" -> 100% | AV85: =IF(AR85=0, 0, AS85/AR85) -> 1 | AW85: P | AX85: Meta 84.docx | AY85: 0.4 | AZ85: 0.4 | BA85: 0.2 | BB85: 0.2 | BC85: 0.2 | BD85: 0.2 | BE85: 0.2 | BG85: =(AY85+BA85+BC85+BE85) -> 1 | BH85: =(AZ85+BB85+BD85+BF85) -> 0.8 | BI85: =BH85/BG85 -> 0.8 | BJ85: =MIN((BG85 /BG85) * 100, 100) & "%" -> 100% | BK85: =IF(BG85=0, 0, BH85/BG85) -> 0.8 | BL85: P | BM85: Meta 84.docx | BN85: 40000000 | BO85: 0 | BP85: 0 | BQ85: 0 | BR85: =+BN85+BP85 -> 40000000 | BS85: =+BO85+BQ85 -> 0 | BT85: =IFERROR(BS85/BR85, "") -> 0 | BU85: 40000000 | BV85: 40000000 | BW85: 27000000 | BX85: 27000000 | BY85: =IFERROR(BW85/BV85, "") -> 0.675 | BZ85: 50000000 | CA85: 50000000 | CB85: 50000000 | CC85: 50000000 | CD85: 200000000
A86: Eje 2. Seguridad Convivencia y Participación Ciudadana | B86: 0.114 | D86: 45 | E86: 4501 | F86: 11 | G86: Ecosistema Inteligente de seguridad y convivencia (Fortalecimiento de la convivencia y seguridad ciudadana) | H86: 1000 | I86: 11.1 | J86: Seguridad inteligente | K86: 11.1.1 | L86: Incrementar a 60% la Percepción de Seguridad Ciudadana | M86: Percepción de Seguridad Ciudadana | N86: 45% Fuente: Encuesta dePercepción de Ciudadana- Sabana Centro Cómo Vámos 2023 | O86: 4501032 | P86: 2024257990011 | Q86: Fortalecimiento de la convivencia y seguridad ciudadana del municipio de Tenjo Cundinamarca | R86: 85 | S86: Garantizar el funcionamiento y mejoramiento al 100% de la atención integral de la Comisaría de Familia y sus servcios de atención integral en el municipio durante el cuatrienio (Ley 2126 del 2021) | T86: 1 | U86: Porcentaje | V86: M | W86: Porcentaje de funcionamiento y mejoramiento garantizado | X86: Sec. Gobierno y convivencia ciudadana o quien haga sus veces | Y86: SI | Z86: =SUM(AF86:AI86)/4 -> 1 | AA86: =AS86/Z86 -> 0.5 | AB86: =BI86/Z86 -> 0.85 | AE86: =SUMPRODUCT(AA86:AD86, {0.15,0.35,0.35,0.15}) -> 0.3725 | AF86: 1 | AG86: 1 | AH86: 1 | AI86: 1 | AN86: 0.7 | AO86: 0.7 | AP86: 0.3 | AQ86: 0.3 | AR86: =(AJ86+AL86+AN86+AP86)/2 -> 0.5 | AS86: =(AK86+AM86+AO86+AQ86)/2 -> 0.5 | AT86: =AS86/AR86 -> 1 | AU86: =MIN((AR86 /AR86) * 100, 100) & "%" -> 100% | AV86: =IF(AR86=0, 0, AS86/AR86) -> 1 | AW86: P | AX86: Meta 85.docx | AY86: 0.15 | AZ86: 0.15 | BA86: 0.3 | BB86: 0.3 | BC86: 0.4 | BD86: 0.4 | BE86: 0.15 | BG86: =(AY86+BA86+BC86+BE86) -> 1 | BH86: =(AZ86+BB86+BD86+BF86) -> 0.85 | BI86: =BH86/BG86 -> 0.85 | BJ86: =MIN((BG86 /BG86) * 100, 100) & "%" -> 100% | BK86: =IF(BG86=0, 0, BH86/BG86) -> 0.85 | BL86: P | BM86: Meta 85.docx | BN86: 1380400792 | BO86: 511749856 | BP86: 515865579 | BQ86: 515865579 | BR86: =+BN86+BP86 -> 1896266371 | BS86: =+BO86+BQ86 -> 1027615435 | BT86: =IFERROR(BS86/BR86, "") -> 0.54191513 | BU86: 1324400792 | BV86: 1380400792 | BW86: 1014661251 | BX86: 809463331 | BY86: =IFERROR(BW86/BV86, "") -> 0.7350483 | BZ86: 988763011 | CA86: 1008538271 | CB86: 1028709037 | CC86: 1059570308 | CD86: 4085580627
A87: Eje 2. Seguridad Convivencia y Participación Ciudadana | B87: 0.114 | D87: 45 | E87: 4501 | F87: 11 | G87: Ecosistema Inteligente de seguridad y convivencia (Fortalecimiento de la convivencia y seguridad ciudadana) | H87: 1000 | I87: 11.1 | J87: Seguridad inteligente | K87: 11.1.1 | L87: Incrementar a 60% la Percepción de Seguridad Ciudadana | M87: Percepción de Seguridad Ciudadana | N87: 45% Fuente: Encuesta dePercepción de Ciudadana- Sabana Centro Cómo Vámos 2023 | O87: 4501048 | P87: 2024257990011 | Q87: Fortalecimiento de la convivencia y seguridad ciudadana del municipio de Tenjo Cundinamarca | R87: 86 | S87: Garantizar al 100% de las personas privadas de la libertad en el municipio de Tenjo sus derechos | T87: 1 | U87: Porcentaje | V87: M | W87: Porcentaje de personas privadas de las libertades con garantía de derechos | X87: Sec. Gobierno y convivencia ciudadana o quien haga sus veces | Z87: =SUM(AF87:AI87)/4 -> 1 | AA87: =AS87/Z87 -> 0.5 | AB87: =BI87/Z87 -> 0.85 | AE87: =SUMPRODUCT(AA87:AD87, {0.15,0.35,0.35,0.15}) -> 0.3725 | AF87: 1 | AG87: 1 | AH87: 1 | AI87: 1 | AN87: 0.7 | AO87: 0.7 | AP87: 0.3 | AQ87: 0.3 | AR87: =(AJ87+AL87+AN87+AP87)/2 -> 0.5 | AS87: =(AK87+AM87+AO87+AQ87)/2 -> 0.5 | AT87: =AS87/AR87 -> 1 | AU87: =MIN((AR87 /AR87) * 100, 100) & "%" -> 100% | AV87: =IF(AR87=0, 0, AS87/AR87) -> 1 | AW87: P | AX87: Meta 86.docx | AY87: 0.15 | AZ87: 0.15 | BA87: 0.3 | BB87: 0.3 | BC87: 0.4 | BD87: 0.4 | BE87: 0.15 | BG87: =(AY87+BA87+BC87+BE87) -> 1 | BH87: =(AZ87+BB87+BD87+BF87) -> 0.85 | BI87: =BH87/BG87 -> 0.85 | BJ87: =MIN((BG87 /BG87) * 100, 100) & "%" -> 100% | BK87: =IF(BG87=0, 0, BH87/BG87) -> 0.85 | BL87: P | BM87: Meta 86.docx | BN87: 150000000 | BO87: 0 | BP87: 23999983 | BQ87: 23999983 | BR87: =+BN87+BP87 -> 173999983 | BS87: =+BO87+BQ87 -> 23999983 | BT87: =IFERROR(BS87/BR87, "") -> 0.13793095 | BU87: 90000000 | BV87: 150000000 | BW87: 17047850 | BX87: 17047850 | BY87: =IFERROR(BW87/BV87, "") -> 0.11365233 | BZ87: 240000000 | CA87: 244800000 | CB87: 249696000 | CC87: 257186880 | CD87: 991682880
A88: Eje 2. Seguridad Convivencia y Participación Ciudadana | B88: 0.114 | D88: 45 | E88: 4501 | F88: 11 | G88: Ecosistema Inteligente de seguridad y convivencia (Fortalecimiento de la convivencia y seguridad ciudadana) | H88: 1000 | I88: 11.1 | J88: Seguridad inteligente | K88: 11.1.1 | L88: Incrementar a 60% la Percepción de Seguridad Ciudadana | M88: Percepción de Seguridad Ciudadana | N88: 45% Fuente: Encuesta dePercepción de Ciudadana- Sabana Centro Cómo Vámos 2023 | O88: 4501025 | P88: 2024257990011 | Q88: Fortalecimiento de la convivencia y seguridad ciudadana del municipio de Tenjo Cundinamarca | R88: 87 | S88: Poner en funcionamiento el Centro de Traslado por Protección dando cumplimiento a la Ley 1801 del 2016 durante el cuatrienio | T88: 1 | U88: Número | V88: M | W88: Centro de Traslado por protección en funcionamiento | X88: Sec. Gobierno y convivencia ciudadana o quien haga sus veces | Y88: SI | Z88: =SUM(AF88:AI88)/4 -> 1 | AA88: =AS88/Z88 -> 0.6 | AB88: =BI88/Z88 -> 0.8 | AE88: =SUMPRODUCT(AA88:AD88, {0.15,0.35,0.35,0.15}) -> 0.37 | AF88: 1 | AG88: 1 | AH88: 1 | AI88: 1 | AN88: 0.5 | AO88: 0.5 | AP88: 0.5 | AQ88: 0.1 | AR88: =(AJ88+AL88+AN88+AP88) -> 1 | AS88: =(AK88+AM88+AO88+AQ88) -> 0.6 | AT88: =AS88/AR88 -> 0.6 | AU88: =MIN((AR88 /AR88) * 100, 100) & "%" -> 100% | AV88: =IF(AR88=0, 0, AS88/AR88) -> 0.6 | AW88: P | AX88: Meta 87.docx | AY88: 0.1 | AZ88: 0.1 | BA88: 0.3 | BB88: 0.3 | BC88: 0.4 | BD88: 0.4 | BE88: 0.2 | BG88: =(AY88+BA88+BC88+BE88) -> 1 | BH88: =(AZ88+BB88+BD88+BF88) -> 0.8 | BI88: =BH88/BG88 -> 0.8 | BJ88: =MIN((BG88 /BG88) * 100, 100) & "%" -> 100% | BK88: =IF(BG88=0, 0, BH88/BG88) -> 0.8 | BL88: P | BM88: Meta 87.docx | BN88: 169000000 | BO88: 0 | BP88: 0 | BQ88: 0 | BR88: =+BN88+BP88 -> 169000000 | BS88: =+BO88+BQ88 -> 0 | BT88: =IFERROR(BS88/BR88, "") -> 0 | BU88: 135000000 | BV88: 169000000 | BW88: 0 | BX88: 0 | BY88: =IFERROR(BW88/BV88, "") -> 0 | BZ88: 100000000 | CA88: 102000000 | CB88: 104040000 | CC88: 107161200 | CD88: 413201200
A89: Eje 2. Seguridad Convivencia y Participación Ciudadana | B89: 0.114 | D89: 45 | E89: 4502 | F89: 12 | G89: Es el tiempo de la acción y partcipación comunitaria (Fortalecimiento del buen gobierno para el respeto y la garantía de los DDHH) | H89: 1000 | I89: 12.1 | J89: Es el tiempo de la infraestructura comunitaria | K89: 12.1.1 | L89: Ejecutar al 100% las acciones establecidas frente al mantenimiento, construcción y adecuación de la infraestructura comunitaria | M89: Porcentaje de acciones ejecutadas | N89: 0.73 | O89: 4502002 | P89: 2024257990012 | Q89: Fortalecimiento a la infraestructura, a la accion y participacion comunitaria en el municipio de Tenjo | R89: 88 | S89: Realizar la construcción, adecuación y/o rehabilitación de 2 aulas comunitarias | T89: 2 | U89: Número | V89: I | W89: Número de salones multifuncionales construidos | X89: Sec. Infraestructura y Obra Pública | Z89: =SUM(AF89:AI89) -> 2 | AA89: =AS89/Z89 -> 0.04985 | AB89: =BI89/Z89 -> 0 | AE89: =SUMPRODUCT(AA89:AD89, {0.15,0.35,0.35,0.15}) -> 0.0074775 | AF89: 0.1 | AG89: 0 | AH89: 0.9 | AI89: 1 | AN89: 0.04985 | AO89: 0.04985 | AP89: 0.04985 | AQ89: 0.04985 | AR89: =(AJ89+AL89+AN89+AP89) -> 0.0997 | AS89: =(AK89+AM89+AO89+AQ89) -> 0.0997 | AT89: =AS89/AR89 -> 1 | AU89: =MIN((AR89 /AR89) * 100, 100) & "%" -> 100% | AV89: =IF(AR89=0, 0, AS89/AR89) -> 1 | AW89: P | AX89: META 88.docx | AY89: 0 | BA89: 0 | BC89: 0 | BE89: 0 | BG89: =(AY89+BA89+BC89+BE89) -> 0 | BH89: =(AZ89+BB89+BD89+BF89) -> 0 | BI89: =IF(BF89> 1, IF(BF89 = BG89, "100%", BF89 & "%"), IF(BF89 <= 0.01, "0%", BF89 * 100 & "%")) -> 0% | BJ89: =IF(BF89=0, 0, BG89/BF89) -> 0 | BK89: =IF(BG89=0, 0, BH89/BG89) -> 0 | BL89: NP | BM89: Meta 88.docx | BN89: 0 | BO89: 0 | BP89: 15000000 | BQ89: 15000000 | BR89: =+BN89+BP89 -> 15000000 | BS89: =+BO89+BQ89 -> 15000000 | BT89: =IFERROR(BS89/BR89, "") -> 1 | BU89: 0 | BV89: 0 | BW89: 0 | BX89: 0 | BY89: =IFERROR(BW89/BV89, "") | BZ89: 0 | CA89: 0 | CB89: 700000000 | CC89: 750000000 | CD89: 1450000000
A90: Eje 2. Seguridad Convivencia y Participación Ciudadana | B90: 0.114 | D90: 45 | E90: 4502 | F90: 12 | G90: Es el tiempo de la acción y partcipación comunitaria (Fortalecimiento del buen gobierno para el respeto y la garantía de los DDHH) | H90: 1000 | I90: 12.1 | J90: Es el tiempo de la infraestructura comunitaria | K90: 12.1.1 | L90: Ejecutar al 100% las acciones establecidas frente al mantenimiento, construcción y adecuación de la infraestructura comunitaria | M90: Porcentaje de acciones ejecutadas | N90: 0.73 | O90: 4502001 | P90: 2024257990012 | Q90: Fortalecimiento a la infraestructura, a la accion y participacion comunitaria en el municipio de Tenjo | R90: 89 | S90: Mantener físicamente el 100% de los salones multifuncionales e infraestructura comunitaria del municipio en el cuatrienio | T90: 0.75 | U90: Porcentaje | V90: I | W90: Porcentaje de salones multifuncionales intervenidos | X90: Sec. Infraestructura y Obra Pública | Z90: =SUM(AF90:AI90)/3 -> 1 | AA90: =AS90/Z90 -> 0 | AB90: =BI90/Z90 -> 0.35 | AE90: =SUMPRODUCT(AA90:AD90, {0.15,0.35,0.35,0.15}) -> 0.1225 | AF90: 0 | AG90: 1 | AH90: 1 | AI90: 1 | AN90: 0 | AO90: 0 | AP90: 0 | AQ90: 0 | AR90: 0 | AS90: =(AK90+AM90+AO90+AQ90)/2 -> 0 | AT90: =IF(AQ90=0, 0, AR90/AQ90) -> 0 | AU90: =IF(AR90> 1, IF(AR90 = AS90, "100%", AR90 & "%"), IF(AR90 <= 0.01, "0%", AR90 * 100 & "%")) -> 0% | AV90: =IF(AR90=0, 0, AS90/AR90) -> 0 | AW90: NP | AY90: 0.15 | AZ90: 0.15 | BA90: 0.3 | BB90: 0.2 | BC90: 0.3 | BD90: 0 | BE90: 0.25 | BG90: =(AY90+BA90+BC90+BE90) -> 1 | BH90: =(AZ90+BB90+BD90+BF90) -> 0.35 | BI90: =BH90/BG90 -> 0.35 | BJ90: =MIN((BG90 /BG90) * 100, 100) & "%" -> 100% | BK90: =IF(BG90=0, 0, BH90/BG90) -> 0.35 | BL90: P | BM90: Meta 89.docx | BN90: 50000000 | BO90: 47750000 | BP90: 0 | BQ90: 0 | BR90: =+BN90+BP90 -> 50000000 | BS90: =+BO90+BQ90 -> 47750000 | BT90: =IFERROR(BS90/BR90, "") -> 0.955 | BU90: 50000000 | BV90: 50000000 | BW90: 47750000 | BX90: 21937500 | BY90: =IFERROR(BW90/BV90, "") -> 0.955 | BZ90: 0 | CA90: 300000000 | CB90: 750000000 | CC90: 500000000 | CD90: 1550000000
A91: Eje 2. Seguridad Convivencia y Participación Ciudadana | B91: 0.114 | D91: 45 | E91: 4502 | F91: 12 | G91: Es el tiempo de la acción y partcipación comunitaria (Fortalecimiento del buen gobierno para el respeto y la garantía de los DDHH) | H91: 1000 | I91: 12.1 | J91: Es el tiempo de la infraestructura comunitaria | K91: 12.1.1 | L91: Ejecutar al 100% las acciones establecidas frente al mantenimiento, construcción y adecuación de la infraestructura comunitaria | M91: Porcentaje de acciones ejecutadas | N91: 0.73 | O91: 4502001 | P91: 2024257990012 | Q91: Fortalecimiento a la infraestructura, a la accion y participacion comunitaria en el municipio de Tenjo | R91: 90 | S91: Ejecutar una estrategia de mantenimiento de ornato público, limpieza de suminideros, cunetas y vallados | T91: 0 | U91: Número | V91: I | W91: Número de estrategias ejecutadas | X91: Sec. Infraestructura y Obra Pública | Z91: =SUM(AF91:AI91)/4 -> 1 | AA91: =AS91/Z91 -> 1 | AB91: =BI91/Z91 -> 0.8 | AE91: =SUMPRODUCT(AA91:AD91, {0.15,0.35,0.35,0.15}) -> 0.43 | AF91: 1 | AG91: 1 | AH91: 1 | AI91: 1 | AN91: 0.5 | AO91: 0.5 | AP91: 0.5 | AQ91: 0.5 | AR91: =(AJ91+AL91+AN91+AP91) -> 1 | AS91: =(AK91+AM91+AO91+AQ91) -> 1 | AT91: =AS91/AR91 -> 1 | AU91: =MIN((AR91 /AR91) * 100, 100) & "%" -> 100% | AV91: =IF(AR91=0, 0, AS91/AR91) -> 1 | AW91: P | AX91: META 90.docx | AY91: 0.3 | AZ91: 0.3 | BA91: 0.3 | BB91: 0.3 | BC91: 0.2 | BD91: 0.2 | BE91: 0.2 | BG91: =(AY91+BA91+BC91+BE91) -> 1 | BH91: =(AZ91+BB91+BD91+BF91) -> 0.8 | BI91: =BH91/BG91 -> 0.8 | BJ91: =MIN((BG91 /BG91) * 100, 100) & "%" -> 100% | BK91: =IF(BG91=0, 0, BH91/BG91) -> 0.8 | BL91: P | BM91: Meta 90.docx | BN91: 700000000 | BO91: 199895695 | BP91: 179999328 | BQ91: 179999328 | BR91: =+BN91+BP91 -> 879999328 | BS91: =+BO91+BQ91 -> 379895023 | BT91: =IFERROR(BS91/BR91, "") -> 0.43169922 | BU91: 200000000 | BV91: 700000000 | BW91: 699773248 | BX91: 199895695 | BY91: =IFERROR(BW91/BV91, "") -> 0.99967607 | BZ91: 200000000 | CA91: 204000000 | CB91: 208080000 | CC91: 214322400 | CD91: 826402400
A92: Eje 2. Seguridad Convivencia y Participación Ciudadana | B92: 0.114 | D92: 45 | E92: 4502 | F92: 12 | G92: Es el tiempo de la acción y partcipación comunitaria (Fortalecimiento del buen gobierno para el respeto y la garantía de los DDHH) | H92: 1000 | I92: 13.1 | J92: Participación comunitaria con acciones y resultados | K92: 13.1.1 | L92: Incrementar al 90% de la capacidad organizativa y participativa de las Juntas de Acción Comunal en el municipio mediante la ejecución de las acciones establecidas en Participación Comunitaria | M92: Porcentaje de capacidad organizativa y participativa de JAC incrementada | N92: 0.7 | O92: 4502001 | P92: 2024257990012 | Q92: Fortalecimiento a la infraestructura, a la accion y participacion comunitaria en el municipio de Tenjo | R92: 91 | S92: Realizar la suscripción de 20 convenios solidarios con las JAC que cuenten con su documentación actualizada | T92: 9 | U92: Número | V92: I | W92: Suscripción de convenios solidarios realizados | X92: Sec. Gobierno y convivencia ciudadana o quien haga sus veces | Z92: =SUM(AF92:AI92) -> 20 | AA92: =AS92/Z92 -> 0 | AB92: =BI92/Z92 -> 0.041666667 | AE92: =SUMPRODUCT(AA92:AD92, {0.15,0.35,0.35,0.15}) -> 0.014583333 | AF92: 0 | AG92: 6 | AH92: 10 | AI92: 4 | AN92: 0 | AO92: 0 | AP92: 0 | AQ92: 0 | AR92: 0 | AS92: =(AK92+AM92+AO92+AQ92)/2 -> 0 | AT92: =IF(AQ92=0, 0, AR92/AQ92) -> 0 | AU92: =IF(AR92> 1, IF(AR92 = AS92, "100%", AR92 & "%"), IF(AR92 <= 0.01, "0%", AR92 * 100 & "%")) -> 0% | AV92: =IF(AR92=0, 0, AS92/AR92) -> 0 | AW92: NP | AX92: Meta 91.docx | AY92: 0 | AZ92: 0 | BA92: 0 | BB92: 0 | BC92: 5 | BD92: 5 | BE92: 1 | BG92: =(AY92+BA92+BC92+BE92) -> 6 | BH92: =(AZ92+BB92+BD92+BF92) -> 5 | BI92: =BH92/BG92 -> 0.83333333 | BJ92: =MIN((BG92 /BG92) * 100, 100) & "%" -> 100% | BK92: =IF(BG92=0, 0, BH92/BG92) -> 0.83333333 | BL92: P | BM92: Meta 91.docx | BN92: 120000000 | BO92: 0 | BP92: 0 | BQ92: 0 | BR92: =+BN92+BP92 -> 120000000 | BS92: =+BO92+BQ92 -> 0 | BT92: =IFERROR(BS92/BR92, "") -> 0 | BU92: 120000000 | BV92: 160000000 | BW92: 0 | BX92: 0 | BY92: =IFERROR(BW92/BV92, "") -> 0 | BZ92: 125000000 | CA92: 176500000 | CB92: 203030000 | CC92: 210370900 | CD92: 714900900
A93: Eje 2. Seguridad Convivencia y Participación Ciudadana | B93: 0.114 | D93: 45 | E93: 4502 | F93: 12 | G93: Es el tiempo de la acción y partcipación comunitaria (Fortalecimiento del buen gobierno para el respeto y la garantía de los DDHH) | H93: 1000 | I93: 13.1 | J93: Participación comunitaria con acciones y resultados | K93: 13.1.1 | L93: Incrementar al 90% de la capacidad organizativa y participativa de las Juntas de Acción Comunal en el municipio mediante la ejecución de las acciones establecidas en Participación Comunitaria | M93: Porcentaje de capacidad organizativa y participativa de JAC incrementada | N93: 0.7 | O93: 4502001 | P93: 2024257990012 | Q93: Fortalecimiento a la infraestructura, a la accion y participacion comunitaria en el municipio de Tenjo | R93: 92 | S93: Reglamentar e implementar el presupuesto participativo en el municipio | T93: 0 | U93: Número | V93: I | W93: Presupuesto participativo reglamentado e implementado | X93: Sec. Gobierno y convivencia ciudadana o quien haga sus veces | Z93: =SUM(AF93:AI93) -> 1 | AA93: =AS93/Z93 -> 0 | AB93: =BI93/Z93 -> 0.85 | AE93: =SUMPRODUCT(AA93:AD93, {0.15,0.35,0.35,0.15}) -> 0.2975 | AF93: 0 | AG93: 0.5 | AH93: 0.5 | AI93: 0 | AN93: 0 | AO93: 0 | AP93: 0 | AQ93: 0 | AR93: 0 | AS93: =(AK93+AM93+AO93+AQ93)/2 -> 0 | AT93: =IF(AQ93=0, 0, AR93/AQ93) -> 0 | AU93: =IF(AR93> 1, IF(AR93 = AS93, "100%", AR93 & "%"), IF(AR93 <= 0.01, "0%", AR93 * 100 & "%")) -> 0% | AV93: =IF(AR93=0, 0, AS93/AR93) -> 0 | AW93: NP | AX93: Meta 92.docx | AY93: 15 | AZ93: 15 | BA93: 30 | BB93: 30 | BC93: 40 | BD93: 40 | BE93: 15 | BG93: =(AY93+BA93+BC93+BE93) -> 100 | BH93: =(AZ93+BB93+BD93+BF93) -> 85 | BI93: =BH93/BG93 -> 0.85 | BJ93: =MIN((BG93 /BG93) * 100, 100) & "%" -> 100% | BK93: =IF(BG93=0, 0, BH93/BG93) -> 0.85 | BL93: P | BM93: Meta 92.docx | BN93: 25000000 | BO93: 17700000 | BP93: 0 | BQ93: 0 | BR93: =+BN93+BP93 -> 25000000 | BS93: =+BO93+BQ93 -> 17700000 | BT93: =IFERROR(BS93/BR93, "") -> 0.708 | BU93: 25000000 | BV93: 17700000 | BW93: 17700000 | BX93: 17700000 | BY93: =IFERROR(BW93/BV93, "") -> 1 | BZ93: 0 | CA93: 0 | CB93: 50000000 | CC93: 50000000 | CD93: 100000000
A94: Eje 2. Seguridad Convivencia y Participación Ciudadana | B94: 0.114 | D94: 45 | E94: 4502 | F94: 12 | G94: Es el tiempo de la acción y partcipación comunitaria (Fortalecimiento del buen gobierno para el respeto y la garantía de los DDHH) | H94: 1000 | I94: 13.1 | J94: Participación comunitaria con acciones y resultados | K94: 13.1.1 | L94: Incrementar al 90% de la capacidad organizativa y participativa de las Juntas de Acción Comunal en el municipio mediante la ejecución de las acciones establecidas en Participación Comunitaria | M94: Porcentaje de capacidad organizativa y participativa de JAC incrementada | N94: 0.7 | O94: 4502022 | P94: 2024257990012 | Q94: Fortalecimiento a la infraestructura, a la accion y participacion comunitaria en el municipio de Tenjo | R94: 93 | S94: Realizar acompañamiento al 100% a las JAC del municipio en asesoría técnica | T94: 1 | U94: Porcentaje | V94: M | W94: proceso realizado | X94: Sec. Gobierno y convivencia ciudadana o quien haga sus veces | Z94: =SUM(AF94:AI94)/4 -> 1 | AA94: =AS94/Z94 -> 0.5 | AB94: =BI94/Z94 -> 0.85 | AE94: =SUMPRODUCT(AA94:AD94, {0.15,0.35,0.35,0.15}) -> 0.3725 | AF94: 1 | AG94: 1 | AH94: 1 | AI94: 1 | AN94: 0.7 | AO94: 0.7 | AP94: 0.3 | AQ94: 0.3 | AR94: =(AJ94+AL94+AN94+AP94)/2 -> 0.5 | AS94: =(AK94+AM94+AO94+AQ94)/2 -> 0.5 | AT94: =AS94/AR94 -> 1 | AU94: =MIN((AR94 /AR94) * 100, 100) & "%" -> 100% | AV94: =IF(AR94=0, 0, AS94/AR94) -> 1 | AW94: P | AX94: Meta 93.docx | AY94: 0.25 | AZ94: 0.25 | BA94: 0.25 | BB94: 0.25 | BC94: 0.35 | BD94: 0.35 | BE94: 0.15 | BG94: =(AY94+BA94+BC94+BE94) -> 1 | BH94: =(AZ94+BB94+BD94+BF94) -> 0.85 | BI94: =BH94/BG94 -> 0.85 | BJ94: =MIN((BG94 /BG94) * 100, 100) & "%" -> 100% | BK94: =IF(BG94=0, 0, BH94/BG94) -> 0.85 | BL94: P | BM94: Meta 93.docx | BN94: 25000000 | BO94: 25000000 | BP94: 17920000 | BQ94: 17920000 | BR94: =+BN94+BP94 -> 42920000 | BS94: =+BO94+BQ94 -> 42920000 | BT94: =IFERROR(BS94/BR94, "") -> 1 | BU94: 25000000 | BV94: 25000000 | BW94: 25000000 | BX94: 12820000 | BY94: =IFERROR(BW94/BV94, "") -> 1 | BZ94: 50000000 | CA94: 51000000 | CB94: 52020000 | CC94: 53580600 | CD94: 206600600
